Workbook

Sheet Instructions
A1: StepCat Workbook Instructions — v252
A2: Use this sheet as the reference for entering records, carrying totals forward, and understanding calculations.
A3: Start here | B3: Enter or paste each new record in a prepared Game Records row beginning with A5. In Microsoft Excel, a forgotten game may also be added directly above or below an existing game by choosing Insert Table Rows Above/Below inside the Game Records table. Paste while the column-A cell is selected, not while a text cursor is editing inside the cell.
A4: Editable columns | B4: Use columns A–M for record information. Columns N–Z contain formulas and update automatically in prepared rows and in Excel table rows inserted inside Game Records.
A5: Calculation fields | B5: Use the fields that apply to the selected Estimate or Finalized mode. Estimate records are projections only; their accounting columns remain N/A and cash totals do not change until the same row is Finalized. Other fields may remain blank when they do not apply.
A6: Yellow input cells | B6: All A:M input cells are yellow because they are editable. They remain yellow whether blank or filled.
A7: Record Review | B7: Record Review is formula-driven and should not be edited directly. Enter or revise records only in Game Records A–M. It assigns each non-subscription game a Game # and Game Records ID, shows the calculated result, review flags, and Notes. Prepared rows may remain blank until a matching game exists. Selecting a cell may show its formula in the formula bar; this is normal. Formula text should not appear as the displayed cell value.
A8: Profit rule | B8: Profit means Result Earned is above Entry Fee.
A9: Draw rule | B9: A finalized paid game earning the Entry Fee or less is treated as a Draw with $0.00 net profit. Estimate rows preserve the exact projection but do not post Profit, Draw, Lost, ROI, or Net Profit accounting until finalized.
A10: Loss rule | B10: A monetary loss occurs only when Disqualified / Lost Entry Fee is Yes on a paid entry; the full Entry Fee is counted as lost.
A11: Subscriptions | B11: For the annual platform membership, select “Subscription — membership charge only” and enter the annual cost in Entry Fee. This is a non-game expense and must not be used for a free-entry challenge.
A12: Free games | B12: Select “Free Game — completed challenge/chips” for a completed free-entry challenge or a record that awards chips/game credit. Enter chips in Final Earned / Chips when known. When the estimate inputs are unavailable, Adjusted Pot / Chips and Estimated Earned / Chips display N/A instead of an error or misleading zero.
A13: Summary | B13: Summary uses exact counts and cash totals. Free Games are shown separately from paid-game Profit, Draw, and Disqualified counts, and their chips are reported in a separate non-cash total.
A14: Game Comparisons | B14: The paid table compares Member, Non-Member, Unclassified, and All Paid Games. A separate Free Game Chip Performance section shows completed, disqualified, chips-earned, eliminated-player, and elimination-rate statistics. Subscription rows are excluded.
... A28: Carryover | B28: Enter prior totals once, then continue with only new records.
A29: Prior Net Game Profit | B29: 0
A30: Prior Subscription Costs | B30: 0
A31: Prior Game Count | B31: 0
A32: Step 1 — Note prior totals | B32: Open the completed or archived workbook and note its ending Net Game Profit, subscription costs already paid, and completed-game count.
A33: Step 2 — Enter once | B33: Enter those three figures once in B29:B31. Do not create Game Records rows for the carryover values.
A34: Step 3 — Continue records | B34: Begin new records on Game Records row 5. Enter only activity that occurred after the previous workbook ended.
A35: Step 4 — Check totals | B35: Running totals and Summary should begin with the carryover figures and then add the new workbook's records.
A36: Important | B36: Use Carryover only when continuing from another workbook or starting partway through a year. Prior Game Count includes finalized completed games only; exclude Subscription rows and Estimate rows. Do not re-enter prior games or prior subscription payments.
A38: Calculations | B38: Reference for how the workbook determines results and totals.
A39: Member games | B39: Adjusted Pot uses 100% of Gross Pot.
A40: Non-Member games | B40: Adjusted Pot uses 85% of Gross Pot.
A41: Estimated Earned | B41: Adjusted Pot divided by Eligible Players. This is a projection only. On Estimate rows, Result Earned / Chips, Profit, Draw, Lost Entry Fee, ROI, and Net Profit show N/A; Result shows Estimate; Running Net Profit remains unchanged. When the game ends, replace the same row’s A–M values with the Finalized record—do not add a second row for that game.
A42: Profit | B42: On Finalized rows, Result Earned above Entry Fee is Profit; Net Profit is Result Earned minus Entry Fee. Estimate rows remain outside accounting until finalized.
A44: Draw | B44: A normal completed paid game earning the Entry Fee or less records $0.00 Net Profit while preserving the exact Estimated Earned or Final Earned amount.
A45: Disqualified | B45: Paid entry: Final Earned / Chips and Result Earned / Chips should show $0.00, and the full Entry Fee is recorded as lost. Free Game: the disqualification status is preserved, 0.00 chips are earned, and no monetary Entry Fee loss is recorded.
... A65: v252 release checklist | B65: Regression-test Start New Entry, Finalize This Estimate, remembered choices, changed validation, a complete A–M row paste, Estimate-to-Finalized row replacement, and hosted installation/update behavior.

Sheet Game Records
A1: ="Running Net Game Profit: "&TEXT(Instructions!$B$29+SUM($W$5:$W$504),"$#,##0.00")&" | Gross Profit Earned: "&TEXT(SUM($Q$5:$Q$504),"$#,##0.00")&" | Total Lost Entry Fees: "&TEXT(SUM($S$5:$S$504),"$#,##0.00")&" | StepCat v252"
A2: Rows 5–504 are prepared. Enter or paste only in A:M; N:Z calculate automatically. Estimate rows remain projections: accounting columns show N/A and cash totals do not change until the same row is Finalized. Archive at row 505.
A3: A:M — Inputs only | N3: N:Z — Formula columns — do not edit
A4: Game Name | B4: Start Date | C4: End Date | D4: Entry Mode | E4: Game Type | F4: Payment / Record Type | G4: Gross Pot / Chips | H4: Entry Fee | I4: Eligible Players | J4: Total Players | K4: Final Earned / Chips | L4: Disqualified / Lost Entry Fee | M4: Notes | N4: Adjusted Pot / Chips | O4: Estimated Earned / Chips | P4: Result Earned / Chips | Q4: Profit | R4: Draw | S4: Lost | T4: ROI | U4: Result | V4: Challenge Length (Weeks) | W4: Net Profit | X4: Eliminated Players | Y4: Elimination Rate | Z4: Running Net Profit
N5: =IF(COUNTA($A5:$M5)=0,"",IF(OR(LEFT(LOWER(TRIM($F5&"")),12)="subscription",LOWER(TRIM($F5&""))="membership"),"",IF(OR(AND($H5<>"",$H5=0),LEFT(LOWER(TRIM($F5&"")),9)="free game",LOWER(TRIM($F5&""))="free",LOWER(TRIM($F5&""))="free entry"),IF(ISNUMBER($G5),IF(ISNUMBER(SEARCH("non",LOWER($E5&""))),$G5*0.85,$G5),"N/A"),IF($G5="","",IFERROR(IF(ISNUMBER(SEARCH("non",LOWER($E5&""))),$G5*0.85,$G5),""))))) | O5: =IF(COUNTA($A5:$M5)=0,"",IF(OR(LEFT(LOWER(TRIM($F5&"")),12)="subscription",LOWER(TRIM($F5&""))="membership"),"",IF(OR(AND($H5<>"",$H5=0),LEFT(LOWER(TRIM($F5&"")),9)="free game",LOWER(TRIM($F5&""))="free",LOWER(TRIM($F5&""))="free entry"),IF(OR(NOT(ISNUMBER($N5)),NOT(ISNUMBER($I5)),$I5=0),"N/A",IFERROR($N5/$I5,"N/A")),IF(OR($N5="",$I5="",$I5=0),"",IFERROR($N5/$I5,""))))) | P5: =IF(COUNTA($A5:$M5)=0,"",IF(OR(LEFT(LOWER(TRIM($F5&"")),12)="subscription",LOWER(TRIM($F5&""))="membership"),"",IF(LOWER(TRIM($D5&""))="estimate","N/A",IF(LOWER($L5&"")="yes",0,IF(OR(AND($H5<>"",$H5=0),LEFT(LOWER(TRIM($F5&"")),9)="free game",LOWER(TRIM($F5&""))="free",LOWER(TRIM($F5&""))="free entry"),IF(ISNUMBER($K5),$K5,""),IF($K5<>"",$K5,"")))))) | Q5: =IF(COUNTA($A5:$M5)=0,"",IF(OR($U5="Subscription",$U5=""),"",IF($U5="Estimate","N/A",IF($U5="Profit",ROUND(IFERROR($P5,0)-IFERROR($H5,0),2),0)))) | R5: =IF(COUNTA($A5:$M5)=0,"",IF(OR($U5="Subscription",$U5=""),"",IF($U5="Estimate","N/A",IF($U5="Draw",$H5,0)))) | S5: =IF(COUNTA($A5:$M5)=0,"",IF(OR($U5="Subscription",$U5=""),"",IF($U5="Estimate","N/A",IF($U5="Disqualified",$H5,0)))) | T5: =IF(COUNTA($A5:$M5)=0,"",IF(OR($U5="Subscription",$U5=""),"",IF($U5="Estimate","N/A",IF(OR($U5="Free Game",$U5="Disqualified — Free Game",$H5=0),"N/A",IF($U5="Profit",$Q5/$H5,IF($U5="Disqualified",-$S5/$H5,0)))))) | U5: =IF(COUNTA($A5:$M5)=0,"",IF(OR(LEFT(LOWER(TRIM($F5&"")),12)="subscription",LOWER(TRIM($F5&""))="membership"),"Subscription",IF(LOWER(TRIM($D5&""))="estimate","Estimate",IF(OR(AND($H5<>"",$H5=0),LEFT(LOWER(TRIM($F5&"")),9)="free game",LOWER(TRIM($F5&""))="free",LOWER(TRIM($F5&""))="free entry"),IF(LOWER($L5&"")="yes","Disqualified — Free Game","Free Game"),IF(LOWER($L5&"")="yes","Disqualified",IF($P5="","",IF(ROUND(IFERROR(VALUE($P5),0)-IFERROR(VALUE($H5),0),2)>0,"Profit","Draw"))))))) | V5: =IF(COUNTA($A5:$M5)=0,"",IF(OR($B5="",$C5="",$U5="Subscription"),"",IFERROR(ROUNDUP(($C5-$B5)/7,0),""))) | W5: =IF(COUNTA($A5:$M5)=0,"",IF(OR($U5="Subscription",$U5=""),"",IF($U5="Estimate","N/A",IF(OR($U5="Free Game",$U5="Disqualified — Free Game"),0,ROUND(IFERROR($Q5,0)-IFERROR($S5,0),2))))) | X5: =IF(COUNTA($A5:$M5)=0,"",IF(OR($U5="Subscription",NOT(ISNUMBER($J5)),NOT(ISNUMBER($I5)),$J5=0,$I5=0,$I5>$J5),"",$J5-$I5)) | Y5: =IF(COUNTA($A5:$M5)=0,"",IF(OR($U5="Subscription",NOT(ISNUMBER($J5)),$J5=0,$X5=""),"",$X5/$J5)) | Z5: =IF(COUNTA($A5:$M5)=0,"",Instructions!$B$29+SUM($W$5:W5))
N6: =IF(COUNTA($A6:$M6)=0,"",IF(OR(LEFT(LOWER(TRIM($F6&"")),12)="subscription",LOWER(TRIM($F6&""))="membership"),"",IF(OR(AND($H6<>"",$H6=0),LEFT(LOWER(TRIM($F6&"")),9)="free game",LOWER(TRIM($F6&""))="free",LOWER(TRIM($F6&""))="free entry"),IF(ISNUMBER($G6),IF(ISNUMBER(SEARCH("non",LOWER($E6&""))),$G6*0.85,$G6),"N/A"),IF($G6="","",IFERROR(IF(ISNUMBER(SEARCH("non",LOWER($E6&""))),$G6*0.85,$G6),""))))) | O6: =IF(COUNTA($A6:$M6)=0,"",IF(OR(LEFT(LOWER(TRIM($F6&"")),12)="subscription",LOWER(TRIM($F6&""))="membership"),"",IF(OR(AND($H6<>"",$H6=0),LEFT(LOWER(TRIM($F6&"")),9)="free game",LOWER(TRIM($F6&""))="free",LOWER(TRIM($F6&""))="free entry"),IF(OR(NOT(ISNUMBER($N6)),NOT(ISNUMBER($I6)),$I6=0),"N/A",IFERROR($N6/$I6,"N/A")),IF(OR($N6="",$I6="",$I6=0),"",IFERROR($N6/$I6,""))))) | P6: =IF(COUNTA($A6:$M6)=0,"",IF(OR(LEFT(LOWER(TRIM($F6&"")),12)="subscription",LOWER(TRIM($F6&""))="membership"),"",IF(LOWER(TRIM($D6&""))="estimate","N/A",IF(LOWER($L6&"")="yes",0,IF(OR(AND($H6<>"",$H6=0),LEFT(LOWER(TRIM($F6&"")),9)="free game",LOWER(TRIM($F6&""))="free",LOWER(TRIM($F6&""))="free entry"),IF(ISNUMBER($K6),$K6,""),IF($K6<>"",$K6,"")))))) | Q6: =IF(COUNTA($A6:$M6)=0,"",IF(OR($U6="Subscription",$U6=""),"",IF($U6="Estimate","N/A",IF($U6="Profit",ROUND(IFERROR($P6,0)-IFERROR($H6,0),2),0)))) | R6: =IF(COUNTA($A6:$M6)=0,"",IF(OR($U6="Subscription",$U6=""),"",IF($U6="Estimate","N/A",IF($U6="Draw",$H6,0)))) | S6: =IF(COUNTA($A6:$M6)=0,"",IF(OR($U6="Subscription",$U6=""),"",IF($U6="Estimate","N/A",IF($U6="Disqualified",$H6,0)))) | T6: =IF(COUNTA($A6:$M6)=0,"",IF(OR($U6="Subscription",$U6=""),"",IF($U6="Estimate","N/A",IF(OR($U6="Free Game",$U6="Disqualified — Free Game",$H6=0),"N/A",IF($U6="Profit",$Q6/$H6,IF($U6="Disqualified",-$S6/$H6,0)))))) | U6: =IF(COUNTA($A6:$M6)=0,"",IF(OR(LEFT(LOWER(TRIM($F6&"")),12)="subscription",LOWER(TRIM($F6&""))="membership"),"Subscription",IF(LOWER(TRIM($D6&""))="estimate","Estimate",IF(OR(AND($H6<>"",$H6=0),LEFT(LOWER(TRIM($F6&"")),9)="free game",LOWER(TRIM($F6&""))="free",LOWER(TRIM($F6&""))="free entry"),IF(LOWER($L6&"")="yes","Disqualified — Free Game","Free Game"),IF(LOWER($L6&"")="yes","Disqualified",IF($P6="","",IF(ROUND(IFERROR(VALUE($P6),0)-IFERROR(VALUE($H6),0),2)>0,"Profit","Draw"))))))) | V6: =IF(COUNTA($A6:$M6)=0,"",IF(OR($B6="",$C6="",$U6="Subscription"),"",IFERROR(ROUNDUP(($C6-$B6)/7,0),""))) | W6: =IF(COUNTA($A6:$M6)=0,"",IF(OR($U6="Subscription",$U6=""),"",IF($U6="Estimate","N/A",IF(OR($U6="Free Game",$U6="Disqualified — Free Game"),0,ROUND(IFERROR($Q6,0)-IFERROR($S6,0),2))))) | X6: =IF(COUNTA($A6:$M6)=0,"",IF(OR($U6="Subscription",NOT(ISNUMBER($J6)),NOT(ISNUMBER($I6)),$J6=0,$I6=0,$I6>$J6),"",$J6-$I6)) | Y6: =IF(COUNTA($A6:$M6)=0,"",IF(OR($U6="Subscription",NOT(ISNUMBER($J6)),$J6=0,$X6=""),"",$X6/$J6)) | Z6: =IF(COUNTA($A6:$M6)=0,"",Instructions!$B$29+SUM($W$5:W6))
N7: =IF(COUNTA($A7:$M7)=0,"",IF(OR(LEFT(LOWER(TRIM($F7&"")),12)="subscription",LOWER(TRIM($F7&""))="membership"),"",IF(OR(AND($H7<>"",$H7=0),LEFT(LOWER(TRIM($F7&"")),9)="free game",LOWER(TRIM($F7&""))="free",LOWER(TRIM($F7&""))="free entry"),IF(ISNUMBER($G7),IF(ISNUMBER(SEARCH("non",LOWER($E7&""))),$G7*0.85,$G7),"N/A"),IF($G7="","",IFERROR(IF(ISNUMBER(SEARCH("non",LOWER($E7&""))),$G7*0.85,$G7),""))))) | O7: =IF(COUNTA($A7:$M7)=0,"",IF(OR(LEFT(LOWER(TRIM($F7&"")),12)="subscription",LOWER(TRIM($F7&""))="membership"),"",IF(OR(AND($H7<>"",$H7=0),LEFT(LOWER(TRIM($F7&"")),9)="free game",LOWER(TRIM($F7&""))="free",LOWER(TRIM($F7&""))="free entry"),IF(OR(NOT(ISNUMBER($N7)),NOT(ISNUMBER($I7)),$I7=0),"N/A",IFERROR($N7/$I7,"N/A")),IF(OR($N7="",$I7="",$I7=0),"",IFERROR($N7/$I7,""))))) | P7: =IF(COUNTA($A7:$M7)=0,"",IF(OR(LEFT(LOWER(TRIM($F7&"")),12)="subscription",LOWER(TRIM($F7&""))="membership"),"",IF(LOWER(TRIM($D7&""))="estimate","N/A",IF(LOWER($L7&"")="yes",0,IF(OR(AND($H7<>"",$H7=0),LEFT(LOWER(TRIM($F7&"")),9)="free game",LOWER(TRIM($F7&""))="free",LOWER(TRIM($F7&""))="free entry"),IF(ISNUMBER($K7),$K7,""),IF($K7<>"",$K7,"")))))) | Q7: =IF(COUNTA($A7:$M7)=0,"",IF(OR($U7="Subscription",$U7=""),"",IF($U7="Estimate","N/A",IF($U7="Profit",ROUND(IFERROR($P7,0)-IFERROR($H7,0),2),0)))) | R7: =IF(COUNTA($A7:$M7)=0,"",IF(OR($U7="Subscription",$U7=""),"",IF($U7="Estimate","N/A",IF($U7="Draw",$H7,0)))) | S7: =IF(COUNTA($A7:$M7)=0,"",IF(OR($U7="Subscription",$U7=""),"",IF($U7="Estimate","N/A",IF($U7="Disqualified",$H7,0)))) | T7: =IF(COUNTA($A7:$M7)=0,"",IF(OR($U7="Subscription",$U7=""),"",IF($U7="Estimate","N/A",IF(OR($U7="Free Game",$U7="Disqualified — Free Game",$H7=0),"N/A",IF($U7="Profit",$Q7/$H7,IF($U7="Disqualified",-$S7/$H7,0)))))) | U7: =IF(COUNTA($A7:$M7)=0,"",IF(OR(LEFT(LOWER(TRIM($F7&"")),12)="subscription",LOWER(TRIM($F7&""))="membership"),"Subscription",IF(LOWER(TRIM($D7&""))="estimate","Estimate",IF(OR(AND($H7<>"",$H7=0),LEFT(LOWER(TRIM($F7&"")),9)="free game",LOWER(TRIM($F7&""))="free",LOWER(TRIM($F7&""))="free entry"),IF(LOWER($L7&"")="yes","Disqualified — Free Game","Free Game"),IF(LOWER($L7&"")="yes","Disqualified",IF($P7="","",IF(ROUND(IFERROR(VALUE($P7),0)-IFERROR(VALUE($H7),0),2)>0,"Profit","Draw"))))))) | V7: =IF(COUNTA($A7:$M7)=0,"",IF(OR($B7="",$C7="",$U7="Subscription"),"",IFERROR(ROUNDUP(($C7-$B7)/7,0),""))) | W7: =IF(COUNTA($A7:$M7)=0,"",IF(OR($U7="Subscription",$U7=""),"",IF($U7="Estimate","N/A",IF(OR($U7="Free Game",$U7="Disqualified — Free Game"),0,ROUND(IFERROR($Q7,0)-IFERROR($S7,0),2))))) | X7: =IF(COUNTA($A7:$M7)=0,"",IF(OR($U7="Subscription",NOT(ISNUMBER($J7)),NOT(ISNUMBER($I7)),$J7=0,$I7=0,$I7>$J7),"",$J7-$I7)) | Y7: =IF(COUNTA($A7:$M7)=0,"",IF(OR($U7="Subscription",NOT(ISNUMBER($J7)),$J7=0,$X7=""),"",$X7/$J7)) | Z7: =IF(COUNTA($A7:$M7)=0,"",Instructions!$B$29+SUM($W$5:W7))
N8: =IF(COUNTA($A8:$M8)=0,"",IF(OR(LEFT(LOWER(TRIM($F8&"")),12)="subscription",LOWER(TRIM($F8&""))="membership"),"",IF(OR(AND($H8<>"",$H8=0),LEFT(LOWER(TRIM($F8&"")),9)="free game",LOWER(TRIM($F8&""))="free",LOWER(TRIM($F8&""))="free entry"),IF(ISNUMBER($G8),IF(ISNUMBER(SEARCH("non",LOWER($E8&""))),$G8*0.85,$G8),"N/A"),IF($G8="","",IFERROR(IF(ISNUMBER(SEARCH("non",LOWER($E8&""))),$G8*0.85,$G8),""))))) | O8: =IF(COUNTA($A8:$M8)=0,"",IF(OR(LEFT(LOWER(TRIM($F8&"")),12)="subscription",LOWER(TRIM($F8&""))="membership"),"",IF(OR(AND($H8<>"",$H8=0),LEFT(LOWER(TRIM($F8&"")),9)="free game",LOWER(TRIM($F8&""))="free",LOWER(TRIM($F8&""))="free entry"),IF(OR(NOT(ISNUMBER($N8)),NOT(ISNUMBER($I8)),$I8=0),"N/A",IFERROR($N8/$I8,"N/A")),IF(OR($N8="",$I8="",$I8=0),"",IFERROR($N8/$I8,""))))) | P8: =IF(COUNTA($A8:$M8)=0,"",IF(OR(LEFT(LOWER(TRIM($F8&"")),12)="subscription",LOWER(TRIM($F8&""))="membership"),"",IF(LOWER(TRIM($D8&""))="estimate","N/A",IF(LOWER($L8&"")="yes",0,IF(OR(AND($H8<>"",$H8=0),LEFT(LOWER(TRIM($F8&"")),9)="free game",LOWER(TRIM($F8&""))="free",LOWER(TRIM($F8&""))="free entry"),IF(ISNUMBER($K8),$K8,""),IF($K8<>"",$K8,"")))))) | Q8: =IF(COUNTA($A8:$M8)=0,"",IF(OR($U8="Subscription",$U8=""),"",IF($U8="Estimate","N/A",IF($U8="Profit",ROUND(IFERROR($P8,0)-IFERROR($H8,0),2),0)))) | R8: =IF(COUNTA($A8:$M8)=0,"",IF(OR($U8="Subscription",$U8=""),"",IF($U8="Estimate","N/A",IF($U8="Draw",$H8,0)))) | S8: =IF(COUNTA($A8:$M8)=0,"",IF(OR($U8="Subscription",$U8=""),"",IF($U8="Estimate","N/A",IF($U8="Disqualified",$H8,0)))) | T8: =IF(COUNTA($A8:$M8)=0,"",IF(OR($U8="Subscription",$U8=""),"",IF($U8="Estimate","N/A",IF(OR($U8="Free Game",$U8="Disqualified — Free Game",$H8=0),"N/A",IF($U8="Profit",$Q8/$H8,IF($U8="Disqualified",-$S8/$H8,0)))))) | U8: =IF(COUNTA($A8:$M8)=0,"",IF(OR(LEFT(LOWER(TRIM($F8&"")),12)="subscription",LOWER(TRIM($F8&""))="membership"),"Subscription",IF(LOWER(TRIM($D8&""))="estimate","Estimate",IF(OR(AND($H8<>"",$H8=0),LEFT(LOWER(TRIM($F8&"")),9)="free game",LOWER(TRIM($F8&""))="free",LOWER(TRIM($F8&""))="free entry"),IF(LOWER($L8&"")="yes","Disqualified — Free Game","Free Game"),IF(LOWER($L8&"")="yes","Disqualified",IF($P8="","",IF(ROUND(IFERROR(VALUE($P8),0)-IFERROR(VALUE($H8),0),2)>0,"Profit","Draw"))))))) | V8: =IF(COUNTA($A8:$M8)=0,"",IF(OR($B8="",$C8="",$U8="Subscription"),"",IFERROR(ROUNDUP(($C8-$B8)/7,0),""))) | W8: =IF(COUNTA($A8:$M8)=0,"",IF(OR($U8="Subscription",$U8=""),"",IF($U8="Estimate","N/A",IF(OR($U8="Free Game",$U8="Disqualified — Free Game"),0,ROUND(IFERROR($Q8,0)-IFERROR($S8,0),2))))) | X8: =IF(COUNTA($A8:$M8)=0,"",IF(OR($U8="Subscription",NOT(ISNUMBER($J8)),NOT(ISNUMBER($I8)),$J8=0,$I8=0,$I8>$J8),"",$J8-$I8)) | Y8: =IF(COUNTA($A8:$M8)=0,"",IF(OR($U8="Subscription",NOT(ISNUMBER($J8)),$J8=0,$X8=""),"",$X8/$J8)) | Z8: =IF(COUNTA($A8:$M8)=0,"",Instructions!$B$29+SUM($W$5:W8))
N9: =IF(COUNTA($A9:$M9)=0,"",IF(OR(LEFT(LOWER(TRIM($F9&"")),12)="subscription",LOWER(TRIM($F9&""))="membership"),"",IF(OR(AND($H9<>"",$H9=0),LEFT(LOWER(TRIM($F9&"")),9)="free game",LOWER(TRIM($F9&""))="free",LOWER(TRIM($F9&""))="free entry"),IF(ISNUMBER($G9),IF(ISNUMBER(SEARCH("non",LOWER($E9&""))),$G9*0.85,$G9),"N/A"),IF($G9="","",IFERROR(IF(ISNUMBER(SEARCH("non",LOWER($E9&""))),$G9*0.85,$G9),""))))) | O9: =IF(COUNTA($A9:$M9)=0,"",IF(OR(LEFT(LOWER(TRIM($F9&"")),12)="subscription",LOWER(TRIM($F9&""))="membership"),"",IF(OR(AND($H9<>"",$H9=0),LEFT(LOWER(TRIM($F9&"")),9)="free game",LOWER(TRIM($F9&""))="free",LOWER(TRIM($F9&""))="free entry"),IF(OR(NOT(ISNUMBER($N9)),NOT(ISNUMBER($I9)),$I9=0),"N/A",IFERROR($N9/$I9,"N/A")),IF(OR($N9="",$I9="",$I9=0),"",IFERROR($N9/$I9,""))))) | P9: =IF(COUNTA($A9:$M9)=0,"",IF(OR(LEFT(LOWER(TRIM($F9&"")),12)="subscription",LOWER(TRIM($F9&""))="membership"),"",IF(LOWER(TRIM($D9&""))="estimate","N/A",IF(LOWER($L9&"")="yes",0,IF(OR(AND($H9<>"",$H9=0),LEFT(LOWER(TRIM($F9&"")),9)="free game",LOWER(TRIM($F9&""))="free",LOWER(TRIM($F9&""))="free entry"),IF(ISNUMBER($K9),$K9,""),IF($K9<>"",$K9,"")))))) | Q9: =IF(COUNTA($A9:$M9)=0,"",IF(OR($U9="Subscription",$U9=""),"",IF($U9="Estimate","N/A",IF($U9="Profit",ROUND(IFERROR($P9,0)-IFERROR($H9,0),2),0)))) | R9: =IF(COUNTA($A9:$M9)=0,"",IF(OR($U9="Subscription",$U9=""),"",IF($U9="Estimate","N/A",IF($U9="Draw",$H9,0)))) | S9: =IF(COUNTA($A9:$M9)=0,"",IF(OR($U9="Subscription",$U9=""),"",IF($U9="Estimate","N/A",IF($U9="Disqualified",$H9,0)))) | T9: =IF(COUNTA($A9:$M9)=0,"",IF(OR($U9="Subscription",$U9=""),"",IF($U9="Estimate","N/A",IF(OR($U9="Free Game",$U9="Disqualified — Free Game",$H9=0),"N/A",IF($U9="Profit",$Q9/$H9,IF($U9="Disqualified",-$S9/$H9,0)))))) | U9: =IF(COUNTA($A9:$M9)=0,"",IF(OR(LEFT(LOWER(TRIM($F9&"")),12)="subscription",LOWER(TRIM($F9&""))="membership"),"Subscription",IF(LOWER(TRIM($D9&""))="estimate","Estimate",IF(OR(AND($H9<>"",$H9=0),LEFT(LOWER(TRIM($F9&"")),9)="free game",LOWER(TRIM($F9&""))="free",LOWER(TRIM($F9&""))="free entry"),IF(LOWER($L9&"")="yes","Disqualified — Free Game","Free Game"),IF(LOWER($L9&"")="yes","Disqualified",IF($P9="","",IF(ROUND(IFERROR(VALUE($P9),0)-IFERROR(VALUE($H9),0),2)>0,"Profit","Draw"))))))) | V9: =IF(COUNTA($A9:$M9)=0,"",IF(OR($B9="",$C9="",$U9="Subscription"),"",IFERROR(ROUNDUP(($C9-$B9)/7,0),""))) | W9: =IF(COUNTA($A9:$M9)=0,"",IF(OR($U9="Subscription",$U9=""),"",IF($U9="Estimate","N/A",IF(OR($U9="Free Game",$U9="Disqualified — Free Game"),0,ROUND(IFERROR($Q9,0)-IFERROR($S9,0),2))))) | X9: =IF(COUNTA($A9:$M9)=0,"",IF(OR($U9="Subscription",NOT(ISNUMBER($J9)),NOT(ISNUMBER($I9)),$J9=0,$I9=0,$I9>$J9),"",$J9-$I9)) | Y9: =IF(COUNTA($A9:$M9)=0,"",IF(OR($U9="Subscription",NOT(ISNUMBER($J9)),$J9=0,$X9=""),"",$X9/$J9)) | Z9: =IF(COUNTA($A9:$M9)=0,"",Instructions!$B$29+SUM($W$5:W9))
N10: =IF(COUNTA($A10:$M10)=0,"",IF(OR(LEFT(LOWER(TRIM($F10&"")),12)="subscription",LOWER(TRIM($F10&""))="membership"),"",IF(OR(AND($H10<>"",$H10=0),LEFT(LOWER(TRIM($F10&"")),9)="free game",LOWER(TRIM($F10&""))="free",LOWER(TRIM($F10&""))="free entry"),IF(ISNUMBER($G10),IF(ISNUMBER(SEARCH("non",LOWER($E10&""))),$G10*0.85,$G10),"N/A"),IF($G10="","",IFERROR(IF(ISNUMBER(SEARCH("non",LOWER($E10&""))),$G10*0.85,$G10),""))))) | O10: =IF(COUNTA($A10:$M10)=0,"",IF(OR(LEFT(LOWER(TRIM($F10&"")),12)="subscription",LOWER(TRIM($F10&""))="membership"),"",IF(OR(AND($H10<>"",$H10=0),LEFT(LOWER(TRIM($F10&"")),9)="free game",LOWER(TRIM($F10&""))="free",LOWER(TRIM($F10&""))="free entry"),IF(OR(NOT(ISNUMBER($N10)),NOT(ISNUMBER($I10)),$I10=0),"N/A",IFERROR($N10/$I10,"N/A")),IF(OR($N10="",$I10="",$I10=0),"",IFERROR($N10/$I10,""))))) | P10: =IF(COUNTA($A10:$M10)=0,"",IF(OR(LEFT(LOWER(TRIM($F10&"")),12)="subscription",LOWER(TRIM($F10&""))="membership"),"",IF(LOWER(TRIM($D10&""))="estimate","N/A",IF(LOWER($L10&"")="yes",0,IF(OR(AND($H10<>"",$H10=0),LEFT(LOWER(TRIM($F10&"")),9)="free game",LOWER(TRIM($F10&""))="free",LOWER(TRIM($F10&""))="free entry"),IF(ISNUMBER($K10),$K10,""),IF($K10<>"",$K10,"")))))) | Q10: =IF(COUNTA($A10:$M10)=0,"",IF(OR($U10="Subscription",$U10=""),"",IF($U10="Estimate","N/A",IF($U10="Profit",ROUND(IFERROR($P10,0)-IFERROR($H10,0),2),0)))) | R10: =IF(COUNTA($A10:$M10)=0,"",IF(OR($U10="Subscription",$U10=""),"",IF($U10="Estimate","N/A",IF($U10="Draw",$H10,0)))) | S10: =IF(COUNTA($A10:$M10)=0,"",IF(OR($U10="Subscription",$U10=""),"",IF($U10="Estimate","N/A",IF($U10="Disqualified",$H10,0)))) | T10: =IF(COUNTA($A10:$M10)=0,"",IF(OR($U10="Subscription",$U10=""),"",IF($U10="Estimate","N/A",IF(OR($U10="Free Game",$U10="Disqualified — Free Game",$H10=0),"N/A",IF($U10="Profit",$Q10/$H10,IF($U10="Disqualified",-$S10/$H10,0)))))) | U10: =IF(COUNTA($A10:$M10)=0,"",IF(OR(LEFT(LOWER(TRIM($F10&"")),12)="subscription",LOWER(TRIM($F10&""))="membership"),"Subscription",IF(LOWER(TRIM($D10&""))="estimate","Estimate",IF(OR(AND($H10<>"",$H10=0),LEFT(LOWER(TRIM($F10&"")),9)="free game",LOWER(TRIM($F10&""))="free",LOWER(TRIM($F10&""))="free entry"),IF(LOWER($L10&"")="yes","Disqualified — Free Game","Free Game"),IF(LOWER($L10&"")="yes","Disqualified",IF($P10="","",IF(ROUND(IFERROR(VALUE($P10),0)-IFERROR(VALUE($H10),0),2)>0,"Profit","Draw"))))))) | V10: =IF(COUNTA($A10:$M10)=0,"",IF(OR($B10="",$C10="",$U10="Subscription"),"",IFERROR(ROUNDUP(($C10-$B10)/7,0),""))) | W10: =IF(COUNTA($A10:$M10)=0,"",IF(OR($U10="Subscription",$U10=""),"",IF($U10="Estimate","N/A",IF(OR($U10="Free Game",$U10="Disqualified — Free Game"),0,ROUND(IFERROR($Q10,0)-IFERROR($S10,0),2))))) | X10: =IF(COUNTA($A10:$M10)=0,"",IF(OR($U10="Subscription",NOT(ISNUMBER($J10)),NOT(ISNUMBER($I10)),$J10=0,$I10=0,$I10>$J10),"",$J10-$I10)) | Y10: =IF(COUNTA($A10:$M10)=0,"",IF(OR($U10="Subscription",NOT(ISNUMBER($J10)),$J10=0,$X10=""),"",$X10/$J10)) | Z10: =IF(COUNTA($A10:$M10)=0,"",Instructions!$B$29+SUM($W$5:W10))
N11: =IF(COUNTA($A11:$M11)=0,"",IF(OR(LEFT(LOWER(TRIM($F11&"")),12)="subscription",LOWER(TRIM($F11&""))="membership"),"",IF(OR(AND($H11<>"",$H11=0),LEFT(LOWER(TRIM($F11&"")),9)="free game",LOWER(TRIM($F11&""))="free",LOWER(TRIM($F11&""))="free entry"),IF(ISNUMBER($G11),IF(ISNUMBER(SEARCH("non",LOWER($E11&""))),$G11*0.85,$G11),"N/A"),IF($G11="","",IFERROR(IF(ISNUMBER(SEARCH("non",LOWER($E11&""))),$G11*0.85,$G11),""))))) | O11: =IF(COUNTA($A11:$M11)=0,"",IF(OR(LEFT(LOWER(TRIM($F11&"")),12)="subscription",LOWER(TRIM($F11&""))="membership"),"",IF(OR(AND($H11<>"",$H11=0),LEFT(LOWER(TRIM($F11&"")),9)="free game",LOWER(TRIM($F11&""))="free",LOWER(TRIM($F11&""))="free entry"),IF(OR(NOT(ISNUMBER($N11)),NOT(ISNUMBER($I11)),$I11=0),"N/A",IFERROR($N11/$I11,"N/A")),IF(OR($N11="",$I11="",$I11=0),"",IFERROR($N11/$I11,""))))) | P11: =IF(COUNTA($A11:$M11)=0,"",IF(OR(LEFT(LOWER(TRIM($F11&"")),12)="subscription",LOWER(TRIM($F11&""))="membership"),"",IF(LOWER(TRIM($D11&""))="estimate","N/A",IF(LOWER($L11&"")="yes",0,IF(OR(AND($H11<>"",$H11=0),LEFT(LOWER(TRIM($F11&"")),9)="free game",LOWER(TRIM($F11&""))="free",LOWER(TRIM($F11&""))="free entry"),IF(ISNUMBER($K11),$K11,""),IF($K11<>"",$K11,"")))))) | Q11: =IF(COUNTA($A11:$M11)=0,"",IF(OR($U11="Subscription",$U11=""),"",IF($U11="Estimate","N/A",IF($U11="Profit",ROUND(IFERROR($P11,0)-IFERROR($H11,0),2),0)))) | R11: =IF(COUNTA($A11:$M11)=0,"",IF(OR($U11="Subscription",$U11=""),"",IF($U11="Estimate","N/A",IF($U11="Draw",$H11,0)))) | S11: =IF(COUNTA($A11:$M11)=0,"",IF(OR($U11="Subscription",$U11=""),"",IF($U11="Estimate","N/A",IF($U11="Disqualified",$H11,0)))) | T11: =IF(COUNTA($A11:$M11)=0,"",IF(OR($U11="Subscription",$U11=""),"",IF($U11="Estimate","N/A",IF(OR($U11="Free Game",$U11="Disqualified — Free Game",$H11=0),"N/A",IF($U11="Profit",$Q11/$H11,IF($U11="Disqualified",-$S11/$H11,0)))))) | U11: =IF(COUNTA($A11:$M11)=0,"",IF(OR(LEFT(LOWER(TRIM($F11&"")),12)="subscription",LOWER(TRIM($F11&""))="membership"),"Subscription",IF(LOWER(TRIM($D11&""))="estimate","Estimate",IF(OR(AND($H11<>"",$H11=0),LEFT(LOWER(TRIM($F11&"")),9)="free game",LOWER(TRIM($F11&""))="free",LOWER(TRIM($F11&""))="free entry"),IF(LOWER($L11&"")="yes","Disqualified — Free Game","Free Game"),IF(LOWER($L11&"")="yes","Disqualified",IF($P11="","",IF(ROUND(IFERROR(VALUE($P11),0)-IFERROR(VALUE($H11),0),2)>0,"Profit","Draw"))))))) | V11: =IF(COUNTA($A11:$M11)=0,"",IF(OR($B11="",$C11="",$U11="Subscription"),"",IFERROR(ROUNDUP(($C11-$B11)/7,0),""))) | W11: =IF(COUNTA($A11:$M11)=0,"",IF(OR($U11="Subscription",$U11=""),"",IF($U11="Estimate","N/A",IF(OR($U11="Free Game",$U11="Disqualified — Free Game"),0,ROUND(IFERROR($Q11,0)-IFERROR($S11,0),2))))) | X11: =IF(COUNTA($A11:$M11)=0,"",IF(OR($U11="Subscription",NOT(ISNUMBER($J11)),NOT(ISNUMBER($I11)),$J11=0,$I11=0,$I11>$J11),"",$J11-$I11)) | Y11: =IF(COUNTA($A11:$M11)=0,"",IF(OR($U11="Subscription",NOT(ISNUMBER($J11)),$J11=0,$X11=""),"",$X11/$J11)) | Z11: =IF(COUNTA($A11:$M11)=0,"",Instructions!$B$29+SUM($W$5:W11))
N12: =IF(COUNTA($A12:$M12)=0,"",IF(OR(LEFT(LOWER(TRIM($F12&"")),12)="subscription",LOWER(TRIM($F12&""))="membership"),"",IF(OR(AND($H12<>"",$H12=0),LEFT(LOWER(TRIM($F12&"")),9)="free game",LOWER(TRIM($F12&""))="free",LOWER(TRIM($F12&""))="free entry"),IF(ISNUMBER($G12),IF(ISNUMBER(SEARCH("non",LOWER($E12&""))),$G12*0.85,$G12),"N/A"),IF($G12="","",IFERROR(IF(ISNUMBER(SEARCH("non",LOWER($E12&""))),$G12*0.85,$G12),""))))) | O12: =IF(COUNTA($A12:$M12)=0,"",IF(OR(LEFT(LOWER(TRIM($F12&"")),12)="subscription",LOWER(TRIM($F12&""))="membership"),"",IF(OR(AND($H12<>"",$H12=0),LEFT(LOWER(TRIM($F12&"")),9)="free game",LOWER(TRIM($F12&""))="free",LOWER(TRIM($F12&""))="free entry"),IF(OR(NOT(ISNUMBER($N12)),NOT(ISNUMBER($I12)),$I12=0),"N/A",IFERROR($N12/$I12,"N/A")),IF(OR($N12="",$I12="",$I12=0),"",IFERROR($N12/$I12,""))))) | P12: =IF(COUNTA($A12:$M12)=0,"",IF(OR(LEFT(LOWER(TRIM($F12&"")),12)="subscription",LOWER(TRIM($F12&""))="membership"),"",IF(LOWER(TRIM($D12&""))="estimate","N/A",IF(LOWER($L12&"")="yes",0,IF(OR(AND($H12<>"",$H12=0),LEFT(LOWER(TRIM($F12&"")),9)="free game",LOWER(TRIM($F12&""))="free",LOWER(TRIM($F12&""))="free entry"),IF(ISNUMBER($K12),$K12,""),IF($K12<>"",$K12,"")))))) | Q12: =IF(COUNTA($A12:$M12)=0,"",IF(OR($U12="Subscription",$U12=""),"",IF($U12="Estimate","N/A",IF($U12="Profit",ROUND(IFERROR($P12,0)-IFERROR($H12,0),2),0)))) | R12: =IF(COUNTA($A12:$M12)=0,"",IF(OR($U12="Subscription",$U12=""),"",IF($U12="Estimate","N/A",IF($U12="Draw",$H12,0)))) | S12: =IF(COUNTA($A12:$M12)=0,"",IF(OR($U12="Subscription",$U12=""),"",IF($U12="Estimate","N/A",IF($U12="Disqualified",$H12,0)))) | T12: =IF(COUNTA($A12:$M12)=0,"",IF(OR($U12="Subscription",$U12=""),"",IF($U12="Estimate","N/A",IF(OR($U12="Free Game",$U12="Disqualified — Free Game",$H12=0),"N/A",IF($U12="Profit",$Q12/$H12,IF($U12="Disqualified",-$S12/$H12,0)))))) | U12: =IF(COUNTA($A12:$M12)=0,"",IF(OR(LEFT(LOWER(TRIM($F12&"")),12)="subscription",LOWER(TRIM($F12&""))="membership"),"Subscription",IF(LOWER(TRIM($D12&""))="estimate","Estimate",IF(OR(AND($H12<>"",$H12=0),LEFT(LOWER(TRIM($F12&"")),9)="free game",LOWER(TRIM($F12&""))="free",LOWER(TRIM($F12&""))="free entry"),IF(LOWER($L12&"")="yes","Disqualified — Free Game","Free Game"),IF(LOWER($L12&"")="yes","Disqualified",IF($P12="","",IF(ROUND(IFERROR(VALUE($P12),0)-IFERROR(VALUE($H12),0),2)>0,"Profit","Draw"))))))) | V12: =IF(COUNTA($A12:$M12)=0,"",IF(OR($B12="",$C12="",$U12="Subscription"),"",IFERROR(ROUNDUP(($C12-$B12)/7,0),""))) | W12: =IF(COUNTA($A12:$M12)=0,"",IF(OR($U12="Subscription",$U12=""),"",IF($U12="Estimate","N/A",IF(OR($U12="Free Game",$U12="Disqualified — Free Game"),0,ROUND(IFERROR($Q12,0)-IFERROR($S12,0),2))))) | X12: =IF(COUNTA($A12:$M12)=0,"",IF(OR($U12="Subscription",NOT(ISNUMBER($J12)),NOT(ISNUMBER($I12)),$J12=0,$I12=0,$I12>$J12),"",$J12-$I12)) | Y12: =IF(COUNTA($A12:$M12)=0,"",IF(OR($U12="Subscription",NOT(ISNUMBER($J12)),$J12=0,$X12=""),"",$X12/$J12)) | Z12: =IF(COUNTA($A12:$M12)=0,"",Instructions!$B$29+SUM($W$5:W12))
N13: =IF(COUNTA($A13:$M13)=0,"",IF(OR(LEFT(LOWER(TRIM($F13&"")),12)="subscription",LOWER(TRIM($F13&""))="membership"),"",IF(OR(AND($H13<>"",$H13=0),LEFT(LOWER(TRIM($F13&"")),9)="free game",LOWER(TRIM($F13&""))="free",LOWER(TRIM($F13&""))="free entry"),IF(ISNUMBER($G13),IF(ISNUMBER(SEARCH("non",LOWER($E13&""))),$G13*0.85,$G13),"N/A"),IF($G13="","",IFERROR(IF(ISNUMBER(SEARCH("non",LOWER($E13&""))),$G13*0.85,$G13),""))))) | O13: =IF(COUNTA($A13:$M13)=0,"",IF(OR(LEFT(LOWER(TRIM($F13&"")),12)="subscription",LOWER(TRIM($F13&""))="membership"),"",IF(OR(AND($H13<>"",$H13=0),LEFT(LOWER(TRIM($F13&"")),9)="free game",LOWER(TRIM($F13&""))="free",LOWER(TRIM($F13&""))="free entry"),IF(OR(NOT(ISNUMBER($N13)),NOT(ISNUMBER($I13)),$I13=0),"N/A",IFERROR($N13/$I13,"N/A")),IF(OR($N13="",$I13="",$I13=0),"",IFERROR($N13/$I13,""))))) | P13: =IF(COUNTA($A13:$M13)=0,"",IF(OR(LEFT(LOWER(TRIM($F13&"")),12)="subscription",LOWER(TRIM($F13&""))="membership"),"",IF(LOWER(TRIM($D13&""))="estimate","N/A",IF(LOWER($L13&"")="yes",0,IF(OR(AND($H13<>"",$H13=0),LEFT(LOWER(TRIM($F13&"")),9)="free game",LOWER(TRIM($F13&""))="free",LOWER(TRIM($F13&""))="free entry"),IF(ISNUMBER($K13),$K13,""),IF($K13<>"",$K13,"")))))) | Q13: =IF(COUNTA($A13:$M13)=0,"",IF(OR($U13="Subscription",$U13=""),"",IF($U13="Estimate","N/A",IF($U13="Profit",ROUND(IFERROR($P13,0)-IFERROR($H13,0),2),0)))) | R13: =IF(COUNTA($A13:$M13)=0,"",IF(OR($U13="Subscription",$U13=""),"",IF($U13="Estimate","N/A",IF($U13="Draw",$H13,0)))) | S13: =IF(COUNTA($A13:$M13)=0,"",IF(OR($U13="Subscription",$U13=""),"",IF($U13="Estimate","N/A",IF($U13="Disqualified",$H13,0)))) | T13: =IF(COUNTA($A13:$M13)=0,"",IF(OR($U13="Subscription",$U13=""),"",IF($U13="Estimate","N/A",IF(OR($U13="Free Game",$U13="Disqualified — Free Game",$H13=0),"N/A",IF($U13="Profit",$Q13/$H13,IF($U13="Disqualified",-$S13/$H13,0)))))) | U13: =IF(COUNTA($A13:$M13)=0,"",IF(OR(LEFT(LOWER(TRIM($F13&"")),12)="subscription",LOWER(TRIM($F13&""))="membership"),"Subscription",IF(LOWER(TRIM($D13&""))="estimate","Estimate",IF(OR(AND($H13<>"",$H13=0),LEFT(LOWER(TRIM($F13&"")),9)="free game",LOWER(TRIM($F13&""))="free",LOWER(TRIM($F13&""))="free entry"),IF(LOWER($L13&"")="yes","Disqualified — Free Game","Free Game"),IF(LOWER($L13&"")="yes","Disqualified",IF($P13="","",IF(ROUND(IFERROR(VALUE($P13),0)-IFERROR(VALUE($H13),0),2)>0,"Profit","Draw"))))))) | V13: =IF(COUNTA($A13:$M13)=0,"",IF(OR($B13="",$C13="",$U13="Subscription"),"",IFERROR(ROUNDUP(($C13-$B13)/7,0),""))) | W13: =IF(COUNTA($A13:$M13)=0,"",IF(OR($U13="Subscription",$U13=""),"",IF($U13="Estimate","N/A",IF(OR($U13="Free Game",$U13="Disqualified — Free Game"),0,ROUND(IFERROR($Q13,0)-IFERROR($S13,0),2))))) | X13: =IF(COUNTA($A13:$M13)=0,"",IF(OR($U13="Subscription",NOT(ISNUMBER($J13)),NOT(ISNUMBER($I13)),$J13=0,$I13=0,$I13>$J13),"",$J13-$I13)) | Y13: =IF(COUNTA($A13:$M13)=0,"",IF(OR($U13="Subscription",NOT(ISNUMBER($J13)),$J13=0,$X13=""),"",$X13/$J13)) | Z13: =IF(COUNTA($A13:$M13)=0,"",Instructions!$B$29+SUM($W$5:W13))
N14: =IF(COUNTA($A14:$M14)=0,"",IF(OR(LEFT(LOWER(TRIM($F14&"")),12)="subscription",LOWER(TRIM($F14&""))="membership"),"",IF(OR(AND($H14<>"",$H14=0),LEFT(LOWER(TRIM($F14&"")),9)="free game",LOWER(TRIM($F14&""))="free",LOWER(TRIM($F14&""))="free entry"),IF(ISNUMBER($G14),IF(ISNUMBER(SEARCH("non",LOWER($E14&""))),$G14*0.85,$G14),"N/A"),IF($G14="","",IFERROR(IF(ISNUMBER(SEARCH("non",LOWER($E14&""))),$G14*0.85,$G14),""))))) | O14: =IF(COUNTA($A14:$M14)=0,"",IF(OR(LEFT(LOWER(TRIM($F14&"")),12)="subscription",LOWER(TRIM($F14&""))="membership"),"",IF(OR(AND($H14<>"",$H14=0),LEFT(LOWER(TRIM($F14&"")),9)="free game",LOWER(TRIM($F14&""))="free",LOWER(TRIM($F14&""))="free entry"),IF(OR(NOT(ISNUMBER($N14)),NOT(ISNUMBER($I14)),$I14=0),"N/A",IFERROR($N14/$I14,"N/A")),IF(OR($N14="",$I14="",$I14=0),"",IFERROR($N14/$I14,""))))) | P14: =IF(COUNTA($A14:$M14)=0,"",IF(OR(LEFT(LOWER(TRIM($F14&"")),12)="subscription",LOWER(TRIM($F14&""))="membership"),"",IF(LOWER(TRIM($D14&""))="estimate","N/A",IF(LOWER($L14&"")="yes",0,IF(OR(AND($H14<>"",$H14=0),LEFT(LOWER(TRIM($F14&"")),9)="free game",LOWER(TRIM($F14&""))="free",LOWER(TRIM($F14&""))="free entry"),IF(ISNUMBER($K14),$K14,""),IF($K14<>"",$K14,"")))))) | Q14: =IF(COUNTA($A14:$M14)=0,"",IF(OR($U14="Subscription",$U14=""),"",IF($U14="Estimate","N/A",IF($U14="Profit",ROUND(IFERROR($P14,0)-IFERROR($H14,0),2),0)))) | R14: =IF(COUNTA($A14:$M14)=0,"",IF(OR($U14="Subscription",$U14=""),"",IF($U14="Estimate","N/A",IF($U14="Draw",$H14,0)))) | S14: =IF(COUNTA($A14:$M14)=0,"",IF(OR($U14="Subscription",$U14=""),"",IF($U14="Estimate","N/A",IF($U14="Disqualified",$H14,0)))) | T14: =IF(COUNTA($A14:$M14)=0,"",IF(OR($U14="Subscription",$U14=""),"",IF($U14="Estimate","N/A",IF(OR($U14="Free Game",$U14="Disqualified — Free Game",$H14=0),"N/A",IF($U14="Profit",$Q14/$H14,IF($U14="Disqualified",-$S14/$H14,0)))))) | U14: =IF(COUNTA($A14:$M14)=0,"",IF(OR(LEFT(LOWER(TRIM($F14&"")),12)="subscription",LOWER(TRIM($F14&""))="membership"),"Subscription",IF(LOWER(TRIM($D14&""))="estimate","Estimate",IF(OR(AND($H14<>"",$H14=0),LEFT(LOWER(TRIM($F14&"")),9)="free game",LOWER(TRIM($F14&""))="free",LOWER(TRIM($F14&""))="free entry"),IF(LOWER($L14&"")="yes","Disqualified — Free Game","Free Game"),IF(LOWER($L14&"")="yes","Disqualified",IF($P14="","",IF(ROUND(IFERROR(VALUE($P14),0)-IFERROR(VALUE($H14),0),2)>0,"Profit","Draw"))))))) | V14: =IF(COUNTA($A14:$M14)=0,"",IF(OR($B14="",$C14="",$U14="Subscription"),"",IFERROR(ROUNDUP(($C14-$B14)/7,0),""))) | W14: =IF(COUNTA($A14:$M14)=0,"",IF(OR($U14="Subscription",$U14=""),"",IF($U14="Estimate","N/A",IF(OR($U14="Free Game",$U14="Disqualified — Free Game"),0,ROUND(IFERROR($Q14,0)-IFERROR($S14,0),2))))) | X14: =IF(COUNTA($A14:$M14)=0,"",IF(OR($U14="Subscription",NOT(ISNUMBER($J14)),NOT(ISNUMBER($I14)),$J14=0,$I14=0,$I14>$J14),"",$J14-$I14)) | Y14: =IF(COUNTA($A14:$M14)=0,"",IF(OR($U14="Subscription",NOT(ISNUMBER($J14)),$J14=0,$X14=""),"",$X14/$J14)) | Z14: =IF(COUNTA($A14:$M14)=0,"",Instructions!$B$29+SUM($W$5:W14))
N15: =IF(COUNTA($A15:$M15)=0,"",IF(OR(LEFT(LOWER(TRIM($F15&"")),12)="subscription",LOWER(TRIM($F15&""))="membership"),"",IF(OR(AND($H15<>"",$H15=0),LEFT(LOWER(TRIM($F15&"")),9)="free game",LOWER(TRIM($F15&""))="free",LOWER(TRIM($F15&""))="free entry"),IF(ISNUMBER($G15),IF(ISNUMBER(SEARCH("non",LOWER($E15&""))),$G15*0.85,$G15),"N/A"),IF($G15="","",IFERROR(IF(ISNUMBER(SEARCH("non",LOWER($E15&""))),$G15*0.85,$G15),""))))) | O15: =IF(COUNTA($A15:$M15)=0,"",IF(OR(LEFT(LOWER(TRIM($F15&"")),12)="subscription",LOWER(TRIM($F15&""))="membership"),"",IF(OR(AND($H15<>"",$H15=0),LEFT(LOWER(TRIM($F15&"")),9)="free game",LOWER(TRIM($F15&""))="free",LOWER(TRIM($F15&""))="free entry"),IF(OR(NOT(ISNUMBER($N15)),NOT(ISNUMBER($I15)),$I15=0),"N/A",IFERROR($N15/$I15,"N/A")),IF(OR($N15="",$I15="",$I15=0),"",IFERROR($N15/$I15,""))))) | P15: =IF(COUNTA($A15:$M15)=0,"",IF(OR(LEFT(LOWER(TRIM($F15&"")),12)="subscription",LOWER(TRIM($F15&""))="membership"),"",IF(LOWER(TRIM($D15&""))="estimate","N/A",IF(LOWER($L15&"")="yes",0,IF(OR(AND($H15<>"",$H15=0),LEFT(LOWER(TRIM($F15&"")),9)="free game",LOWER(TRIM($F15&""))="free",LOWER(TRIM($F15&""))="free entry"),IF(ISNUMBER($K15),$K15,""),IF($K15<>"",$K15,"")))))) | Q15: =IF(COUNTA($A15:$M15)=0,"",IF(OR($U15="Subscription",$U15=""),"",IF($U15="Estimate","N/A",IF($U15="Profit",ROUND(IFERROR($P15,0)-IFERROR($H15,0),2),0)))) | R15: =IF(COUNTA($A15:$M15)=0,"",IF(OR($U15="Subscription",$U15=""),"",IF($U15="Estimate","N/A",IF($U15="Draw",$H15,0)))) | S15: =IF(COUNTA($A15:$M15)=0,"",IF(OR($U15="Subscription",$U15=""),"",IF($U15="Estimate","N/A",IF($U15="Disqualified",$H15,0)))) | T15: =IF(COUNTA($A15:$M15)=0,"",IF(OR($U15="Subscription",$U15=""),"",IF($U15="Estimate","N/A",IF(OR($U15="Free Game",$U15="Disqualified — Free Game",$H15=0),"N/A",IF($U15="Profit",$Q15/$H15,IF($U15="Disqualified",-$S15/$H15,0)))))) | U15: =IF(COUNTA($A15:$M15)=0,"",IF(OR(LEFT(LOWER(TRIM($F15&"")),12)="subscription",LOWER(TRIM($F15&""))="membership"),"Subscription",IF(LOWER(TRIM($D15&""))="estimate","Estimate",IF(OR(AND($H15<>"",$H15=0),LEFT(LOWER(TRIM($F15&"")),9)="free game",LOWER(TRIM($F15&""))="free",LOWER(TRIM($F15&""))="free entry"),IF(LOWER($L15&"")="yes","Disqualified — Free Game","Free Game"),IF(LOWER($L15&"")="yes","Disqualified",IF($P15="","",IF(ROUND(IFERROR(VALUE($P15),0)-IFERROR(VALUE($H15),0),2)>0,"Profit","Draw"))))))) | V15: =IF(COUNTA($A15:$M15)=0,"",IF(OR($B15="",$C15="",$U15="Subscription"),"",IFERROR(ROUNDUP(($C15-$B15)/7,0),""))) | W15: =IF(COUNTA($A15:$M15)=0,"",IF(OR($U15="Subscription",$U15=""),"",IF($U15="Estimate","N/A",IF(OR($U15="Free Game",$U15="Disqualified — Free Game"),0,ROUND(IFERROR($Q15,0)-IFERROR($S15,0),2))))) | X15: =IF(COUNTA($A15:$M15)=0,"",IF(OR($U15="Subscription",NOT(ISNUMBER($J15)),NOT(ISNUMBER($I15)),$J15=0,$I15=0,$I15>$J15),"",$J15-$I15)) | Y15: =IF(COUNTA($A15:$M15)=0,"",IF(OR($U15="Subscription",NOT(ISNUMBER($J15)),$J15=0,$X15=""),"",$X15/$J15)) | Z15: =IF(COUNTA($A15:$M15)=0,"",Instructions!$B$29+SUM($W$5:W15))
N16: =IF(COUNTA($A16:$M16)=0,"",IF(OR(LEFT(LOWER(TRIM($F16&"")),12)="subscription",LOWER(TRIM($F16&""))="membership"),"",IF(OR(AND($H16<>"",$H16=0),LEFT(LOWER(TRIM($F16&"")),9)="free game",LOWER(TRIM($F16&""))="free",LOWER(TRIM($F16&""))="free entry"),IF(ISNUMBER($G16),IF(ISNUMBER(SEARCH("non",LOWER($E16&""))),$G16*0.85,$G16),"N/A"),IF($G16="","",IFERROR(IF(ISNUMBER(SEARCH("non",LOWER($E16&""))),$G16*0.85,$G16),""))))) | O16: =IF(COUNTA($A16:$M16)=0,"",IF(OR(LEFT(LOWER(TRIM($F16&"")),12)="subscription",LOWER(TRIM($F16&""))="membership"),"",IF(OR(AND($H16<>"",$H16=0),LEFT(LOWER(TRIM($F16&"")),9)="free game",LOWER(TRIM($F16&""))="free",LOWER(TRIM($F16&""))="free entry"),IF(OR(NOT(ISNUMBER($N16)),NOT(ISNUMBER($I16)),$I16=0),"N/A",IFERROR($N16/$I16,"N/A")),IF(OR($N16="",$I16="",$I16=0),"",IFERROR($N16/$I16,""))))) | P16: =IF(COUNTA($A16:$M16)=0,"",IF(OR(LEFT(LOWER(TRIM($F16&"")),12)="subscription",LOWER(TRIM($F16&""))="membership"),"",IF(LOWER(TRIM($D16&""))="estimate","N/A",IF(LOWER($L16&"")="yes",0,IF(OR(AND($H16<>"",$H16=0),LEFT(LOWER(TRIM($F16&"")),9)="free game",LOWER(TRIM($F16&""))="free",LOWER(TRIM($F16&""))="free entry"),IF(ISNUMBER($K16),$K16,""),IF($K16<>"",$K16,"")))))) | Q16: =IF(COUNTA($A16:$M16)=0,"",IF(OR($U16="Subscription",$U16=""),"",IF($U16="Estimate","N/A",IF($U16="Profit",ROUND(IFERROR($P16,0)-IFERROR($H16,0),2),0)))) | R16: =IF(COUNTA($A16:$M16)=0,"",IF(OR($U16="Subscription",$U16=""),"",IF($U16="Estimate","N/A",IF($U16="Draw",$H16,0)))) | S16: =IF(COUNTA($A16:$M16)=0,"",IF(OR($U16="Subscription",$U16=""),"",IF($U16="Estimate","N/A",IF($U16="Disqualified",$H16,0)))) | T16: =IF(COUNTA($A16:$M16)=0,"",IF(OR($U16="Subscription",$U16=""),"",IF($U16="Estimate","N/A",IF(OR($U16="Free Game",$U16="Disqualified — Free Game",$H16=0),"N/A",IF($U16="Profit",$Q16/$H16,IF($U16="Disqualified",-$S16/$H16,0)))))) | U16: =IF(COUNTA($A16:$M16)=0,"",IF(OR(LEFT(LOWER(TRIM($F16&"")),12)="subscription",LOWER(TRIM($F16&""))="membership"),"Subscription",IF(LOWER(TRIM($D16&""))="estimate","Estimate",IF(OR(AND($H16<>"",$H16=0),LEFT(LOWER(TRIM($F16&"")),9)="free game",LOWER(TRIM($F16&""))="free",LOWER(TRIM($F16&""))="free entry"),IF(LOWER($L16&"")="yes","Disqualified — Free Game","Free Game"),IF(LOWER($L16&"")="yes","Disqualified",IF($P16="","",IF(ROUND(IFERROR(VALUE($P16),0)-IFERROR(VALUE($H16),0),2)>0,"Profit","Draw"))))))) | V16: =IF(COUNTA($A16:$M16)=0,"",IF(OR($B16="",$C16="",$U16="Subscription"),"",IFERROR(ROUNDUP(($C16-$B16)/7,0),""))) | W16: =IF(COUNTA($A16:$M16)=0,"",IF(OR($U16="Subscription",$U16=""),"",IF($U16="Estimate","N/A",IF(OR($U16="Free Game",$U16="Disqualified — Free Game"),0,ROUND(IFERROR($Q16,0)-IFERROR($S16,0),2))))) | X16: =IF(COUNTA($A16:$M16)=0,"",IF(OR($U16="Subscription",NOT(ISNUMBER($J16)),NOT(ISNUMBER($I16)),$J16=0,$I16=0,$I16>$J16),"",$J16-$I16)) | Y16: =IF(COUNTA($A16:$M16)=0,"",IF(OR($U16="Subscription",NOT(ISNUMBER($J16)),$J16=0,$X16=""),"",$X16/$J16)) | Z16: =IF(COUNTA($A16:$M16)=0,"",Instructions!$B$29+SUM($W$5:W16))
... N504: =IF(COUNTA($A504:$M504)=0,"",IF(OR(LEFT(LOWER(TRIM($F504&"")),12)="subscription",LOWER(TRIM($F504&""))="membership"),"",IF(OR(AND($H504<>"",$H504=0),LEFT(LOWER(TRIM($F504&"")),9)="free game",LOWER(TRIM($F504&""))="free",LOWER(TRIM($F504&""))="free entry"),IF(ISNUMBER($G504),IF(ISNUMBER(SEARCH("non",LOWER($E504&""))),$G504*0.85,$G504),"N/A"),IF($G504="","",IFERROR(IF(ISNUMBER(SEARCH("non",LOWER($E504&""))),$G504*0.85,$G504),""))))) | O504: =IF(COUNTA($A504:$M504)=0,"",IF(OR(LEFT(LOWER(TRIM($F504&"")),12)="subscription",LOWER(TRIM($F504&""))="membership"),"",IF(OR(AND($H504<>"",$H504=0),LEFT(LOWER(TRIM($F504&"")),9)="free game",LOWER(TRIM($F504&""))="free",LOWER(TRIM($F504&""))="free entry"),IF(OR(NOT(ISNUMBER($N504)),NOT(ISNUMBER($I504)),$I504=0),"N/A",IFERROR($N504/$I504,"N/A")),IF(OR($N504="",$I504="",$I504=0),"",IFERROR($N504/$I504,""))))) | P504: =IF(COUNTA($A504:$M504)=0,"",IF(OR(LEFT(LOWER(TRIM($F504&"")),12)="subscription",LOWER(TRIM($F504&""))="membership"),"",IF(LOWER(TRIM($D504&""))="estimate","N/A",IF(LOWER($L504&"")="yes",0,IF(OR(AND($H504<>"",$H504=0),LEFT(LOWER(TRIM($F504&"")),9)="free game",LOWER(TRIM($F504&""))="free",LOWER(TRIM($F504&""))="free entry"),IF(ISNUMBER($K504),$K504,""),IF($K504<>"",$K504,"")))))) | Q504: =IF(COUNTA($A504:$M504)=0,"",IF(OR($U504="Subscription",$U504=""),"",IF($U504="Estimate","N/A",IF($U504="Profit",ROUND(IFERROR($P504,0)-IFERROR($H504,0),2),0)))) | R504: =IF(COUNTA($A504:$M504)=0,"",IF(OR($U504="Subscription",$U504=""),"",IF($U504="Estimate","N/A",IF($U504="Draw",$H504,0)))) | S504: =IF(COUNTA($A504:$M504)=0,"",IF(OR($U504="Subscription",$U504=""),"",IF($U504="Estimate","N/A",IF($U504="Disqualified",$H504,0)))) | T504: =IF(COUNTA($A504:$M504)=0,"",IF(OR($U504="Subscription",$U504=""),"",IF($U504="Estimate","N/A",IF(OR($U504="Free Game",$U504="Disqualified — Free Game",$H504=0),"N/A",IF($U504="Profit",$Q504/$H504,IF($U504="Disqualified",-$S504/$H504,0)))))) | U504: =IF(COUNTA($A504:$M504)=0,"",IF(OR(LEFT(LOWER(TRIM($F504&"")),12)="subscription",LOWER(TRIM($F504&""))="membership"),"Subscription",IF(LOWER(TRIM($D504&""))="estimate","Estimate",IF(OR(AND($H504<>"",$H504=0),LEFT(LOWER(TRIM($F504&"")),9)="free game",LOWER(TRIM($F504&""))="free",LOWER(TRIM($F504&""))="free entry"),IF(LOWER($L504&"")="yes","Disqualified — Free Game","Free Game"),IF(LOWER($L504&"")="yes","Disqualified",IF($P504="","",IF(ROUND(IFERROR(VALUE($P504),0)-IFERROR(VALUE($H504),0),2)>0,"Profit","Draw"))))))) | V504: =IF(COUNTA($A504:$M504)=0,"",IF(OR($B504="",$C504="",$U504="Subscription"),"",IFERROR(ROUNDUP(($C504-$B504)/7,0),""))) | W504: =IF(COUNTA($A504:$M504)=0,"",IF(OR($U504="Subscription",$U504=""),"",IF($U504="Estimate","N/A",IF(OR($U504="Free Game",$U504="Disqualified — Free Game"),0,ROUND(IFERROR($Q504,0)-IFERROR($S504,0),2))))) | X504: =IF(COUNTA($A504:$M504)=0,"",IF(OR($U504="Subscription",NOT(ISNUMBER($J504)),NOT(ISNUMBER($I504)),$J504=0,$I504=0,$I504>$J504),"",$J504-$I504)) | Y504: =IF(COUNTA($A504:$M504)=0,"",IF(OR($U504="Subscription",NOT(ISNUMBER($J504)),$J504=0,$X504=""),"",$X504/$J504)) | Z504: =IF(COUNTA($A504:$M504)=0,"",Instructions!$B$29+SUM($W$5:W504))
A505: END OF WORKBOOK — 500 RECORD ROWS USED. ARCHIVE THIS FILE AND BEGIN A FRESH COPY. DO NOT ENTER RECORDS BELOW THIS ROW.

Sheet Record Review
A1: Record Review — Game Index and Field Review — v252
A2: Formula-driven view only — do not type or paste into Record Review. Enter or edit records in Game Records A–M. Blank rows are expected until matching non-subscription games exist. Selecting a prepared cell may show a formula in the formula bar; the worksheet cell should display its calculated result or remain blank.
A4: Game # | B4: Game Records ID | C4: Game Name | D4: Calculated Result | E4: Review Status | F4: What to Review | G4: Notes from Game Records
A5: =IF($H5="","",ROWS($A$5:A5)) | B5: =IF($H5="","","G-"&TEXT($A5,"0000")) | C5: =IF($H5="","",IFERROR(INDEX('Game Records'!$A:$A,$H5),"")) | D5: =IF($H5="","",IFERROR(INDEX('Game Records'!$U:$U,$H5),"")) | E5: =IF($H5="","",IF($F5="","No Highlighted Fields","Highlighted Fields Present")) | F5: =IF($H5="","",IF(OR(NOT(ISFORMULA(INDEX('Game Records'!$N:$N,$H5))),NOT(ISFORMULA(INDEX('Game Records'!$O:$O,$H5))),NOT(ISFORMULA(INDEX('Game Records'!$P:$P,$H5))),NOT(ISFORMULA(INDEX('Game Records'!$Q:$Q,$H5))),NOT(ISFORMULA(INDEX('Game Records'!$R:$R,$H5))),NOT(ISFORMULA(INDEX('Game Records'!$S:$S,$H5))),NOT(ISFORMULA(INDEX('Game Records'!$T:$T,$H5))),NOT(ISFORMULA(INDEX('Game Records'!$U:$U,$H5))),NOT(ISFORMULA(INDEX('Game Records'!$V:$V,$H5))),NOT(ISFORMULA(INDEX('Game Records'!$W:$W,$H5))),NOT(ISFORMULA(INDEX('Game Records'!$X:$X,$H5))),NOT(ISFORMULA(INDEX('Game Records'!$Y:$Y,$H5))),NOT(ISFORMULA(INDEX('Game Records'!$Z:$Z,$H5)))),"Formula columns missing; ","")&IF(INDEX('Game Records'!$B:$B,$H5)="","Start Date; ","")&IF(INDEX('Game Records'!$C:$C,$H5)="","End Date; ","")&IF(AND(INDEX('Game Records'!$U:$U,$H5)<>"Subscription",INDEX('Game Records'!$U:$U,$H5)<>"Free Game",INDEX('Game Records'!$U:$U,$H5)<>"Disqualified — Free Game",OR(INDEX('Game Records'!$D:$D,$H5)="",LOWER(INDEX('Game Records'!$D:$D,$H5)&"")="n/a")),"Entry Mode; ","")&IF(AND(INDEX('Game Records'!$U:$U,$H5)<>"Subscription",INDEX('Game Records'!$U:$U,$H5)<>"Free Game",INDEX('Game Records'!$U:$U,$H5)<>"Disqualified — Free Game",OR(INDEX('Game Records'!$E:$E,$H5)="",LOWER(INDEX('Game Records'!$E:$E,$H5)&"")="n/a")),"Game Type; ","")&IF(INDEX('Game Records'!$F:$F,$H5)="","Payment Type; ","")&IF(AND(INDEX('Game Records'!$U:$U,$H5)<>"Subscription",INDEX('Game Records'!$U:$U,$H5)<>"Free Game",INDEX('Game Records'!$U:$U,$H5)<>"Disqualified — Free Game",INDEX('Game Records'!$G:$G,$H5)=""),"Gross Pot; ","")&IF(AND(INDEX('Game Records'!$U:$U,$H5)<>"Free Game",INDEX('Game Records'!$U:$U,$H5)<>"Disqualified — Free Game",INDEX('Game Records'!$H:$H,$H5)=""),"Entry Fee; ","")&IF(AND(INDEX('Game Records'!$U:$U,$H5)<>"Subscription",INDEX('Game Records'!$U:$U,$H5)<>"Free Game",INDEX('Game Records'!$U:$U,$H5)<>"Disqualified — Free Game",INDEX('Game Records'!$I:$I,$H5)=""),"Eligible Players; ","")&IF(AND(INDEX('Game Records'!$U:$U,$H5)<>"Subscription",INDEX('Game Records'!$U:$U,$H5)<>"Free Game",INDEX('Game Records'!$U:$U,$H5)<>"Disqualified — Free Game",INDEX('Game Records'!$J:$J,$H5)=""),"Total Players; ","")&IF(AND(LOWER(INDEX('Game Records'!$D:$D,$H5)&"")="finalized",LOWER(INDEX('Game Records'!$L:$L,$H5)&"")<>"yes",INDEX('Game Records'!$U:$U,$H5)<>"Subscription",INDEX('Game Records'!$U:$U,$H5)<>"Free Game",INDEX('Game Records'!$U:$U,$H5)<>"Disqualified — Free Game",INDEX('Game Records'!$K:$K,$H5)=""),"Final Earned; ","")&IF(AND(LOWER(INDEX('Game Records'!$D:$D,$H5)&"")="finalized",INDEX('Game Records'!$U:$U,$H5)<>"Subscription",INDEX('Game Records'!$U:$U,$H5)<>"Free Game",INDEX('Game Records'!$U:$U,$H5)<>"Disqualified — Free Game",OR(INDEX('Game Records'!$L:$L,$H5)="",LOWER(INDEX('Game Records'!$L:$L,$H5)&"")="n/a")),"Disqualified Status; ","")&IF(AND(OR(LOWER(TRIM(INDEX('Game Records'!$F:$F,$H5)&""))="free game",INDEX('Game Records'!$U:$U,$H5)="Free Game",INDEX('Game Records'!$U:$U,$H5)="Disqualified — Free Game"),N(INDEX('Game Records'!$H:$H,$H5))<>0),"Free Game has a non-zero Entry Fee. Free Game records require a $0 Entry Fee; ","")) | G5: =IF($H5="","",IFERROR(INDEX('Game Records'!$M:$M,$H5),"")) | H5: =IFERROR(MATCH(1,INDEX((('Game Records'!$A$5:$A$504<>"")+('Game Records'!$B$5:$B$504<>"")+('Game Records'!$C$5:$C$504<>"")+('Game Records'!$D$5:$D$504<>"")+('Game Records'!$E$5:$E$504<>"")+('Game Records'!$F$5:$F$504<>"")+('Game Records'!$G$5:$G$504<>"")+('Game Records'!$H$5:$H$504<>"")+('Game Records'!$I$5:$I$504<>"")+('Game Records'!$J$5:$J$504<>"")+('Game Records'!$K$5:$K$504<>"")+('Game Records'!$L$5:$L$504<>"")+('Game Records'!$M$5:$M$504<>"")>0)*('Game Records'!$U$5:$U$504<>"Subscription"),0),0)+4,"") | I5: Review Totals
A6: =IF($H6="","",ROWS($A$5:A6)) | B6: =IF($H6="","","G-"&TEXT($A6,"0000")) | C6: =IF($H6="","",IFERROR(INDEX('Game Records'!$A:$A,$H6),"")) | D6: =IF($H6="","",IFERROR(INDEX('Game Records'!$U:$U,$H6),"")) | E6: =IF($H6="","",IF($F6="","No Highlighted Fields","Highlighted Fields Present")) | F6: =IF($H6="","",IF(OR(NOT(ISFORMULA(INDEX('Game Records'!$N:$N,$H6))),NOT(ISFORMULA(INDEX('Game Records'!$O:$O,$H6))),NOT(ISFORMULA(INDEX('Game Records'!$P:$P,$H6))),NOT(ISFORMULA(INDEX('Game Records'!$Q:$Q,$H6))),NOT(ISFORMULA(INDEX('Game Records'!$R:$R,$H6))),NOT(ISFORMULA(INDEX('Game Records'!$S:$S,$H6))),NOT(ISFORMULA(INDEX('Game Records'!$T:$T,$H6))),NOT(ISFORMULA(INDEX('Game Records'!$U:$U,$H6))),NOT(ISFORMULA(INDEX('Game Records'!$V:$V,$H6))),NOT(ISFORMULA(INDEX('Game Records'!$W:$W,$H6))),NOT(ISFORMULA(INDEX('Game Records'!$X:$X,$H6))),NOT(ISFORMULA(INDEX('Game Records'!$Y:$Y,$H6))),NOT(ISFORMULA(INDEX('Game Records'!$Z:$Z,$H6)))),"Formula columns missing; ","")&IF(INDEX('Game Records'!$B:$B,$H6)="","Start Date; ","")&IF(INDEX('Game Records'!$C:$C,$H6)="","End Date; ","")&IF(AND(INDEX('Game Records'!$U:$U,$H6)<>"Subscription",INDEX('Game Records'!$U:$U,$H6)<>"Free Game",INDEX('Game Records'!$U:$U,$H6)<>"Disqualified — Free Game",OR(INDEX('Game Records'!$D:$D,$H6)="",LOWER(INDEX('Game Records'!$D:$D,$H6)&"")="n/a")),"Entry Mode; ","")&IF(AND(INDEX('Game Records'!$U:$U,$H6)<>"Subscription",INDEX('Game Records'!$U:$U,$H6)<>"Free Game",INDEX('Game Records'!$U:$U,$H6)<>"Disqualified — Free Game",OR(INDEX('Game Records'!$E:$E,$H6)="",LOWER(INDEX('Game Records'!$E:$E,$H6)&"")="n/a")),"Game Type; ","")&IF(INDEX('Game Records'!$F:$F,$H6)="","Payment Type; ","")&IF(AND(INDEX('Game Records'!$U:$U,$H6)<>"Subscription",INDEX('Game Records'!$U:$U,$H6)<>"Free Game",INDEX('Game Records'!$U:$U,$H6)<>"Disqualified — Free Game",INDEX('Game Records'!$G:$G,$H6)=""),"Gross Pot; ","")&IF(AND(INDEX('Game Records'!$U:$U,$H6)<>"Free Game",INDEX('Game Records'!$U:$U,$H6)<>"Disqualified — Free Game",INDEX('Game Records'!$H:$H,$H6)=""),"Entry Fee; ","")&IF(AND(INDEX('Game Records'!$U:$U,$H6)<>"Subscription",INDEX('Game Records'!$U:$U,$H6)<>"Free Game",INDEX('Game Records'!$U:$U,$H6)<>"Disqualified — Free Game",INDEX('Game Records'!$I:$I,$H6)=""),"Eligible Players; ","")&IF(AND(INDEX('Game Records'!$U:$U,$H6)<>"Subscription",INDEX('Game Records'!$U:$U,$H6)<>"Free Game",INDEX('Game Records'!$U:$U,$H6)<>"Disqualified — Free Game",INDEX('Game Records'!$J:$J,$H6)=""),"Total Players; ","")&IF(AND(LOWER(INDEX('Game Records'!$D:$D,$H6)&"")="finalized",LOWER(INDEX('Game Records'!$L:$L,$H6)&"")<>"yes",INDEX('Game Records'!$U:$U,$H6)<>"Subscription",INDEX('Game Records'!$U:$U,$H6)<>"Free Game",INDEX('Game Records'!$U:$U,$H6)<>"Disqualified — Free Game",INDEX('Game Records'!$K:$K,$H6)=""),"Final Earned; ","")&IF(AND(LOWER(INDEX('Game Records'!$D:$D,$H6)&"")="finalized",INDEX('Game Records'!$U:$U,$H6)<>"Subscription",INDEX('Game Records'!$U:$U,$H6)<>"Free Game",INDEX('Game Records'!$U:$U,$H6)<>"Disqualified — Free Game",OR(INDEX('Game Records'!$L:$L,$H6)="",LOWER(INDEX('Game Records'!$L:$L,$H6)&"")="n/a")),"Disqualified Status; ","")&IF(AND(OR(LOWER(TRIM(INDEX('Game Records'!$F:$F,$H6)&""))="free game",INDEX('Game Records'!$U:$U,$H6)="Free Game",INDEX('Game Records'!$U:$U,$H6)="Disqualified — Free Game"),N(INDEX('Game Records'!$H:$H,$H6))<>0),"Free Game has a non-zero Entry Fee. Free Game records require a $0 Entry Fee; ","")) | G6: =IF($H6="","",IFERROR(INDEX('Game Records'!$M:$M,$H6),"")) | H6: =IF($H5="","",IFERROR(MATCH(1,INDEX((ROW('Game Records'!$U$5:$U$504)>$H5)*(('Game Records'!$A$5:$A$504<>"")+('Game Records'!$B$5:$B$504<>"")+('Game Records'!$C$5:$C$504<>"")+('Game Records'!$D$5:$D$504<>"")+('Game Records'!$E$5:$E$504<>"")+('Game Records'!$F$5:$F$504<>"")+('Game Records'!$G$5:$G$504<>"")+('Game Records'!$H$5:$H$504<>"")+('Game Records'!$I$5:$I$504<>"")+('Game Records'!$J$5:$J$504<>"")+('Game Records'!$K$5:$K$504<>"")+('Game Records'!$L$5:$L$504<>"")+('Game Records'!$M$5:$M$504<>"")>0)*('Game Records'!$U$5:$U$504<>"Subscription"),0),0)+4,"")) | I6: Total Games | J6: =COUNT($A$5:$A$504) -> 0
A7: =IF($H7="","",ROWS($A$5:A7)) | B7: =IF($H7="","","G-"&TEXT($A7,"0000")) | C7: =IF($H7="","",IFERROR(INDEX('Game Records'!$A:$A,$H7),"")) | D7: =IF($H7="","",IFERROR(INDEX('Game Records'!$U:$U,$H7),"")) | E7: =IF($H7="","",IF($F7="","No Highlighted Fields","Highlighted Fields Present")) | F7: =IF($H7="","",IF(OR(NOT(ISFORMULA(INDEX('Game Records'!$N:$N,$H7))),NOT(ISFORMULA(INDEX('Game Records'!$O:$O,$H7))),NOT(ISFORMULA(INDEX('Game Records'!$P:$P,$H7))),NOT(ISFORMULA(INDEX('Game Records'!$Q:$Q,$H7))),NOT(ISFORMULA(INDEX('Game Records'!$R:$R,$H7))),NOT(ISFORMULA(INDEX('Game Records'!$S:$S,$H7))),NOT(ISFORMULA(INDEX('Game Records'!$T:$T,$H7))),NOT(ISFORMULA(INDEX('Game Records'!$U:$U,$H7))),NOT(ISFORMULA(INDEX('Game Records'!$V:$V,$H7))),NOT(ISFORMULA(INDEX('Game Records'!$W:$W,$H7))),NOT(ISFORMULA(INDEX('Game Records'!$X:$X,$H7))),NOT(ISFORMULA(INDEX('Game Records'!$Y:$Y,$H7))),NOT(ISFORMULA(INDEX('Game Records'!$Z:$Z,$H7)))),"Formula columns missing; ","")&IF(INDEX('Game Records'!$B:$B,$H7)="","Start Date; ","")&IF(INDEX('Game Records'!$C:$C,$H7)="","End Date; ","")&IF(AND(INDEX('Game Records'!$U:$U,$H7)<>"Subscription",INDEX('Game Records'!$U:$U,$H7)<>"Free Game",INDEX('Game Records'!$U:$U,$H7)<>"Disqualified — Free Game",OR(INDEX('Game Records'!$D:$D,$H7)="",LOWER(INDEX('Game Records'!$D:$D,$H7)&"")="n/a")),"Entry Mode; ","")&IF(AND(INDEX('Game Records'!$U:$U,$H7)<>"Subscription",INDEX('Game Records'!$U:$U,$H7)<>"Free Game",INDEX('Game Records'!$U:$U,$H7)<>"Disqualified — Free Game",OR(INDEX('Game Records'!$E:$E,$H7)="",LOWER(INDEX('Game Records'!$E:$E,$H7)&"")="n/a")),"Game Type; ","")&IF(INDEX('Game Records'!$F:$F,$H7)="","Payment Type; ","")&IF(AND(INDEX('Game Records'!$U:$U,$H7)<>"Subscription",INDEX('Game Records'!$U:$U,$H7)<>"Free Game",INDEX('Game Records'!$U:$U,$H7)<>"Disqualified — Free Game",INDEX('Game Records'!$G:$G,$H7)=""),"Gross Pot; ","")&IF(AND(INDEX('Game Records'!$U:$U,$H7)<>"Free Game",INDEX('Game Records'!$U:$U,$H7)<>"Disqualified — Free Game",INDEX('Game Records'!$H:$H,$H7)=""),"Entry Fee; ","")&IF(AND(INDEX('Game Records'!$U:$U,$H7)<>"Subscription",INDEX('Game Records'!$U:$U,$H7)<>"Free Game",INDEX('Game Records'!$U:$U,$H7)<>"Disqualified — Free Game",INDEX('Game Records'!$I:$I,$H7)=""),"Eligible Players; ","")&IF(AND(INDEX('Game Records'!$U:$U,$H7)<>"Subscription",INDEX('Game Records'!$U:$U,$H7)<>"Free Game",INDEX('Game Records'!$U:$U,$H7)<>"Disqualified — Free Game",INDEX('Game Records'!$J:$J,$H7)=""),"Total Players; ","")&IF(AND(LOWER(INDEX('Game Records'!$D:$D,$H7)&"")="finalized",LOWER(INDEX('Game Records'!$L:$L,$H7)&"")<>"yes",INDEX('Game Records'!$U:$U,$H7)<>"Subscription",INDEX('Game Records'!$U:$U,$H7)<>"Free Game",INDEX('Game Records'!$U:$U,$H7)<>"Disqualified — Free Game",INDEX('Game Records'!$K:$K,$H7)=""),"Final Earned; ","")&IF(AND(LOWER(INDEX('Game Records'!$D:$D,$H7)&"")="finalized",INDEX('Game Records'!$U:$U,$H7)<>"Subscription",INDEX('Game Records'!$U:$U,$H7)<>"Free Game",INDEX('Game Records'!$U:$U,$H7)<>"Disqualified — Free Game",OR(INDEX('Game Records'!$L:$L,$H7)="",LOWER(INDEX('Game Records'!$L:$L,$H7)&"")="n/a")),"Disqualified Status; ","")&IF(AND(OR(LOWER(TRIM(INDEX('Game Records'!$F:$F,$H7)&""))="free game",INDEX('Game Records'!$U:$U,$H7)="Free Game",INDEX('Game Records'!$U:$U,$H7)="Disqualified — Free Game"),N(INDEX('Game Records'!$H:$H,$H7))<>0),"Free Game has a non-zero Entry Fee. Free Game records require a $0 Entry Fee; ","")) | G7: =IF($H7="","",IFERROR(INDEX('Game Records'!$M:$M,$H7),"")) | H7: =IF($H6="","",IFERROR(MATCH(1,INDEX((ROW('Game Records'!$U$5:$U$504)>$H6)*(('Game Records'!$A$5:$A$504<>"")+('Game Records'!$B$5:$B$504<>"")+('Game Records'!$C$5:$C$504<>"")+('Game Records'!$D$5:$D$504<>"")+('Game Records'!$E$5:$E$504<>"")+('Game Records'!$F$5:$F$504<>"")+('Game Records'!$G$5:$G$504<>"")+('Game Records'!$H$5:$H$504<>"")+('Game Records'!$I$5:$I$504<>"")+('Game Records'!$J$5:$J$504<>"")+('Game Records'!$K$5:$K$504<>"")+('Game Records'!$L$5:$L$504<>"")+('Game Records'!$M$5:$M$504<>"")>0)*('Game Records'!$U$5:$U$504<>"Subscription"),0),0)+4,"")) | I7: Profit Games | J7: =COUNTIF('Game Records'!$U$5:$U$504,"Profit") -> 0
A8: =IF($H8="","",ROWS($A$5:A8)) | B8: =IF($H8="","","G-"&TEXT($A8,"0000")) | C8: =IF($H8="","",IFERROR(INDEX('Game Records'!$A:$A,$H8),"")) | D8: =IF($H8="","",IFERROR(INDEX('Game Records'!$U:$U,$H8),"")) | E8: =IF($H8="","",IF($F8="","No Highlighted Fields","Highlighted Fields Present")) | F8: =IF($H8="","",IF(OR(NOT(ISFORMULA(INDEX('Game Records'!$N:$N,$H8))),NOT(ISFORMULA(INDEX('Game Records'!$O:$O,$H8))),NOT(ISFORMULA(INDEX('Game Records'!$P:$P,$H8))),NOT(ISFORMULA(INDEX('Game Records'!$Q:$Q,$H8))),NOT(ISFORMULA(INDEX('Game Records'!$R:$R,$H8))),NOT(ISFORMULA(INDEX('Game Records'!$S:$S,$H8))),NOT(ISFORMULA(INDEX('Game Records'!$T:$T,$H8))),NOT(ISFORMULA(INDEX('Game Records'!$U:$U,$H8))),NOT(ISFORMULA(INDEX('Game Records'!$V:$V,$H8))),NOT(ISFORMULA(INDEX('Game Records'!$W:$W,$H8))),NOT(ISFORMULA(INDEX('Game Records'!$X:$X,$H8))),NOT(ISFORMULA(INDEX('Game Records'!$Y:$Y,$H8))),NOT(ISFORMULA(INDEX('Game Records'!$Z:$Z,$H8)))),"Formula columns missing; ","")&IF(INDEX('Game Records'!$B:$B,$H8)="","Start Date; ","")&IF(INDEX('Game Records'!$C:$C,$H8)="","End Date; ","")&IF(AND(INDEX('Game Records'!$U:$U,$H8)<>"Subscription",INDEX('Game Records'!$U:$U,$H8)<>"Free Game",INDEX('Game Records'!$U:$U,$H8)<>"Disqualified — Free Game",OR(INDEX('Game Records'!$D:$D,$H8)="",LOWER(INDEX('Game Records'!$D:$D,$H8)&"")="n/a")),"Entry Mode; ","")&IF(AND(INDEX('Game Records'!$U:$U,$H8)<>"Subscription",INDEX('Game Records'!$U:$U,$H8)<>"Free Game",INDEX('Game Records'!$U:$U,$H8)<>"Disqualified — Free Game",OR(INDEX('Game Records'!$E:$E,$H8)="",LOWER(INDEX('Game Records'!$E:$E,$H8)&"")="n/a")),"Game Type; ","")&IF(INDEX('Game Records'!$F:$F,$H8)="","Payment Type; ","")&IF(AND(INDEX('Game Records'!$U:$U,$H8)<>"Subscription",INDEX('Game Records'!$U:$U,$H8)<>"Free Game",INDEX('Game Records'!$U:$U,$H8)<>"Disqualified — Free Game",INDEX('Game Records'!$G:$G,$H8)=""),"Gross Pot; ","")&IF(AND(INDEX('Game Records'!$U:$U,$H8)<>"Free Game",INDEX('Game Records'!$U:$U,$H8)<>"Disqualified — Free Game",INDEX('Game Records'!$H:$H,$H8)=""),"Entry Fee; ","")&IF(AND(INDEX('Game Records'!$U:$U,$H8)<>"Subscription",INDEX('Game Records'!$U:$U,$H8)<>"Free Game",INDEX('Game Records'!$U:$U,$H8)<>"Disqualified — Free Game",INDEX('Game Records'!$I:$I,$H8)=""),"Eligible Players; ","")&IF(AND(INDEX('Game Records'!$U:$U,$H8)<>"Subscription",INDEX('Game Records'!$U:$U,$H8)<>"Free Game",INDEX('Game Records'!$U:$U,$H8)<>"Disqualified — Free Game",INDEX('Game Records'!$J:$J,$H8)=""),"Total Players; ","")&IF(AND(LOWER(INDEX('Game Records'!$D:$D,$H8)&"")="finalized",LOWER(INDEX('Game Records'!$L:$L,$H8)&"")<>"yes",INDEX('Game Records'!$U:$U,$H8)<>"Subscription",INDEX('Game Records'!$U:$U,$H8)<>"Free Game",INDEX('Game Records'!$U:$U,$H8)<>"Disqualified — Free Game",INDEX('Game Records'!$K:$K,$H8)=""),"Final Earned; ","")&IF(AND(LOWER(INDEX('Game Records'!$D:$D,$H8)&"")="finalized",INDEX('Game Records'!$U:$U,$H8)<>"Subscription",INDEX('Game Records'!$U:$U,$H8)<>"Free Game",INDEX('Game Records'!$U:$U,$H8)<>"Disqualified — Free Game",OR(INDEX('Game Records'!$L:$L,$H8)="",LOWER(INDEX('Game Records'!$L:$L,$H8)&"")="n/a")),"Disqualified Status; ","")&IF(AND(OR(LOWER(TRIM(INDEX('Game Records'!$F:$F,$H8)&""))="free game",INDEX('Game Records'!$U:$U,$H8)="Free Game",INDEX('Game Records'!$U:$U,$H8)="Disqualified — Free Game"),N(INDEX('Game Records'!$H:$H,$H8))<>0),"Free Game has a non-zero Entry Fee. Free Game records require a $0 Entry Fee; ","")) | G8: =IF($H8="","",IFERROR(INDEX('Game Records'!$M:$M,$H8),"")) | H8: =IF($H7="","",IFERROR(MATCH(1,INDEX((ROW('Game Records'!$U$5:$U$504)>$H7)*(('Game Records'!$A$5:$A$504<>"")+('Game Records'!$B$5:$B$504<>"")+('Game Records'!$C$5:$C$504<>"")+('Game Records'!$D$5:$D$504<>"")+('Game Records'!$E$5:$E$504<>"")+('Game Records'!$F$5:$F$504<>"")+('Game Records'!$G$5:$G$504<>"")+('Game Records'!$H$5:$H$504<>"")+('Game Records'!$I$5:$I$504<>"")+('Game Records'!$J$5:$J$504<>"")+('Game Records'!$K$5:$K$504<>"")+('Game Records'!$L$5:$L$504<>"")+('Game Records'!$M$5:$M$504<>"")>0)*('Game Records'!$U$5:$U$504<>"Subscription"),0),0)+4,"")) | I8: Draw Games | J8: =COUNTIF('Game Records'!$U$5:$U$504,"Draw") -> 0
A9: =IF($H9="","",ROWS($A$5:A9)) | B9: =IF($H9="","","G-"&TEXT($A9,"0000")) | C9: =IF($H9="","",IFERROR(INDEX('Game Records'!$A:$A,$H9),"")) | D9: =IF($H9="","",IFERROR(INDEX('Game Records'!$U:$U,$H9),"")) | E9: =IF($H9="","",IF($F9="","No Highlighted Fields","Highlighted Fields Present")) | F9: =IF($H9="","",IF(OR(NOT(ISFORMULA(INDEX('Game Records'!$N:$N,$H9))),NOT(ISFORMULA(INDEX('Game Records'!$O:$O,$H9))),NOT(ISFORMULA(INDEX('Game Records'!$P:$P,$H9))),NOT(ISFORMULA(INDEX('Game Records'!$Q:$Q,$H9))),NOT(ISFORMULA(INDEX('Game Records'!$R:$R,$H9))),NOT(ISFORMULA(INDEX('Game Records'!$S:$S,$H9))),NOT(ISFORMULA(INDEX('Game Records'!$T:$T,$H9))),NOT(ISFORMULA(INDEX('Game Records'!$U:$U,$H9))),NOT(ISFORMULA(INDEX('Game Records'!$V:$V,$H9))),NOT(ISFORMULA(INDEX('Game Records'!$W:$W,$H9))),NOT(ISFORMULA(INDEX('Game Records'!$X:$X,$H9))),NOT(ISFORMULA(INDEX('Game Records'!$Y:$Y,$H9))),NOT(ISFORMULA(INDEX('Game Records'!$Z:$Z,$H9)))),"Formula columns missing; ","")&IF(INDEX('Game Records'!$B:$B,$H9)="","Start Date; ","")&IF(INDEX('Game Records'!$C:$C,$H9)="","End Date; ","")&IF(AND(INDEX('Game Records'!$U:$U,$H9)<>"Subscription",INDEX('Game Records'!$U:$U,$H9)<>"Free Game",INDEX('Game Records'!$U:$U,$H9)<>"Disqualified — Free Game",OR(INDEX('Game Records'!$D:$D,$H9)="",LOWER(INDEX('Game Records'!$D:$D,$H9)&"")="n/a")),"Entry Mode; ","")&IF(AND(INDEX('Game Records'!$U:$U,$H9)<>"Subscription",INDEX('Game Records'!$U:$U,$H9)<>"Free Game",INDEX('Game Records'!$U:$U,$H9)<>"Disqualified — Free Game",OR(INDEX('Game Records'!$E:$E,$H9)="",LOWER(INDEX('Game Records'!$E:$E,$H9)&"")="n/a")),"Game Type; ","")&IF(INDEX('Game Records'!$F:$F,$H9)="","Payment Type; ","")&IF(AND(INDEX('Game Records'!$U:$U,$H9)<>"Subscription",INDEX('Game Records'!$U:$U,$H9)<>"Free Game",INDEX('Game Records'!$U:$U,$H9)<>"Disqualified — Free Game",INDEX('Game Records'!$G:$G,$H9)=""),"Gross Pot; ","")&IF(AND(INDEX('Game Records'!$U:$U,$H9)<>"Free Game",INDEX('Game Records'!$U:$U,$H9)<>"Disqualified — Free Game",INDEX('Game Records'!$H:$H,$H9)=""),"Entry Fee; ","")&IF(AND(INDEX('Game Records'!$U:$U,$H9)<>"Subscription",INDEX('Game Records'!$U:$U,$H9)<>"Free Game",INDEX('Game Records'!$U:$U,$H9)<>"Disqualified — Free Game",INDEX('Game Records'!$I:$I,$H9)=""),"Eligible Players; ","")&IF(AND(INDEX('Game Records'!$U:$U,$H9)<>"Subscription",INDEX('Game Records'!$U:$U,$H9)<>"Free Game",INDEX('Game Records'!$U:$U,$H9)<>"Disqualified — Free Game",INDEX('Game Records'!$J:$J,$H9)=""),"Total Players; ","")&IF(AND(LOWER(INDEX('Game Records'!$D:$D,$H9)&"")="finalized",LOWER(INDEX('Game Records'!$L:$L,$H9)&"")<>"yes",INDEX('Game Records'!$U:$U,$H9)<>"Subscription",INDEX('Game Records'!$U:$U,$H9)<>"Free Game",INDEX('Game Records'!$U:$U,$H9)<>"Disqualified — Free Game",INDEX('Game Records'!$K:$K,$H9)=""),"Final Earned; ","")&IF(AND(LOWER(INDEX('Game Records'!$D:$D,$H9)&"")="finalized",INDEX('Game Records'!$U:$U,$H9)<>"Subscription",INDEX('Game Records'!$U:$U,$H9)<>"Free Game",INDEX('Game Records'!$U:$U,$H9)<>"Disqualified — Free Game",OR(INDEX('Game Records'!$L:$L,$H9)="",LOWER(INDEX('Game Records'!$L:$L,$H9)&"")="n/a")),"Disqualified Status; ","")&IF(AND(OR(LOWER(TRIM(INDEX('Game Records'!$F:$F,$H9)&""))="free game",INDEX('Game Records'!$U:$U,$H9)="Free Game",INDEX('Game Records'!$U:$U,$H9)="Disqualified — Free Game"),N(INDEX('Game Records'!$H:$H,$H9))<>0),"Free Game has a non-zero Entry Fee. Free Game records require a $0 Entry Fee; ","")) | G9: =IF($H9="","",IFERROR(INDEX('Game Records'!$M:$M,$H9),"")) | H9: =IF($H8="","",IFERROR(MATCH(1,INDEX((ROW('Game Records'!$U$5:$U$504)>$H8)*(('Game Records'!$A$5:$A$504<>"")+('Game Records'!$B$5:$B$504<>"")+('Game Records'!$C$5:$C$504<>"")+('Game Records'!$D$5:$D$504<>"")+('Game Records'!$E$5:$E$504<>"")+('Game Records'!$F$5:$F$504<>"")+('Game Records'!$G$5:$G$504<>"")+('Game Records'!$H$5:$H$504<>"")+('Game Records'!$I$5:$I$504<>"")+('Game Records'!$J$5:$J$504<>"")+('Game Records'!$K$5:$K$504<>"")+('Game Records'!$L$5:$L$504<>"")+('Game Records'!$M$5:$M$504<>"")>0)*('Game Records'!$U$5:$U$504<>"Subscription"),0),0)+4,"")) | I9: Disqualified Games | J9: =COUNTIF('Game Records'!$U$5:$U$504,"Disqualified") -> 0
A10: =IF($H10="","",ROWS($A$5:A10)) | B10: =IF($H10="","","G-"&TEXT($A10,"0000")) | C10: =IF($H10="","",IFERROR(INDEX('Game Records'!$A:$A,$H10),"")) | D10: =IF($H10="","",IFERROR(INDEX('Game Records'!$U:$U,$H10),"")) | E10: =IF($H10="","",IF($F10="","No Highlighted Fields","Highlighted Fields Present")) | F10: =IF($H10="","",IF(OR(NOT(ISFORMULA(INDEX('Game Records'!$N:$N,$H10))),NOT(ISFORMULA(INDEX('Game Records'!$O:$O,$H10))),NOT(ISFORMULA(INDEX('Game Records'!$P:$P,$H10))),NOT(ISFORMULA(INDEX('Game Records'!$Q:$Q,$H10))),NOT(ISFORMULA(INDEX('Game Records'!$R:$R,$H10))),NOT(ISFORMULA(INDEX('Game Records'!$S:$S,$H10))),NOT(ISFORMULA(INDEX('Game Records'!$T:$T,$H10))),NOT(ISFORMULA(INDEX('Game Records'!$U:$U,$H10))),NOT(ISFORMULA(INDEX('Game Records'!$V:$V,$H10))),NOT(ISFORMULA(INDEX('Game Records'!$W:$W,$H10))),NOT(ISFORMULA(INDEX('Game Records'!$X:$X,$H10))),NOT(ISFORMULA(INDEX('Game Records'!$Y:$Y,$H10))),NOT(ISFORMULA(INDEX('Game Records'!$Z:$Z,$H10)))),"Formula columns missing; ","")&IF(INDEX('Game Records'!$B:$B,$H10)="","Start Date; ","")&IF(INDEX('Game Records'!$C:$C,$H10)="","End Date; ","")&IF(AND(INDEX('Game Records'!$U:$U,$H10)<>"Subscription",INDEX('Game Records'!$U:$U,$H10)<>"Free Game",INDEX('Game Records'!$U:$U,$H10)<>"Disqualified — Free Game",OR(INDEX('Game Records'!$D:$D,$H10)="",LOWER(INDEX('Game Records'!$D:$D,$H10)&"")="n/a")),"Entry Mode; ","")&IF(AND(INDEX('Game Records'!$U:$U,$H10)<>"Subscription",INDEX('Game Records'!$U:$U,$H10)<>"Free Game",INDEX('Game Records'!$U:$U,$H10)<>"Disqualified — Free Game",OR(INDEX('Game Records'!$E:$E,$H10)="",LOWER(INDEX('Game Records'!$E:$E,$H10)&"")="n/a")),"Game Type; ","")&IF(INDEX('Game Records'!$F:$F,$H10)="","Payment Type; ","")&IF(AND(INDEX('Game Records'!$U:$U,$H10)<>"Subscription",INDEX('Game Records'!$U:$U,$H10)<>"Free Game",INDEX('Game Records'!$U:$U,$H10)<>"Disqualified — Free Game",INDEX('Game Records'!$G:$G,$H10)=""),"Gross Pot; ","")&IF(AND(INDEX('Game Records'!$U:$U,$H10)<>"Free Game",INDEX('Game Records'!$U:$U,$H10)<>"Disqualified — Free Game",INDEX('Game Records'!$H:$H,$H10)=""),"Entry Fee; ","")&IF(AND(INDEX('Game Records'!$U:$U,$H10)<>"Subscription",INDEX('Game Records'!$U:$U,$H10)<>"Free Game",INDEX('Game Records'!$U:$U,$H10)<>"Disqualified — Free Game",INDEX('Game Records'!$I:$I,$H10)=""),"Eligible Players; ","")&IF(AND(INDEX('Game Records'!$U:$U,$H10)<>"Subscription",INDEX('Game Records'!$U:$U,$H10)<>"Free Game",INDEX('Game Records'!$U:$U,$H10)<>"Disqualified — Free Game",INDEX('Game Records'!$J:$J,$H10)=""),"Total Players; ","")&IF(AND(LOWER(INDEX('Game Records'!$D:$D,$H10)&"")="finalized",LOWER(INDEX('Game Records'!$L:$L,$H10)&"")<>"yes",INDEX('Game Records'!$U:$U,$H10)<>"Subscription",INDEX('Game Records'!$U:$U,$H10)<>"Free Game",INDEX('Game Records'!$U:$U,$H10)<>"Disqualified — Free Game",INDEX('Game Records'!$K:$K,$H10)=""),"Final Earned; ","")&IF(AND(LOWER(INDEX('Game Records'!$D:$D,$H10)&"")="finalized",INDEX('Game Records'!$U:$U,$H10)<>"Subscription",INDEX('Game Records'!$U:$U,$H10)<>"Free Game",INDEX('Game Records'!$U:$U,$H10)<>"Disqualified — Free Game",OR(INDEX('Game Records'!$L:$L,$H10)="",LOWER(INDEX('Game Records'!$L:$L,$H10)&"")="n/a")),"Disqualified Status; ","")&IF(AND(OR(LOWER(TRIM(INDEX('Game Records'!$F:$F,$H10)&""))="free game",INDEX('Game Records'!$U:$U,$H10)="Free Game",INDEX('Game Records'!$U:$U,$H10)="Disqualified — Free Game"),N(INDEX('Game Records'!$H:$H,$H10))<>0),"Free Game has a non-zero Entry Fee. Free Game records require a $0 Entry Fee; ","")) | G10: =IF($H10="","",IFERROR(INDEX('Game Records'!$M:$M,$H10),"")) | H10: =IF($H9="","",IFERROR(MATCH(1,INDEX((ROW('Game Records'!$U$5:$U$504)>$H9)*(('Game Records'!$A$5:$A$504<>"")+('Game Records'!$B$5:$B$504<>"")+('Game Records'!$C$5:$C$504<>"")+('Game Records'!$D$5:$D$504<>"")+('Game Records'!$E$5:$E$504<>"")+('Game Records'!$F$5:$F$504<>"")+('Game Records'!$G$5:$G$504<>"")+('Game Records'!$H$5:$H$504<>"")+('Game Records'!$I$5:$I$504<>"")+('Game Records'!$J$5:$J$504<>"")+('Game Records'!$K$5:$K$504<>"")+('Game Records'!$L$5:$L$504<>"")+('Game Records'!$M$5:$M$504<>"")>0)*('Game Records'!$U$5:$U$504<>"Subscription"),0),0)+4,"")) | I10: Free Games | J10: =COUNTIF('Game Records'!$U$5:$U$504,"Free Game")+COUNTIF('Game Records'!$U$5:$U$504,"Disqualified — Free Game") -> 0
A11: =IF($H11="","",ROWS($A$5:A11)) | B11: =IF($H11="","","G-"&TEXT($A11,"0000")) | C11: =IF($H11="","",IFERROR(INDEX('Game Records'!$A:$A,$H11),"")) | D11: =IF($H11="","",IFERROR(INDEX('Game Records'!$U:$U,$H11),"")) | E11: =IF($H11="","",IF($F11="","No Highlighted Fields","Highlighted Fields Present")) | F11: =IF($H11="","",IF(OR(NOT(ISFORMULA(INDEX('Game Records'!$N:$N,$H11))),NOT(ISFORMULA(INDEX('Game Records'!$O:$O,$H11))),NOT(ISFORMULA(INDEX('Game Records'!$P:$P,$H11))),NOT(ISFORMULA(INDEX('Game Records'!$Q:$Q,$H11))),NOT(ISFORMULA(INDEX('Game Records'!$R:$R,$H11))),NOT(ISFORMULA(INDEX('Game Records'!$S:$S,$H11))),NOT(ISFORMULA(INDEX('Game Records'!$T:$T,$H11))),NOT(ISFORMULA(INDEX('Game Records'!$U:$U,$H11))),NOT(ISFORMULA(INDEX('Game Records'!$V:$V,$H11))),NOT(ISFORMULA(INDEX('Game Records'!$W:$W,$H11))),NOT(ISFORMULA(INDEX('Game Records'!$X:$X,$H11))),NOT(ISFORMULA(INDEX('Game Records'!$Y:$Y,$H11))),NOT(ISFORMULA(INDEX('Game Records'!$Z:$Z,$H11)))),"Formula columns missing; ","")&IF(INDEX('Game Records'!$B:$B,$H11)="","Start Date; ","")&IF(INDEX('Game Records'!$C:$C,$H11)="","End Date; ","")&IF(AND(INDEX('Game Records'!$U:$U,$H11)<>"Subscription",INDEX('Game Records'!$U:$U,$H11)<>"Free Game",INDEX('Game Records'!$U:$U,$H11)<>"Disqualified — Free Game",OR(INDEX('Game Records'!$D:$D,$H11)="",LOWER(INDEX('Game Records'!$D:$D,$H11)&"")="n/a")),"Entry Mode; ","")&IF(AND(INDEX('Game Records'!$U:$U,$H11)<>"Subscription",INDEX('Game Records'!$U:$U,$H11)<>"Free Game",INDEX('Game Records'!$U:$U,$H11)<>"Disqualified — Free Game",OR(INDEX('Game Records'!$E:$E,$H11)="",LOWER(INDEX('Game Records'!$E:$E,$H11)&"")="n/a")),"Game Type; ","")&IF(INDEX('Game Records'!$F:$F,$H11)="","Payment Type; ","")&IF(AND(INDEX('Game Records'!$U:$U,$H11)<>"Subscription",INDEX('Game Records'!$U:$U,$H11)<>"Free Game",INDEX('Game Records'!$U:$U,$H11)<>"Disqualified — Free Game",INDEX('Game Records'!$G:$G,$H11)=""),"Gross Pot; ","")&IF(AND(INDEX('Game Records'!$U:$U,$H11)<>"Free Game",INDEX('Game Records'!$U:$U,$H11)<>"Disqualified — Free Game",INDEX('Game Records'!$H:$H,$H11)=""),"Entry Fee; ","")&IF(AND(INDEX('Game Records'!$U:$U,$H11)<>"Subscription",INDEX('Game Records'!$U:$U,$H11)<>"Free Game",INDEX('Game Records'!$U:$U,$H11)<>"Disqualified — Free Game",INDEX('Game Records'!$I:$I,$H11)=""),"Eligible Players; ","")&IF(AND(INDEX('Game Records'!$U:$U,$H11)<>"Subscription",INDEX('Game Records'!$U:$U,$H11)<>"Free Game",INDEX('Game Records'!$U:$U,$H11)<>"Disqualified — Free Game",INDEX('Game Records'!$J:$J,$H11)=""),"Total Players; ","")&IF(AND(LOWER(INDEX('Game Records'!$D:$D,$H11)&"")="finalized",LOWER(INDEX('Game Records'!$L:$L,$H11)&"")<>"yes",INDEX('Game Records'!$U:$U,$H11)<>"Subscription",INDEX('Game Records'!$U:$U,$H11)<>"Free Game",INDEX('Game Records'!$U:$U,$H11)<>"Disqualified — Free Game",INDEX('Game Records'!$K:$K,$H11)=""),"Final Earned; ","")&IF(AND(LOWER(INDEX('Game Records'!$D:$D,$H11)&"")="finalized",INDEX('Game Records'!$U:$U,$H11)<>"Subscription",INDEX('Game Records'!$U:$U,$H11)<>"Free Game",INDEX('Game Records'!$U:$U,$H11)<>"Disqualified — Free Game",OR(INDEX('Game Records'!$L:$L,$H11)="",LOWER(INDEX('Game Records'!$L:$L,$H11)&"")="n/a")),"Disqualified Status; ","")&IF(AND(OR(LOWER(TRIM(INDEX('Game Records'!$F:$F,$H11)&""))="free game",INDEX('Game Records'!$U:$U,$H11)="Free Game",INDEX('Game Records'!$U:$U,$H11)="Disqualified — Free Game"),N(INDEX('Game Records'!$H:$H,$H11))<>0),"Free Game has a non-zero Entry Fee. Free Game records require a $0 Entry Fee; ","")) | G11: =IF($H11="","",IFERROR(INDEX('Game Records'!$M:$M,$H11),"")) | H11: =IF($H10="","",IFERROR(MATCH(1,INDEX((ROW('Game Records'!$U$5:$U$504)>$H10)*(('Game Records'!$A$5:$A$504<>"")+('Game Records'!$B$5:$B$504<>"")+('Game Records'!$C$5:$C$504<>"")+('Game Records'!$D$5:$D$504<>"")+('Game Records'!$E$5:$E$504<>"")+('Game Records'!$F$5:$F$504<>"")+('Game Records'!$G$5:$G$504<>"")+('Game Records'!$H$5:$H$504<>"")+('Game Records'!$I$5:$I$504<>"")+('Game Records'!$J$5:$J$504<>"")+('Game Records'!$K$5:$K$504<>"")+('Game Records'!$L$5:$L$504<>"")+('Game Records'!$M$5:$M$504<>"")>0)*('Game Records'!$U$5:$U$504<>"Subscription"),0),0)+4,"")) | I11: Points Games | J11: =COUNTIF('Game Records'!$F$5:$F$504,"Points") -> 0
A12: =IF($H12="","",ROWS($A$5:A12)) | B12: =IF($H12="","","G-"&TEXT($A12,"0000")) | C12: =IF($H12="","",IFERROR(INDEX('Game Records'!$A:$A,$H12),"")) | D12: =IF($H12="","",IFERROR(INDEX('Game Records'!$U:$U,$H12),"")) | E12: =IF($H12="","",IF($F12="","No Highlighted Fields","Highlighted Fields Present")) | F12: =IF($H12="","",IF(OR(NOT(ISFORMULA(INDEX('Game Records'!$N:$N,$H12))),NOT(ISFORMULA(INDEX('Game Records'!$O:$O,$H12))),NOT(ISFORMULA(INDEX('Game Records'!$P:$P,$H12))),NOT(ISFORMULA(INDEX('Game Records'!$Q:$Q,$H12))),NOT(ISFORMULA(INDEX('Game Records'!$R:$R,$H12))),NOT(ISFORMULA(INDEX('Game Records'!$S:$S,$H12))),NOT(ISFORMULA(INDEX('Game Records'!$T:$T,$H12))),NOT(ISFORMULA(INDEX('Game Records'!$U:$U,$H12))),NOT(ISFORMULA(INDEX('Game Records'!$V:$V,$H12))),NOT(ISFORMULA(INDEX('Game Records'!$W:$W,$H12))),NOT(ISFORMULA(INDEX('Game Records'!$X:$X,$H12))),NOT(ISFORMULA(INDEX('Game Records'!$Y:$Y,$H12))),NOT(ISFORMULA(INDEX('Game Records'!$Z:$Z,$H12)))),"Formula columns missing; ","")&IF(INDEX('Game Records'!$B:$B,$H12)="","Start Date; ","")&IF(INDEX('Game Records'!$C:$C,$H12)="","End Date; ","")&IF(AND(INDEX('Game Records'!$U:$U,$H12)<>"Subscription",INDEX('Game Records'!$U:$U,$H12)<>"Free Game",INDEX('Game Records'!$U:$U,$H12)<>"Disqualified — Free Game",OR(INDEX('Game Records'!$D:$D,$H12)="",LOWER(INDEX('Game Records'!$D:$D,$H12)&"")="n/a")),"Entry Mode; ","")&IF(AND(INDEX('Game Records'!$U:$U,$H12)<>"Subscription",INDEX('Game Records'!$U:$U,$H12)<>"Free Game",INDEX('Game Records'!$U:$U,$H12)<>"Disqualified — Free Game",OR(INDEX('Game Records'!$E:$E,$H12)="",LOWER(INDEX('Game Records'!$E:$E,$H12)&"")="n/a")),"Game Type; ","")&IF(INDEX('Game Records'!$F:$F,$H12)="","Payment Type; ","")&IF(AND(INDEX('Game Records'!$U:$U,$H12)<>"Subscription",INDEX('Game Records'!$U:$U,$H12)<>"Free Game",INDEX('Game Records'!$U:$U,$H12)<>"Disqualified — Free Game",INDEX('Game Records'!$G:$G,$H12)=""),"Gross Pot; ","")&IF(AND(INDEX('Game Records'!$U:$U,$H12)<>"Free Game",INDEX('Game Records'!$U:$U,$H12)<>"Disqualified — Free Game",INDEX('Game Records'!$H:$H,$H12)=""),"Entry Fee; ","")&IF(AND(INDEX('Game Records'!$U:$U,$H12)<>"Subscription",INDEX('Game Records'!$U:$U,$H12)<>"Free Game",INDEX('Game Records'!$U:$U,$H12)<>"Disqualified — Free Game",INDEX('Game Records'!$I:$I,$H12)=""),"Eligible Players; ","")&IF(AND(INDEX('Game Records'!$U:$U,$H12)<>"Subscription",INDEX('Game Records'!$U:$U,$H12)<>"Free Game",INDEX('Game Records'!$U:$U,$H12)<>"Disqualified — Free Game",INDEX('Game Records'!$J:$J,$H12)=""),"Total Players; ","")&IF(AND(LOWER(INDEX('Game Records'!$D:$D,$H12)&"")="finalized",LOWER(INDEX('Game Records'!$L:$L,$H12)&"")<>"yes",INDEX('Game Records'!$U:$U,$H12)<>"Subscription",INDEX('Game Records'!$U:$U,$H12)<>"Free Game",INDEX('Game Records'!$U:$U,$H12)<>"Disqualified — Free Game",INDEX('Game Records'!$K:$K,$H12)=""),"Final Earned; ","")&IF(AND(LOWER(INDEX('Game Records'!$D:$D,$H12)&"")="finalized",INDEX('Game Records'!$U:$U,$H12)<>"Subscription",INDEX('Game Records'!$U:$U,$H12)<>"Free Game",INDEX('Game Records'!$U:$U,$H12)<>"Disqualified — Free Game",OR(INDEX('Game Records'!$L:$L,$H12)="",LOWER(INDEX('Game Records'!$L:$L,$H12)&"")="n/a")),"Disqualified Status; ","")&IF(AND(OR(LOWER(TRIM(INDEX('Game Records'!$F:$F,$H12)&""))="free game",INDEX('Game Records'!$U:$U,$H12)="Free Game",INDEX('Game Records'!$U:$U,$H12)="Disqualified — Free Game"),N(INDEX('Game Records'!$H:$H,$H12))<>0),"Free Game has a non-zero Entry Fee. Free Game records require a $0 Entry Fee; ","")) | G12: =IF($H12="","",IFERROR(INDEX('Game Records'!$M:$M,$H12),"")) | H12: =IF($H11="","",IFERROR(MATCH(1,INDEX((ROW('Game Records'!$U$5:$U$504)>$H11)*(('Game Records'!$A$5:$A$504<>"")+('Game Records'!$B$5:$B$504<>"")+('Game Records'!$C$5:$C$504<>"")+('Game Records'!$D$5:$D$504<>"")+('Game Records'!$E$5:$E$504<>"")+('Game Records'!$F$5:$F$504<>"")+('Game Records'!$G$5:$G$504<>"")+('Game Records'!$H$5:$H$504<>"")+('Game Records'!$I$5:$I$504<>"")+('Game Records'!$J$5:$J$504<>"")+('Game Records'!$K$5:$K$504<>"")+('Game Records'!$L$5:$L$504<>"")+('Game Records'!$M$5:$M$504<>"")>0)*('Game Records'!$U$5:$U$504<>"Subscription"),0),0)+4,"")) | I12: Cash / Hybrid Games | J12: =COUNTIF('Game Records'!$F$5:$F$504,"Cash")+COUNTIF('Game Records'!$F$5:$F$504,"Hybrid") -> 0
A13: =IF($H13="","",ROWS($A$5:A13)) | B13: =IF($H13="","","G-"&TEXT($A13,"0000")) | C13: =IF($H13="","",IFERROR(INDEX('Game Records'!$A:$A,$H13),"")) | D13: =IF($H13="","",IFERROR(INDEX('Game Records'!$U:$U,$H13),"")) | E13: =IF($H13="","",IF($F13="","No Highlighted Fields","Highlighted Fields Present")) | F13: =IF($H13="","",IF(OR(NOT(ISFORMULA(INDEX('Game Records'!$N:$N,$H13))),NOT(ISFORMULA(INDEX('Game Records'!$O:$O,$H13))),NOT(ISFORMULA(INDEX('Game Records'!$P:$P,$H13))),NOT(ISFORMULA(INDEX('Game Records'!$Q:$Q,$H13))),NOT(ISFORMULA(INDEX('Game Records'!$R:$R,$H13))),NOT(ISFORMULA(INDEX('Game Records'!$S:$S,$H13))),NOT(ISFORMULA(INDEX('Game Records'!$T:$T,$H13))),NOT(ISFORMULA(INDEX('Game Records'!$U:$U,$H13))),NOT(ISFORMULA(INDEX('Game Records'!$V:$V,$H13))),NOT(ISFORMULA(INDEX('Game Records'!$W:$W,$H13))),NOT(ISFORMULA(INDEX('Game Records'!$X:$X,$H13))),NOT(ISFORMULA(INDEX('Game Records'!$Y:$Y,$H13))),NOT(ISFORMULA(INDEX('Game Records'!$Z:$Z,$H13)))),"Formula columns missing; ","")&IF(INDEX('Game Records'!$B:$B,$H13)="","Start Date; ","")&IF(INDEX('Game Records'!$C:$C,$H13)="","End Date; ","")&IF(AND(INDEX('Game Records'!$U:$U,$H13)<>"Subscription",INDEX('Game Records'!$U:$U,$H13)<>"Free Game",INDEX('Game Records'!$U:$U,$H13)<>"Disqualified — Free Game",OR(INDEX('Game Records'!$D:$D,$H13)="",LOWER(INDEX('Game Records'!$D:$D,$H13)&"")="n/a")),"Entry Mode; ","")&IF(AND(INDEX('Game Records'!$U:$U,$H13)<>"Subscription",INDEX('Game Records'!$U:$U,$H13)<>"Free Game",INDEX('Game Records'!$U:$U,$H13)<>"Disqualified — Free Game",OR(INDEX('Game Records'!$E:$E,$H13)="",LOWER(INDEX('Game Records'!$E:$E,$H13)&"")="n/a")),"Game Type; ","")&IF(INDEX('Game Records'!$F:$F,$H13)="","Payment Type; ","")&IF(AND(INDEX('Game Records'!$U:$U,$H13)<>"Subscription",INDEX('Game Records'!$U:$U,$H13)<>"Free Game",INDEX('Game Records'!$U:$U,$H13)<>"Disqualified — Free Game",INDEX('Game Records'!$G:$G,$H13)=""),"Gross Pot; ","")&IF(AND(INDEX('Game Records'!$U:$U,$H13)<>"Free Game",INDEX('Game Records'!$U:$U,$H13)<>"Disqualified — Free Game",INDEX('Game Records'!$H:$H,$H13)=""),"Entry Fee; ","")&IF(AND(INDEX('Game Records'!$U:$U,$H13)<>"Subscription",INDEX('Game Records'!$U:$U,$H13)<>"Free Game",INDEX('Game Records'!$U:$U,$H13)<>"Disqualified — Free Game",INDEX('Game Records'!$I:$I,$H13)=""),"Eligible Players; ","")&IF(AND(INDEX('Game Records'!$U:$U,$H13)<>"Subscription",INDEX('Game Records'!$U:$U,$H13)<>"Free Game",INDEX('Game Records'!$U:$U,$H13)<>"Disqualified — Free Game",INDEX('Game Records'!$J:$J,$H13)=""),"Total Players; ","")&IF(AND(LOWER(INDEX('Game Records'!$D:$D,$H13)&"")="finalized",LOWER(INDEX('Game Records'!$L:$L,$H13)&"")<>"yes",INDEX('Game Records'!$U:$U,$H13)<>"Subscription",INDEX('Game Records'!$U:$U,$H13)<>"Free Game",INDEX('Game Records'!$U:$U,$H13)<>"Disqualified — Free Game",INDEX('Game Records'!$K:$K,$H13)=""),"Final Earned; ","")&IF(AND(LOWER(INDEX('Game Records'!$D:$D,$H13)&"")="finalized",INDEX('Game Records'!$U:$U,$H13)<>"Subscription",INDEX('Game Records'!$U:$U,$H13)<>"Free Game",INDEX('Game Records'!$U:$U,$H13)<>"Disqualified — Free Game",OR(INDEX('Game Records'!$L:$L,$H13)="",LOWER(INDEX('Game Records'!$L:$L,$H13)&"")="n/a")),"Disqualified Status; ","")&IF(AND(OR(LOWER(TRIM(INDEX('Game Records'!$F:$F,$H13)&""))="free game",INDEX('Game Records'!$U:$U,$H13)="Free Game",INDEX('Game Records'!$U:$U,$H13)="Disqualified — Free Game"),N(INDEX('Game Records'!$H:$H,$H13))<>0),"Free Game has a non-zero Entry Fee. Free Game records require a $0 Entry Fee; ","")) | G13: =IF($H13="","",IFERROR(INDEX('Game Records'!$M:$M,$H13),"")) | H13: =IF($H12="","",IFERROR(MATCH(1,INDEX((ROW('Game Records'!$U$5:$U$504)>$H12)*(('Game Records'!$A$5:$A$504<>"")+('Game Records'!$B$5:$B$504<>"")+('Game Records'!$C$5:$C$504<>"")+('Game Records'!$D$5:$D$504<>"")+('Game Records'!$E$5:$E$504<>"")+('Game Records'!$F$5:$F$504<>"")+('Game Records'!$G$5:$G$504<>"")+('Game Records'!$H$5:$H$504<>"")+('Game Records'!$I$5:$I$504<>"")+('Game Records'!$J$5:$J$504<>"")+('Game Records'!$K$5:$K$504<>"")+('Game Records'!$L$5:$L$504<>"")+('Game Records'!$M$5:$M$504<>"")>0)*('Game Records'!$U$5:$U$504<>"Subscription"),0),0)+4,""))
A14: =IF($H14="","",ROWS($A$5:A14)) | B14: =IF($H14="","","G-"&TEXT($A14,"0000")) | C14: =IF($H14="","",IFERROR(INDEX('Game Records'!$A:$A,$H14),"")) | D14: =IF($H14="","",IFERROR(INDEX('Game Records'!$U:$U,$H14),"")) | E14: =IF($H14="","",IF($F14="","No Highlighted Fields","Highlighted Fields Present")) | F14: =IF($H14="","",IF(OR(NOT(ISFORMULA(INDEX('Game Records'!$N:$N,$H14))),NOT(ISFORMULA(INDEX('Game Records'!$O:$O,$H14))),NOT(ISFORMULA(INDEX('Game Records'!$P:$P,$H14))),NOT(ISFORMULA(INDEX('Game Records'!$Q:$Q,$H14))),NOT(ISFORMULA(INDEX('Game Records'!$R:$R,$H14))),NOT(ISFORMULA(INDEX('Game Records'!$S:$S,$H14))),NOT(ISFORMULA(INDEX('Game Records'!$T:$T,$H14))),NOT(ISFORMULA(INDEX('Game Records'!$U:$U,$H14))),NOT(ISFORMULA(INDEX('Game Records'!$V:$V,$H14))),NOT(ISFORMULA(INDEX('Game Records'!$W:$W,$H14))),NOT(ISFORMULA(INDEX('Game Records'!$X:$X,$H14))),NOT(ISFORMULA(INDEX('Game Records'!$Y:$Y,$H14))),NOT(ISFORMULA(INDEX('Game Records'!$Z:$Z,$H14)))),"Formula columns missing; ","")&IF(INDEX('Game Records'!$B:$B,$H14)="","Start Date; ","")&IF(INDEX('Game Records'!$C:$C,$H14)="","End Date; ","")&IF(AND(INDEX('Game Records'!$U:$U,$H14)<>"Subscription",INDEX('Game Records'!$U:$U,$H14)<>"Free Game",INDEX('Game Records'!$U:$U,$H14)<>"Disqualified — Free Game",OR(INDEX('Game Records'!$D:$D,$H14)="",LOWER(INDEX('Game Records'!$D:$D,$H14)&"")="n/a")),"Entry Mode; ","")&IF(AND(INDEX('Game Records'!$U:$U,$H14)<>"Subscription",INDEX('Game Records'!$U:$U,$H14)<>"Free Game",INDEX('Game Records'!$U:$U,$H14)<>"Disqualified — Free Game",OR(INDEX('Game Records'!$E:$E,$H14)="",LOWER(INDEX('Game Records'!$E:$E,$H14)&"")="n/a")),"Game Type; ","")&IF(INDEX('Game Records'!$F:$F,$H14)="","Payment Type; ","")&IF(AND(INDEX('Game Records'!$U:$U,$H14)<>"Subscription",INDEX('Game Records'!$U:$U,$H14)<>"Free Game",INDEX('Game Records'!$U:$U,$H14)<>"Disqualified — Free Game",INDEX('Game Records'!$G:$G,$H14)=""),"Gross Pot; ","")&IF(AND(INDEX('Game Records'!$U:$U,$H14)<>"Free Game",INDEX('Game Records'!$U:$U,$H14)<>"Disqualified — Free Game",INDEX('Game Records'!$H:$H,$H14)=""),"Entry Fee; ","")&IF(AND(INDEX('Game Records'!$U:$U,$H14)<>"Subscription",INDEX('Game Records'!$U:$U,$H14)<>"Free Game",INDEX('Game Records'!$U:$U,$H14)<>"Disqualified — Free Game",INDEX('Game Records'!$I:$I,$H14)=""),"Eligible Players; ","")&IF(AND(INDEX('Game Records'!$U:$U,$H14)<>"Subscription",INDEX('Game Records'!$U:$U,$H14)<>"Free Game",INDEX('Game Records'!$U:$U,$H14)<>"Disqualified — Free Game",INDEX('Game Records'!$J:$J,$H14)=""),"Total Players; ","")&IF(AND(LOWER(INDEX('Game Records'!$D:$D,$H14)&"")="finalized",LOWER(INDEX('Game Records'!$L:$L,$H14)&"")<>"yes",INDEX('Game Records'!$U:$U,$H14)<>"Subscription",INDEX('Game Records'!$U:$U,$H14)<>"Free Game",INDEX('Game Records'!$U:$U,$H14)<>"Disqualified — Free Game",INDEX('Game Records'!$K:$K,$H14)=""),"Final Earned; ","")&IF(AND(LOWER(INDEX('Game Records'!$D:$D,$H14)&"")="finalized",INDEX('Game Records'!$U:$U,$H14)<>"Subscription",INDEX('Game Records'!$U:$U,$H14)<>"Free Game",INDEX('Game Records'!$U:$U,$H14)<>"Disqualified — Free Game",OR(INDEX('Game Records'!$L:$L,$H14)="",LOWER(INDEX('Game Records'!$L:$L,$H14)&"")="n/a")),"Disqualified Status; ","")&IF(AND(OR(LOWER(TRIM(INDEX('Game Records'!$F:$F,$H14)&""))="free game",INDEX('Game Records'!$U:$U,$H14)="Free Game",INDEX('Game Records'!$U:$U,$H14)="Disqualified — Free Game"),N(INDEX('Game Records'!$H:$H,$H14))<>0),"Free Game has a non-zero Entry Fee. Free Game records require a $0 Entry Fee; ","")) | G14: =IF($H14="","",IFERROR(INDEX('Game Records'!$M:$M,$H14),"")) | H14: =IF($H13="","",IFERROR(MATCH(1,INDEX((ROW('Game Records'!$U$5:$U$504)>$H13)*(('Game Records'!$A$5:$A$504<>"")+('Game Records'!$B$5:$B$504<>"")+('Game Records'!$C$5:$C$504<>"")+('Game Records'!$D$5:$D$504<>"")+('Game Records'!$E$5:$E$504<>"")+('Game Records'!$F$5:$F$504<>"")+('Game Records'!$G$5:$G$504<>"")+('Game Records'!$H$5:$H$504<>"")+('Game Records'!$I$5:$I$504<>"")+('Game Records'!$J$5:$J$504<>"")+('Game Records'!$K$5:$K$504<>"")+('Game Records'!$L$5:$L$504<>"")+('Game Records'!$M$5:$M$504<>"")>0)*('Game Records'!$U$5:$U$504<>"Subscription"),0),0)+4,""))
A15: =IF($H15="","",ROWS($A$5:A15)) | B15: =IF($H15="","","G-"&TEXT($A15,"0000")) | C15: =IF($H15="","",IFERROR(INDEX('Game Records'!$A:$A,$H15),"")) | D15: =IF($H15="","",IFERROR(INDEX('Game Records'!$U:$U,$H15),"")) | E15: =IF($H15="","",IF($F15="","No Highlighted Fields","Highlighted Fields Present")) | F15: =IF($H15="","",IF(OR(NOT(ISFORMULA(INDEX('Game Records'!$N:$N,$H15))),NOT(ISFORMULA(INDEX('Game Records'!$O:$O,$H15))),NOT(ISFORMULA(INDEX('Game Records'!$P:$P,$H15))),NOT(ISFORMULA(INDEX('Game Records'!$Q:$Q,$H15))),NOT(ISFORMULA(INDEX('Game Records'!$R:$R,$H15))),NOT(ISFORMULA(INDEX('Game Records'!$S:$S,$H15))),NOT(ISFORMULA(INDEX('Game Records'!$T:$T,$H15))),NOT(ISFORMULA(INDEX('Game Records'!$U:$U,$H15))),NOT(ISFORMULA(INDEX('Game Records'!$V:$V,$H15))),NOT(ISFORMULA(INDEX('Game Records'!$W:$W,$H15))),NOT(ISFORMULA(INDEX('Game Records'!$X:$X,$H15))),NOT(ISFORMULA(INDEX('Game Records'!$Y:$Y,$H15))),NOT(ISFORMULA(INDEX('Game Records'!$Z:$Z,$H15)))),"Formula columns missing; ","")&IF(INDEX('Game Records'!$B:$B,$H15)="","Start Date; ","")&IF(INDEX('Game Records'!$C:$C,$H15)="","End Date; ","")&IF(AND(INDEX('Game Records'!$U:$U,$H15)<>"Subscription",INDEX('Game Records'!$U:$U,$H15)<>"Free Game",INDEX('Game Records'!$U:$U,$H15)<>"Disqualified — Free Game",OR(INDEX('Game Records'!$D:$D,$H15)="",LOWER(INDEX('Game Records'!$D:$D,$H15)&"")="n/a")),"Entry Mode; ","")&IF(AND(INDEX('Game Records'!$U:$U,$H15)<>"Subscription",INDEX('Game Records'!$U:$U,$H15)<>"Free Game",INDEX('Game Records'!$U:$U,$H15)<>"Disqualified — Free Game",OR(INDEX('Game Records'!$E:$E,$H15)="",LOWER(INDEX('Game Records'!$E:$E,$H15)&"")="n/a")),"Game Type; ","")&IF(INDEX('Game Records'!$F:$F,$H15)="","Payment Type; ","")&IF(AND(INDEX('Game Records'!$U:$U,$H15)<>"Subscription",INDEX('Game Records'!$U:$U,$H15)<>"Free Game",INDEX('Game Records'!$U:$U,$H15)<>"Disqualified — Free Game",INDEX('Game Records'!$G:$G,$H15)=""),"Gross Pot; ","")&IF(AND(INDEX('Game Records'!$U:$U,$H15)<>"Free Game",INDEX('Game Records'!$U:$U,$H15)<>"Disqualified — Free Game",INDEX('Game Records'!$H:$H,$H15)=""),"Entry Fee; ","")&IF(AND(INDEX('Game Records'!$U:$U,$H15)<>"Subscription",INDEX('Game Records'!$U:$U,$H15)<>"Free Game",INDEX('Game Records'!$U:$U,$H15)<>"Disqualified — Free Game",INDEX('Game Records'!$I:$I,$H15)=""),"Eligible Players; ","")&IF(AND(INDEX('Game Records'!$U:$U,$H15)<>"Subscription",INDEX('Game Records'!$U:$U,$H15)<>"Free Game",INDEX('Game Records'!$U:$U,$H15)<>"Disqualified — Free Game",INDEX('Game Records'!$J:$J,$H15)=""),"Total Players; ","")&IF(AND(LOWER(INDEX('Game Records'!$D:$D,$H15)&"")="finalized",LOWER(INDEX('Game Records'!$L:$L,$H15)&"")<>"yes",INDEX('Game Records'!$U:$U,$H15)<>"Subscription",INDEX('Game Records'!$U:$U,$H15)<>"Free Game",INDEX('Game Records'!$U:$U,$H15)<>"Disqualified — Free Game",INDEX('Game Records'!$K:$K,$H15)=""),"Final Earned; ","")&IF(AND(LOWER(INDEX('Game Records'!$D:$D,$H15)&"")="finalized",INDEX('Game Records'!$U:$U,$H15)<>"Subscription",INDEX('Game Records'!$U:$U,$H15)<>"Free Game",INDEX('Game Records'!$U:$U,$H15)<>"Disqualified — Free Game",OR(INDEX('Game Records'!$L:$L,$H15)="",LOWER(INDEX('Game Records'!$L:$L,$H15)&"")="n/a")),"Disqualified Status; ","")&IF(AND(OR(LOWER(TRIM(INDEX('Game Records'!$F:$F,$H15)&""))="free game",INDEX('Game Records'!$U:$U,$H15)="Free Game",INDEX('Game Records'!$U:$U,$H15)="Disqualified — Free Game"),N(INDEX('Game Records'!$H:$H,$H15))<>0),"Free Game has a non-zero Entry Fee. Free Game records require a $0 Entry Fee; ","")) | G15: =IF($H15="","",IFERROR(INDEX('Game Records'!$M:$M,$H15),"")) | H15: =IF($H14="","",IFERROR(MATCH(1,INDEX((ROW('Game Records'!$U$5:$U$504)>$H14)*(('Game Records'!$A$5:$A$504<>"")+('Game Records'!$B$5:$B$504<>"")+('Game Records'!$C$5:$C$504<>"")+('Game Records'!$D$5:$D$504<>"")+('Game Records'!$E$5:$E$504<>"")+('Game Records'!$F$5:$F$504<>"")+('Game Records'!$G$5:$G$504<>"")+('Game Records'!$H$5:$H$504<>"")+('Game Records'!$I$5:$I$504<>"")+('Game Records'!$J$5:$J$504<>"")+('Game Records'!$K$5:$K$504<>"")+('Game Records'!$L$5:$L$504<>"")+('Game Records'!$M$5:$M$504<>"")>0)*('Game Records'!$U$5:$U$504<>"Subscription"),0),0)+4,""))
A16: =IF($H16="","",ROWS($A$5:A16)) | B16: =IF($H16="","","G-"&TEXT($A16,"0000")) | C16: =IF($H16="","",IFERROR(INDEX('Game Records'!$A:$A,$H16),"")) | D16: =IF($H16="","",IFERROR(INDEX('Game Records'!$U:$U,$H16),"")) | E16: =IF($H16="","",IF($F16="","No Highlighted Fields","Highlighted Fields Present")) | F16: =IF($H16="","",IF(OR(NOT(ISFORMULA(INDEX('Game Records'!$N:$N,$H16))),NOT(ISFORMULA(INDEX('Game Records'!$O:$O,$H16))),NOT(ISFORMULA(INDEX('Game Records'!$P:$P,$H16))),NOT(ISFORMULA(INDEX('Game Records'!$Q:$Q,$H16))),NOT(ISFORMULA(INDEX('Game Records'!$R:$R,$H16))),NOT(ISFORMULA(INDEX('Game Records'!$S:$S,$H16))),NOT(ISFORMULA(INDEX('Game Records'!$T:$T,$H16))),NOT(ISFORMULA(INDEX('Game Records'!$U:$U,$H16))),NOT(ISFORMULA(INDEX('Game Records'!$V:$V,$H16))),NOT(ISFORMULA(INDEX('Game Records'!$W:$W,$H16))),NOT(ISFORMULA(INDEX('Game Records'!$X:$X,$H16))),NOT(ISFORMULA(INDEX('Game Records'!$Y:$Y,$H16))),NOT(ISFORMULA(INDEX('Game Records'!$Z:$Z,$H16)))),"Formula columns missing; ","")&IF(INDEX('Game Records'!$B:$B,$H16)="","Start Date; ","")&IF(INDEX('Game Records'!$C:$C,$H16)="","End Date; ","")&IF(AND(INDEX('Game Records'!$U:$U,$H16)<>"Subscription",INDEX('Game Records'!$U:$U,$H16)<>"Free Game",INDEX('Game Records'!$U:$U,$H16)<>"Disqualified — Free Game",OR(INDEX('Game Records'!$D:$D,$H16)="",LOWER(INDEX('Game Records'!$D:$D,$H16)&"")="n/a")),"Entry Mode; ","")&IF(AND(INDEX('Game Records'!$U:$U,$H16)<>"Subscription",INDEX('Game Records'!$U:$U,$H16)<>"Free Game",INDEX('Game Records'!$U:$U,$H16)<>"Disqualified — Free Game",OR(INDEX('Game Records'!$E:$E,$H16)="",LOWER(INDEX('Game Records'!$E:$E,$H16)&"")="n/a")),"Game Type; ","")&IF(INDEX('Game Records'!$F:$F,$H16)="","Payment Type; ","")&IF(AND(INDEX('Game Records'!$U:$U,$H16)<>"Subscription",INDEX('Game Records'!$U:$U,$H16)<>"Free Game",INDEX('Game Records'!$U:$U,$H16)<>"Disqualified — Free Game",INDEX('Game Records'!$G:$G,$H16)=""),"Gross Pot; ","")&IF(AND(INDEX('Game Records'!$U:$U,$H16)<>"Free Game",INDEX('Game Records'!$U:$U,$H16)<>"Disqualified — Free Game",INDEX('Game Records'!$H:$H,$H16)=""),"Entry Fee; ","")&IF(AND(INDEX('Game Records'!$U:$U,$H16)<>"Subscription",INDEX('Game Records'!$U:$U,$H16)<>"Free Game",INDEX('Game Records'!$U:$U,$H16)<>"Disqualified — Free Game",INDEX('Game Records'!$I:$I,$H16)=""),"Eligible Players; ","")&IF(AND(INDEX('Game Records'!$U:$U,$H16)<>"Subscription",INDEX('Game Records'!$U:$U,$H16)<>"Free Game",INDEX('Game Records'!$U:$U,$H16)<>"Disqualified — Free Game",INDEX('Game Records'!$J:$J,$H16)=""),"Total Players; ","")&IF(AND(LOWER(INDEX('Game Records'!$D:$D,$H16)&"")="finalized",LOWER(INDEX('Game Records'!$L:$L,$H16)&"")<>"yes",INDEX('Game Records'!$U:$U,$H16)<>"Subscription",INDEX('Game Records'!$U:$U,$H16)<>"Free Game",INDEX('Game Records'!$U:$U,$H16)<>"Disqualified — Free Game",INDEX('Game Records'!$K:$K,$H16)=""),"Final Earned; ","")&IF(AND(LOWER(INDEX('Game Records'!$D:$D,$H16)&"")="finalized",INDEX('Game Records'!$U:$U,$H16)<>"Subscription",INDEX('Game Records'!$U:$U,$H16)<>"Free Game",INDEX('Game Records'!$U:$U,$H16)<>"Disqualified — Free Game",OR(INDEX('Game Records'!$L:$L,$H16)="",LOWER(INDEX('Game Records'!$L:$L,$H16)&"")="n/a")),"Disqualified Status; ","")&IF(AND(OR(LOWER(TRIM(INDEX('Game Records'!$F:$F,$H16)&""))="free game",INDEX('Game Records'!$U:$U,$H16)="Free Game",INDEX('Game Records'!$U:$U,$H16)="Disqualified — Free Game"),N(INDEX('Game Records'!$H:$H,$H16))<>0),"Free Game has a non-zero Entry Fee. Free Game records require a $0 Entry Fee; ","")) | G16: =IF($H16="","",IFERROR(INDEX('Game Records'!$M:$M,$H16),"")) | H16: =IF($H15="","",IFERROR(MATCH(1,INDEX((ROW('Game Records'!$U$5:$U$504)>$H15)*(('Game Records'!$A$5:$A$504<>"")+('Game Records'!$B$5:$B$504<>"")+('Game Records'!$C$5:$C$504<>"")+('Game Records'!$D$5:$D$504<>"")+('Game Records'!$E$5:$E$504<>"")+('Game Records'!$F$5:$F$504<>"")+('Game Records'!$G$5:$G$504<>"")+('Game Records'!$H$5:$H$504<>"")+('Game Records'!$I$5:$I$504<>"")+('Game Records'!$J$5:$J$504<>"")+('Game Records'!$K$5:$K$504<>"")+('Game Records'!$L$5:$L$504<>"")+('Game Records'!$M$5:$M$504<>"")>0)*('Game Records'!$U$5:$U$504<>"Subscription"),0),0)+4,""))
A17: =IF($H17="","",ROWS($A$5:A17)) | B17: =IF($H17="","","G-"&TEXT($A17,"0000")) | C17: =IF($H17="","",IFERROR(INDEX('Game Records'!$A:$A,$H17),"")) | D17: =IF($H17="","",IFERROR(INDEX('Game Records'!$U:$U,$H17),"")) | E17: =IF($H17="","",IF($F17="","No Highlighted Fields","Highlighted Fields Present")) | F17: =IF($H17="","",IF(OR(NOT(ISFORMULA(INDEX('Game Records'!$N:$N,$H17))),NOT(ISFORMULA(INDEX('Game Records'!$O:$O,$H17))),NOT(ISFORMULA(INDEX('Game Records'!$P:$P,$H17))),NOT(ISFORMULA(INDEX('Game Records'!$Q:$Q,$H17))),NOT(ISFORMULA(INDEX('Game Records'!$R:$R,$H17))),NOT(ISFORMULA(INDEX('Game Records'!$S:$S,$H17))),NOT(ISFORMULA(INDEX('Game Records'!$T:$T,$H17))),NOT(ISFORMULA(INDEX('Game Records'!$U:$U,$H17))),NOT(ISFORMULA(INDEX('Game Records'!$V:$V,$H17))),NOT(ISFORMULA(INDEX('Game Records'!$W:$W,$H17))),NOT(ISFORMULA(INDEX('Game Records'!$X:$X,$H17))),NOT(ISFORMULA(INDEX('Game Records'!$Y:$Y,$H17))),NOT(ISFORMULA(INDEX('Game Records'!$Z:$Z,$H17)))),"Formula columns missing; ","")&IF(INDEX('Game Records'!$B:$B,$H17)="","Start Date; ","")&IF(INDEX('Game Records'!$C:$C,$H17)="","End Date; ","")&IF(AND(INDEX('Game Records'!$U:$U,$H17)<>"Subscription",INDEX('Game Records'!$U:$U,$H17)<>"Free Game",INDEX('Game Records'!$U:$U,$H17)<>"Disqualified — Free Game",OR(INDEX('Game Records'!$D:$D,$H17)="",LOWER(INDEX('Game Records'!$D:$D,$H17)&"")="n/a")),"Entry Mode; ","")&IF(AND(INDEX('Game Records'!$U:$U,$H17)<>"Subscription",INDEX('Game Records'!$U:$U,$H17)<>"Free Game",INDEX('Game Records'!$U:$U,$H17)<>"Disqualified — Free Game",OR(INDEX('Game Records'!$E:$E,$H17)="",LOWER(INDEX('Game Records'!$E:$E,$H17)&"")="n/a")),"Game Type; ","")&IF(INDEX('Game Records'!$F:$F,$H17)="","Payment Type; ","")&IF(AND(INDEX('Game Records'!$U:$U,$H17)<>"Subscription",INDEX('Game Records'!$U:$U,$H17)<>"Free Game",INDEX('Game Records'!$U:$U,$H17)<>"Disqualified — Free Game",INDEX('Game Records'!$G:$G,$H17)=""),"Gross Pot; ","")&IF(AND(INDEX('Game Records'!$U:$U,$H17)<>"Free Game",INDEX('Game Records'!$U:$U,$H17)<>"Disqualified — Free Game",INDEX('Game Records'!$H:$H,$H17)=""),"Entry Fee; ","")&IF(AND(INDEX('Game Records'!$U:$U,$H17)<>"Subscription",INDEX('Game Records'!$U:$U,$H17)<>"Free Game",INDEX('Game Records'!$U:$U,$H17)<>"Disqualified — Free Game",INDEX('Game Records'!$I:$I,$H17)=""),"Eligible Players; ","")&IF(AND(INDEX('Game Records'!$U:$U,$H17)<>"Subscription",INDEX('Game Records'!$U:$U,$H17)<>"Free Game",INDEX('Game Records'!$U:$U,$H17)<>"Disqualified — Free Game",INDEX('Game Records'!$J:$J,$H17)=""),"Total Players; ","")&IF(AND(LOWER(INDEX('Game Records'!$D:$D,$H17)&"")="finalized",LOWER(INDEX('Game Records'!$L:$L,$H17)&"")<>"yes",INDEX('Game Records'!$U:$U,$H17)<>"Subscription",INDEX('Game Records'!$U:$U,$H17)<>"Free Game",INDEX('Game Records'!$U:$U,$H17)<>"Disqualified — Free Game",INDEX('Game Records'!$K:$K,$H17)=""),"Final Earned; ","")&IF(AND(LOWER(INDEX('Game Records'!$D:$D,$H17)&"")="finalized",INDEX('Game Records'!$U:$U,$H17)<>"Subscription",INDEX('Game Records'!$U:$U,$H17)<>"Free Game",INDEX('Game Records'!$U:$U,$H17)<>"Disqualified — Free Game",OR(INDEX('Game Records'!$L:$L,$H17)="",LOWER(INDEX('Game Records'!$L:$L,$H17)&"")="n/a")),"Disqualified Status; ","")&IF(AND(OR(LOWER(TRIM(INDEX('Game Records'!$F:$F,$H17)&""))="free game",INDEX('Game Records'!$U:$U,$H17)="Free Game",INDEX('Game Records'!$U:$U,$H17)="Disqualified — Free Game"),N(INDEX('Game Records'!$H:$H,$H17))<>0),"Free Game has a non-zero Entry Fee. Free Game records require a $0 Entry Fee; ","")) | G17: =IF($H17="","",IFERROR(INDEX('Game Records'!$M:$M,$H17),"")) | H17: =IF($H16="","",IFERROR(MATCH(1,INDEX((ROW('Game Records'!$U$5:$U$504)>$H16)*(('Game Records'!$A$5:$A$504<>"")+('Game Records'!$B$5:$B$504<>"")+('Game Records'!$C$5:$C$504<>"")+('Game Records'!$D$5:$D$504<>"")+('Game Records'!$E$5:$E$504<>"")+('Game Records'!$F$5:$F$504<>"")+('Game Records'!$G$5:$G$504<>"")+('Game Records'!$H$5:$H$504<>"")+('Game Records'!$I$5:$I$504<>"")+('Game Records'!$J$5:$J$504<>"")+('Game Records'!$K$5:$K$504<>"")+('Game Records'!$L$5:$L$504<>"")+('Game Records'!$M$5:$M$504<>"")>0)*('Game Records'!$U$5:$U$504<>"Subscription"),0),0)+4,""))
A18: =IF($H18="","",ROWS($A$5:A18)) | B18: =IF($H18="","","G-"&TEXT($A18,"0000")) | C18: =IF($H18="","",IFERROR(INDEX('Game Records'!$A:$A,$H18),"")) | D18: =IF($H18="","",IFERROR(INDEX('Game Records'!$U:$U,$H18),"")) | E18: =IF($H18="","",IF($F18="","No Highlighted Fields","Highlighted Fields Present")) | F18: =IF($H18="","",IF(OR(NOT(ISFORMULA(INDEX('Game Records'!$N:$N,$H18))),NOT(ISFORMULA(INDEX('Game Records'!$O:$O,$H18))),NOT(ISFORMULA(INDEX('Game Records'!$P:$P,$H18))),NOT(ISFORMULA(INDEX('Game Records'!$Q:$Q,$H18))),NOT(ISFORMULA(INDEX('Game Records'!$R:$R,$H18))),NOT(ISFORMULA(INDEX('Game Records'!$S:$S,$H18))),NOT(ISFORMULA(INDEX('Game Records'!$T:$T,$H18))),NOT(ISFORMULA(INDEX('Game Records'!$U:$U,$H18))),NOT(ISFORMULA(INDEX('Game Records'!$V:$V,$H18))),NOT(ISFORMULA(INDEX('Game Records'!$W:$W,$H18))),NOT(ISFORMULA(INDEX('Game Records'!$X:$X,$H18))),NOT(ISFORMULA(INDEX('Game Records'!$Y:$Y,$H18))),NOT(ISFORMULA(INDEX('Game Records'!$Z:$Z,$H18)))),"Formula columns missing; ","")&IF(INDEX('Game Records'!$B:$B,$H18)="","Start Date; ","")&IF(INDEX('Game Records'!$C:$C,$H18)="","End Date; ","")&IF(AND(INDEX('Game Records'!$U:$U,$H18)<>"Subscription",INDEX('Game Records'!$U:$U,$H18)<>"Free Game",INDEX('Game Records'!$U:$U,$H18)<>"Disqualified — Free Game",OR(INDEX('Game Records'!$D:$D,$H18)="",LOWER(INDEX('Game Records'!$D:$D,$H18)&"")="n/a")),"Entry Mode; ","")&IF(AND(INDEX('Game Records'!$U:$U,$H18)<>"Subscription",INDEX('Game Records'!$U:$U,$H18)<>"Free Game",INDEX('Game Records'!$U:$U,$H18)<>"Disqualified — Free Game",OR(INDEX('Game Records'!$E:$E,$H18)="",LOWER(INDEX('Game Records'!$E:$E,$H18)&"")="n/a")),"Game Type; ","")&IF(INDEX('Game Records'!$F:$F,$H18)="","Payment Type; ","")&IF(AND(INDEX('Game Records'!$U:$U,$H18)<>"Subscription",INDEX('Game Records'!$U:$U,$H18)<>"Free Game",INDEX('Game Records'!$U:$U,$H18)<>"Disqualified — Free Game",INDEX('Game Records'!$G:$G,$H18)=""),"Gross Pot; ","")&IF(AND(INDEX('Game Records'!$U:$U,$H18)<>"Free Game",INDEX('Game Records'!$U:$U,$H18)<>"Disqualified — Free Game",INDEX('Game Records'!$H:$H,$H18)=""),"Entry Fee; ","")&IF(AND(INDEX('Game Records'!$U:$U,$H18)<>"Subscription",INDEX('Game Records'!$U:$U,$H18)<>"Free Game",INDEX('Game Records'!$U:$U,$H18)<>"Disqualified — Free Game",INDEX('Game Records'!$I:$I,$H18)=""),"Eligible Players; ","")&IF(AND(INDEX('Game Records'!$U:$U,$H18)<>"Subscription",INDEX('Game Records'!$U:$U,$H18)<>"Free Game",INDEX('Game Records'!$U:$U,$H18)<>"Disqualified — Free Game",INDEX('Game Records'!$J:$J,$H18)=""),"Total Players; ","")&IF(AND(LOWER(INDEX('Game Records'!$D:$D,$H18)&"")="finalized",LOWER(INDEX('Game Records'!$L:$L,$H18)&"")<>"yes",INDEX('Game Records'!$U:$U,$H18)<>"Subscription",INDEX('Game Records'!$U:$U,$H18)<>"Free Game",INDEX('Game Records'!$U:$U,$H18)<>"Disqualified — Free Game",INDEX('Game Records'!$K:$K,$H18)=""),"Final Earned; ","")&IF(AND(LOWER(INDEX('Game Records'!$D:$D,$H18)&"")="finalized",INDEX('Game Records'!$U:$U,$H18)<>"Subscription",INDEX('Game Records'!$U:$U,$H18)<>"Free Game",INDEX('Game Records'!$U:$U,$H18)<>"Disqualified — Free Game",OR(INDEX('Game Records'!$L:$L,$H18)="",LOWER(INDEX('Game Records'!$L:$L,$H18)&"")="n/a")),"Disqualified Status; ","")&IF(AND(OR(LOWER(TRIM(INDEX('Game Records'!$F:$F,$H18)&""))="free game",INDEX('Game Records'!$U:$U,$H18)="Free Game",INDEX('Game Records'!$U:$U,$H18)="Disqualified — Free Game"),N(INDEX('Game Records'!$H:$H,$H18))<>0),"Free Game has a non-zero Entry Fee. Free Game records require a $0 Entry Fee; ","")) | G18: =IF($H18="","",IFERROR(INDEX('Game Records'!$M:$M,$H18),"")) | H18: =IF($H17="","",IFERROR(MATCH(1,INDEX((ROW('Game Records'!$U$5:$U$504)>$H17)*(('Game Records'!$A$5:$A$504<>"")+('Game Records'!$B$5:$B$504<>"")+('Game Records'!$C$5:$C$504<>"")+('Game Records'!$D$5:$D$504<>"")+('Game Records'!$E$5:$E$504<>"")+('Game Records'!$F$5:$F$504<>"")+('Game Records'!$G$5:$G$504<>"")+('Game Records'!$H$5:$H$504<>"")+('Game Records'!$I$5:$I$504<>"")+('Game Records'!$J$5:$J$504<>"")+('Game Records'!$K$5:$K$504<>"")+('Game Records'!$L$5:$L$504<>"")+('Game Records'!$M$5:$M$504<>"")>0)*('Game Records'!$U$5:$U$504<>"Subscription"),0),0)+4,""))
A19: =IF($H19="","",ROWS($A$5:A19)) | B19: =IF($H19="","","G-"&TEXT($A19,"0000")) | C19: =IF($H19="","",IFERROR(INDEX('Game Records'!$A:$A,$H19),"")) | D19: =IF($H19="","",IFERROR(INDEX('Game Records'!$U:$U,$H19),"")) | E19: =IF($H19="","",IF($F19="","No Highlighted Fields","Highlighted Fields Present")) | F19: =IF($H19="","",IF(OR(NOT(ISFORMULA(INDEX('Game Records'!$N:$N,$H19))),NOT(ISFORMULA(INDEX('Game Records'!$O:$O,$H19))),NOT(ISFORMULA(INDEX('Game Records'!$P:$P,$H19))),NOT(ISFORMULA(INDEX('Game Records'!$Q:$Q,$H19))),NOT(ISFORMULA(INDEX('Game Records'!$R:$R,$H19))),NOT(ISFORMULA(INDEX('Game Records'!$S:$S,$H19))),NOT(ISFORMULA(INDEX('Game Records'!$T:$T,$H19))),NOT(ISFORMULA(INDEX('Game Records'!$U:$U,$H19))),NOT(ISFORMULA(INDEX('Game Records'!$V:$V,$H19))),NOT(ISFORMULA(INDEX('Game Records'!$W:$W,$H19))),NOT(ISFORMULA(INDEX('Game Records'!$X:$X,$H19))),NOT(ISFORMULA(INDEX('Game Records'!$Y:$Y,$H19))),NOT(ISFORMULA(INDEX('Game Records'!$Z:$Z,$H19)))),"Formula columns missing; ","")&IF(INDEX('Game Records'!$B:$B,$H19)="","Start Date; ","")&IF(INDEX('Game Records'!$C:$C,$H19)="","End Date; ","")&IF(AND(INDEX('Game Records'!$U:$U,$H19)<>"Subscription",INDEX('Game Records'!$U:$U,$H19)<>"Free Game",INDEX('Game Records'!$U:$U,$H19)<>"Disqualified — Free Game",OR(INDEX('Game Records'!$D:$D,$H19)="",LOWER(INDEX('Game Records'!$D:$D,$H19)&"")="n/a")),"Entry Mode; ","")&IF(AND(INDEX('Game Records'!$U:$U,$H19)<>"Subscription",INDEX('Game Records'!$U:$U,$H19)<>"Free Game",INDEX('Game Records'!$U:$U,$H19)<>"Disqualified — Free Game",OR(INDEX('Game Records'!$E:$E,$H19)="",LOWER(INDEX('Game Records'!$E:$E,$H19)&"")="n/a")),"Game Type; ","")&IF(INDEX('Game Records'!$F:$F,$H19)="","Payment Type; ","")&IF(AND(INDEX('Game Records'!$U:$U,$H19)<>"Subscription",INDEX('Game Records'!$U:$U,$H19)<>"Free Game",INDEX('Game Records'!$U:$U,$H19)<>"Disqualified — Free Game",INDEX('Game Records'!$G:$G,$H19)=""),"Gross Pot; ","")&IF(AND(INDEX('Game Records'!$U:$U,$H19)<>"Free Game",INDEX('Game Records'!$U:$U,$H19)<>"Disqualified — Free Game",INDEX('Game Records'!$H:$H,$H19)=""),"Entry Fee; ","")&IF(AND(INDEX('Game Records'!$U:$U,$H19)<>"Subscription",INDEX('Game Records'!$U:$U,$H19)<>"Free Game",INDEX('Game Records'!$U:$U,$H19)<>"Disqualified — Free Game",INDEX('Game Records'!$I:$I,$H19)=""),"Eligible Players; ","")&IF(AND(INDEX('Game Records'!$U:$U,$H19)<>"Subscription",INDEX('Game Records'!$U:$U,$H19)<>"Free Game",INDEX('Game Records'!$U:$U,$H19)<>"Disqualified — Free Game",INDEX('Game Records'!$J:$J,$H19)=""),"Total Players; ","")&IF(AND(LOWER(INDEX('Game Records'!$D:$D,$H19)&"")="finalized",LOWER(INDEX('Game Records'!$L:$L,$H19)&"")<>"yes",INDEX('Game Records'!$U:$U,$H19)<>"Subscription",INDEX('Game Records'!$U:$U,$H19)<>"Free Game",INDEX('Game Records'!$U:$U,$H19)<>"Disqualified — Free Game",INDEX('Game Records'!$K:$K,$H19)=""),"Final Earned; ","")&IF(AND(LOWER(INDEX('Game Records'!$D:$D,$H19)&"")="finalized",INDEX('Game Records'!$U:$U,$H19)<>"Subscription",INDEX('Game Records'!$U:$U,$H19)<>"Free Game",INDEX('Game Records'!$U:$U,$H19)<>"Disqualified — Free Game",OR(INDEX('Game Records'!$L:$L,$H19)="",LOWER(INDEX('Game Records'!$L:$L,$H19)&"")="n/a")),"Disqualified Status; ","")&IF(AND(OR(LOWER(TRIM(INDEX('Game Records'!$F:$F,$H19)&""))="free game",INDEX('Game Records'!$U:$U,$H19)="Free Game",INDEX('Game Records'!$U:$U,$H19)="Disqualified — Free Game"),N(INDEX('Game Records'!$H:$H,$H19))<>0),"Free Game has a non-zero Entry Fee. Free Game records require a $0 Entry Fee; ","")) | G19: =IF($H19="","",IFERROR(INDEX('Game Records'!$M:$M,$H19),"")) | H19: =IF($H18="","",IFERROR(MATCH(1,INDEX((ROW('Game Records'!$U$5:$U$504)>$H18)*(('Game Records'!$A$5:$A$504<>"")+('Game Records'!$B$5:$B$504<>"")+('Game Records'!$C$5:$C$504<>"")+('Game Records'!$D$5:$D$504<>"")+('Game Records'!$E$5:$E$504<>"")+('Game Records'!$F$5:$F$504<>"")+('Game Records'!$G$5:$G$504<>"")+('Game Records'!$H$5:$H$504<>"")+('Game Records'!$I$5:$I$504<>"")+('Game Records'!$J$5:$J$504<>"")+('Game Records'!$K$5:$K$504<>"")+('Game Records'!$L$5:$L$504<>"")+('Game Records'!$M$5:$M$504<>"")>0)*('Game Records'!$U$5:$U$504<>"Subscription"),0),0)+4,""))
A20: =IF($H20="","",ROWS($A$5:A20)) | B20: =IF($H20="","","G-"&TEXT($A20,"0000")) | C20: =IF($H20="","",IFERROR(INDEX('Game Records'!$A:$A,$H20),"")) | D20: =IF($H20="","",IFERROR(INDEX('Game Records'!$U:$U,$H20),"")) | E20: =IF($H20="","",IF($F20="","No Highlighted Fields","Highlighted Fields Present")) | F20: =IF($H20="","",IF(OR(NOT(ISFORMULA(INDEX('Game Records'!$N:$N,$H20))),NOT(ISFORMULA(INDEX('Game Records'!$O:$O,$H20))),NOT(ISFORMULA(INDEX('Game Records'!$P:$P,$H20))),NOT(ISFORMULA(INDEX('Game Records'!$Q:$Q,$H20))),NOT(ISFORMULA(INDEX('Game Records'!$R:$R,$H20))),NOT(ISFORMULA(INDEX('Game Records'!$S:$S,$H20))),NOT(ISFORMULA(INDEX('Game Records'!$T:$T,$H20))),NOT(ISFORMULA(INDEX('Game Records'!$U:$U,$H20))),NOT(ISFORMULA(INDEX('Game Records'!$V:$V,$H20))),NOT(ISFORMULA(INDEX('Game Records'!$W:$W,$H20))),NOT(ISFORMULA(INDEX('Game Records'!$X:$X,$H20))),NOT(ISFORMULA(INDEX('Game Records'!$Y:$Y,$H20))),NOT(ISFORMULA(INDEX('Game Records'!$Z:$Z,$H20)))),"Formula columns missing; ","")&IF(INDEX('Game Records'!$B:$B,$H20)="","Start Date; ","")&IF(INDEX('Game Records'!$C:$C,$H20)="","End Date; ","")&IF(AND(INDEX('Game Records'!$U:$U,$H20)<>"Subscription",INDEX('Game Records'!$U:$U,$H20)<>"Free Game",INDEX('Game Records'!$U:$U,$H20)<>"Disqualified — Free Game",OR(INDEX('Game Records'!$D:$D,$H20)="",LOWER(INDEX('Game Records'!$D:$D,$H20)&"")="n/a")),"Entry Mode; ","")&IF(AND(INDEX('Game Records'!$U:$U,$H20)<>"Subscription",INDEX('Game Records'!$U:$U,$H20)<>"Free Game",INDEX('Game Records'!$U:$U,$H20)<>"Disqualified — Free Game",OR(INDEX('Game Records'!$E:$E,$H20)="",LOWER(INDEX('Game Records'!$E:$E,$H20)&"")="n/a")),"Game Type; ","")&IF(INDEX('Game Records'!$F:$F,$H20)="","Payment Type; ","")&IF(AND(INDEX('Game Records'!$U:$U,$H20)<>"Subscription",INDEX('Game Records'!$U:$U,$H20)<>"Free Game",INDEX('Game Records'!$U:$U,$H20)<>"Disqualified — Free Game",INDEX('Game Records'!$G:$G,$H20)=""),"Gross Pot; ","")&IF(AND(INDEX('Game Records'!$U:$U,$H20)<>"Free Game",INDEX('Game Records'!$U:$U,$H20)<>"Disqualified — Free Game",INDEX('Game Records'!$H:$H,$H20)=""),"Entry Fee; ","")&IF(AND(INDEX('Game Records'!$U:$U,$H20)<>"Subscription",INDEX('Game Records'!$U:$U,$H20)<>"Free Game",INDEX('Game Records'!$U:$U,$H20)<>"Disqualified — Free Game",INDEX('Game Records'!$I:$I,$H20)=""),"Eligible Players; ","")&IF(AND(INDEX('Game Records'!$U:$U,$H20)<>"Subscription",INDEX('Game Records'!$U:$U,$H20)<>"Free Game",INDEX('Game Records'!$U:$U,$H20)<>"Disqualified — Free Game",INDEX('Game Records'!$J:$J,$H20)=""),"Total Players; ","")&IF(AND(LOWER(INDEX('Game Records'!$D:$D,$H20)&"")="finalized",LOWER(INDEX('Game Records'!$L:$L,$H20)&"")<>"yes",INDEX('Game Records'!$U:$U,$H20)<>"Subscription",INDEX('Game Records'!$U:$U,$H20)<>"Free Game",INDEX('Game Records'!$U:$U,$H20)<>"Disqualified — Free Game",INDEX('Game Records'!$K:$K,$H20)=""),"Final Earned; ","")&IF(AND(LOWER(INDEX('Game Records'!$D:$D,$H20)&"")="finalized",INDEX('Game Records'!$U:$U,$H20)<>"Subscription",INDEX('Game Records'!$U:$U,$H20)<>"Free Game",INDEX('Game Records'!$U:$U,$H20)<>"Disqualified — Free Game",OR(INDEX('Game Records'!$L:$L,$H20)="",LOWER(INDEX('Game Records'!$L:$L,$H20)&"")="n/a")),"Disqualified Status; ","")&IF(AND(OR(LOWER(TRIM(INDEX('Game Records'!$F:$F,$H20)&""))="free game",INDEX('Game Records'!$U:$U,$H20)="Free Game",INDEX('Game Records'!$U:$U,$H20)="Disqualified — Free Game"),N(INDEX('Game Records'!$H:$H,$H20))<>0),"Free Game has a non-zero Entry Fee. Free Game records require a $0 Entry Fee; ","")) | G20: =IF($H20="","",IFERROR(INDEX('Game Records'!$M:$M,$H20),"")) | H20: =IF($H19="","",IFERROR(MATCH(1,INDEX((ROW('Game Records'!$U$5:$U$504)>$H19)*(('Game Records'!$A$5:$A$504<>"")+('Game Records'!$B$5:$B$504<>"")+('Game Records'!$C$5:$C$504<>"")+('Game Records'!$D$5:$D$504<>"")+('Game Records'!$E$5:$E$504<>"")+('Game Records'!$F$5:$F$504<>"")+('Game Records'!$G$5:$G$504<>"")+('Game Records'!$H$5:$H$504<>"")+('Game Records'!$I$5:$I$504<>"")+('Game Records'!$J$5:$J$504<>"")+('Game Records'!$K$5:$K$504<>"")+('Game Records'!$L$5:$L$504<>"")+('Game Records'!$M$5:$M$504<>"")>0)*('Game Records'!$U$5:$U$504<>"Subscription"),0),0)+4,""))
A21: =IF($H21="","",ROWS($A$5:A21)) | B21: =IF($H21="","","G-"&TEXT($A21,"0000")) | C21: =IF($H21="","",IFERROR(INDEX('Game Records'!$A:$A,$H21),"")) | D21: =IF($H21="","",IFERROR(INDEX('Game Records'!$U:$U,$H21),"")) | E21: =IF($H21="","",IF($F21="","No Highlighted Fields","Highlighted Fields Present")) | F21: =IF($H21="","",IF(OR(NOT(ISFORMULA(INDEX('Game Records'!$N:$N,$H21))),NOT(ISFORMULA(INDEX('Game Records'!$O:$O,$H21))),NOT(ISFORMULA(INDEX('Game Records'!$P:$P,$H21))),NOT(ISFORMULA(INDEX('Game Records'!$Q:$Q,$H21))),NOT(ISFORMULA(INDEX('Game Records'!$R:$R,$H21))),NOT(ISFORMULA(INDEX('Game Records'!$S:$S,$H21))),NOT(ISFORMULA(INDEX('Game Records'!$T:$T,$H21))),NOT(ISFORMULA(INDEX('Game Records'!$U:$U,$H21))),NOT(ISFORMULA(INDEX('Game Records'!$V:$V,$H21))),NOT(ISFORMULA(INDEX('Game Records'!$W:$W,$H21))),NOT(ISFORMULA(INDEX('Game Records'!$X:$X,$H21))),NOT(ISFORMULA(INDEX('Game Records'!$Y:$Y,$H21))),NOT(ISFORMULA(INDEX('Game Records'!$Z:$Z,$H21)))),"Formula columns missing; ","")&IF(INDEX('Game Records'!$B:$B,$H21)="","Start Date; ","")&IF(INDEX('Game Records'!$C:$C,$H21)="","End Date; ","")&IF(AND(INDEX('Game Records'!$U:$U,$H21)<>"Subscription",INDEX('Game Records'!$U:$U,$H21)<>"Free Game",INDEX('Game Records'!$U:$U,$H21)<>"Disqualified — Free Game",OR(INDEX('Game Records'!$D:$D,$H21)="",LOWER(INDEX('Game Records'!$D:$D,$H21)&"")="n/a")),"Entry Mode; ","")&IF(AND(INDEX('Game Records'!$U:$U,$H21)<>"Subscription",INDEX('Game Records'!$U:$U,$H21)<>"Free Game",INDEX('Game Records'!$U:$U,$H21)<>"Disqualified — Free Game",OR(INDEX('Game Records'!$E:$E,$H21)="",LOWER(INDEX('Game Records'!$E:$E,$H21)&"")="n/a")),"Game Type; ","")&IF(INDEX('Game Records'!$F:$F,$H21)="","Payment Type; ","")&IF(AND(INDEX('Game Records'!$U:$U,$H21)<>"Subscription",INDEX('Game Records'!$U:$U,$H21)<>"Free Game",INDEX('Game Records'!$U:$U,$H21)<>"Disqualified — Free Game",INDEX('Game Records'!$G:$G,$H21)=""),"Gross Pot; ","")&IF(AND(INDEX('Game Records'!$U:$U,$H21)<>"Free Game",INDEX('Game Records'!$U:$U,$H21)<>"Disqualified — Free Game",INDEX('Game Records'!$H:$H,$H21)=""),"Entry Fee; ","")&IF(AND(INDEX('Game Records'!$U:$U,$H21)<>"Subscription",INDEX('Game Records'!$U:$U,$H21)<>"Free Game",INDEX('Game Records'!$U:$U,$H21)<>"Disqualified — Free Game",INDEX('Game Records'!$I:$I,$H21)=""),"Eligible Players; ","")&IF(AND(INDEX('Game Records'!$U:$U,$H21)<>"Subscription",INDEX('Game Records'!$U:$U,$H21)<>"Free Game",INDEX('Game Records'!$U:$U,$H21)<>"Disqualified — Free Game",INDEX('Game Records'!$J:$J,$H21)=""),"Total Players; ","")&IF(AND(LOWER(INDEX('Game Records'!$D:$D,$H21)&"")="finalized",LOWER(INDEX('Game Records'!$L:$L,$H21)&"")<>"yes",INDEX('Game Records'!$U:$U,$H21)<>"Subscription",INDEX('Game Records'!$U:$U,$H21)<>"Free Game",INDEX('Game Records'!$U:$U,$H21)<>"Disqualified — Free Game",INDEX('Game Records'!$K:$K,$H21)=""),"Final Earned; ","")&IF(AND(LOWER(INDEX('Game Records'!$D:$D,$H21)&"")="finalized",INDEX('Game Records'!$U:$U,$H21)<>"Subscription",INDEX('Game Records'!$U:$U,$H21)<>"Free Game",INDEX('Game Records'!$U:$U,$H21)<>"Disqualified — Free Game",OR(INDEX('Game Records'!$L:$L,$H21)="",LOWER(INDEX('Game Records'!$L:$L,$H21)&"")="n/a")),"Disqualified Status; ","")&IF(AND(OR(LOWER(TRIM(INDEX('Game Records'!$F:$F,$H21)&""))="free game",INDEX('Game Records'!$U:$U,$H21)="Free Game",INDEX('Game Records'!$U:$U,$H21)="Disqualified — Free Game"),N(INDEX('Game Records'!$H:$H,$H21))<>0),"Free Game has a non-zero Entry Fee. Free Game records require a $0 Entry Fee; ","")) | G21: =IF($H21="","",IFERROR(INDEX('Game Records'!$M:$M,$H21),"")) | H21: =IF($H20="","",IFERROR(MATCH(1,INDEX((ROW('Game Records'!$U$5:$U$504)>$H20)*(('Game Records'!$A$5:$A$504<>"")+('Game Records'!$B$5:$B$504<>"")+('Game Records'!$C$5:$C$504<>"")+('Game Records'!$D$5:$D$504<>"")+('Game Records'!$E$5:$E$504<>"")+('Game Records'!$F$5:$F$504<>"")+('Game Records'!$G$5:$G$504<>"")+('Game Records'!$H$5:$H$504<>"")+('Game Records'!$I$5:$I$504<>"")+('Game Records'!$J$5:$J$504<>"")+('Game Records'!$K$5:$K$504<>"")+('Game Records'!$L$5:$L$504<>"")+('Game Records'!$M$5:$M$504<>"")>0)*('Game Records'!$U$5:$U$504<>"Subscription"),0),0)+4,""))
A22: =IF($H22="","",ROWS($A$5:A22)) | B22: =IF($H22="","","G-"&TEXT($A22,"0000")) | C22: =IF($H22="","",IFERROR(INDEX('Game Records'!$A:$A,$H22),"")) | D22: =IF($H22="","",IFERROR(INDEX('Game Records'!$U:$U,$H22),"")) | E22: =IF($H22="","",IF($F22="","No Highlighted Fields","Highlighted Fields Present")) | F22: =IF($H22="","",IF(OR(NOT(ISFORMULA(INDEX('Game Records'!$N:$N,$H22))),NOT(ISFORMULA(INDEX('Game Records'!$O:$O,$H22))),NOT(ISFORMULA(INDEX('Game Records'!$P:$P,$H22))),NOT(ISFORMULA(INDEX('Game Records'!$Q:$Q,$H22))),NOT(ISFORMULA(INDEX('Game Records'!$R:$R,$H22))),NOT(ISFORMULA(INDEX('Game Records'!$S:$S,$H22))),NOT(ISFORMULA(INDEX('Game Records'!$T:$T,$H22))),NOT(ISFORMULA(INDEX('Game Records'!$U:$U,$H22))),NOT(ISFORMULA(INDEX('Game Records'!$V:$V,$H22))),NOT(ISFORMULA(INDEX('Game Records'!$W:$W,$H22))),NOT(ISFORMULA(INDEX('Game Records'!$X:$X,$H22))),NOT(ISFORMULA(INDEX('Game Records'!$Y:$Y,$H22))),NOT(ISFORMULA(INDEX('Game Records'!$Z:$Z,$H22)))),"Formula columns missing; ","")&IF(INDEX('Game Records'!$B:$B,$H22)="","Start Date; ","")&IF(INDEX('Game Records'!$C:$C,$H22)="","End Date; ","")&IF(AND(INDEX('Game Records'!$U:$U,$H22)<>"Subscription",INDEX('Game Records'!$U:$U,$H22)<>"Free Game",INDEX('Game Records'!$U:$U,$H22)<>"Disqualified — Free Game",OR(INDEX('Game Records'!$D:$D,$H22)="",LOWER(INDEX('Game Records'!$D:$D,$H22)&"")="n/a")),"Entry Mode; ","")&IF(AND(INDEX('Game Records'!$U:$U,$H22)<>"Subscription",INDEX('Game Records'!$U:$U,$H22)<>"Free Game",INDEX('Game Records'!$U:$U,$H22)<>"Disqualified — Free Game",OR(INDEX('Game Records'!$E:$E,$H22)="",LOWER(INDEX('Game Records'!$E:$E,$H22)&"")="n/a")),"Game Type; ","")&IF(INDEX('Game Records'!$F:$F,$H22)="","Payment Type; ","")&IF(AND(INDEX('Game Records'!$U:$U,$H22)<>"Subscription",INDEX('Game Records'!$U:$U,$H22)<>"Free Game",INDEX('Game Records'!$U:$U,$H22)<>"Disqualified — Free Game",INDEX('Game Records'!$G:$G,$H22)=""),"Gross Pot; ","")&IF(AND(INDEX('Game Records'!$U:$U,$H22)<>"Free Game",INDEX('Game Records'!$U:$U,$H22)<>"Disqualified — Free Game",INDEX('Game Records'!$H:$H,$H22)=""),"Entry Fee; ","")&IF(AND(INDEX('Game Records'!$U:$U,$H22)<>"Subscription",INDEX('Game Records'!$U:$U,$H22)<>"Free Game",INDEX('Game Records'!$U:$U,$H22)<>"Disqualified — Free Game",INDEX('Game Records'!$I:$I,$H22)=""),"Eligible Players; ","")&IF(AND(INDEX('Game Records'!$U:$U,$H22)<>"Subscription",INDEX('Game Records'!$U:$U,$H22)<>"Free Game",INDEX('Game Records'!$U:$U,$H22)<>"Disqualified — Free Game",INDEX('Game Records'!$J:$J,$H22)=""),"Total Players; ","")&IF(AND(LOWER(INDEX('Game Records'!$D:$D,$H22)&"")="finalized",LOWER(INDEX('Game Records'!$L:$L,$H22)&"")<>"yes",INDEX('Game Records'!$U:$U,$H22)<>"Subscription",INDEX('Game Records'!$U:$U,$H22)<>"Free Game",INDEX('Game Records'!$U:$U,$H22)<>"Disqualified — Free Game",INDEX('Game Records'!$K:$K,$H22)=""),"Final Earned; ","")&IF(AND(LOWER(INDEX('Game Records'!$D:$D,$H22)&"")="finalized",INDEX('Game Records'!$U:$U,$H22)<>"Subscription",INDEX('Game Records'!$U:$U,$H22)<>"Free Game",INDEX('Game Records'!$U:$U,$H22)<>"Disqualified — Free Game",OR(INDEX('Game Records'!$L:$L,$H22)="",LOWER(INDEX('Game Records'!$L:$L,$H22)&"")="n/a")),"Disqualified Status; ","")&IF(AND(OR(LOWER(TRIM(INDEX('Game Records'!$F:$F,$H22)&""))="free game",INDEX('Game Records'!$U:$U,$H22)="Free Game",INDEX('Game Records'!$U:$U,$H22)="Disqualified — Free Game"),N(INDEX('Game Records'!$H:$H,$H22))<>0),"Free Game has a non-zero Entry Fee. Free Game records require a $0 Entry Fee; ","")) | G22: =IF($H22="","",IFERROR(INDEX('Game Records'!$M:$M,$H22),"")) | H22: =IF($H21="","",IFERROR(MATCH(1,INDEX((ROW('Game Records'!$U$5:$U$504)>$H21)*(('Game Records'!$A$5:$A$504<>"")+('Game Records'!$B$5:$B$504<>"")+('Game Records'!$C$5:$C$504<>"")+('Game Records'!$D$5:$D$504<>"")+('Game Records'!$E$5:$E$504<>"")+('Game Records'!$F$5:$F$504<>"")+('Game Records'!$G$5:$G$504<>"")+('Game Records'!$H$5:$H$504<>"")+('Game Records'!$I$5:$I$504<>"")+('Game Records'!$J$5:$J$504<>"")+('Game Records'!$K$5:$K$504<>"")+('Game Records'!$L$5:$L$504<>"")+('Game Records'!$M$5:$M$504<>"")>0)*('Game Records'!$U$5:$U$504<>"Subscription"),0),0)+4,""))
A23: =IF($H23="","",ROWS($A$5:A23)) | B23: =IF($H23="","","G-"&TEXT($A23,"0000")) | C23: =IF($H23="","",IFERROR(INDEX('Game Records'!$A:$A,$H23),"")) | D23: =IF($H23="","",IFERROR(INDEX('Game Records'!$U:$U,$H23),"")) | E23: =IF($H23="","",IF($F23="","No Highlighted Fields","Highlighted Fields Present")) | F23: =IF($H23="","",IF(OR(NOT(ISFORMULA(INDEX('Game Records'!$N:$N,$H23))),NOT(ISFORMULA(INDEX('Game Records'!$O:$O,$H23))),NOT(ISFORMULA(INDEX('Game Records'!$P:$P,$H23))),NOT(ISFORMULA(INDEX('Game Records'!$Q:$Q,$H23))),NOT(ISFORMULA(INDEX('Game Records'!$R:$R,$H23))),NOT(ISFORMULA(INDEX('Game Records'!$S:$S,$H23))),NOT(ISFORMULA(INDEX('Game Records'!$T:$T,$H23))),NOT(ISFORMULA(INDEX('Game Records'!$U:$U,$H23))),NOT(ISFORMULA(INDEX('Game Records'!$V:$V,$H23))),NOT(ISFORMULA(INDEX('Game Records'!$W:$W,$H23))),NOT(ISFORMULA(INDEX('Game Records'!$X:$X,$H23))),NOT(ISFORMULA(INDEX('Game Records'!$Y:$Y,$H23))),NOT(ISFORMULA(INDEX('Game Records'!$Z:$Z,$H23)))),"Formula columns missing; ","")&IF(INDEX('Game Records'!$B:$B,$H23)="","Start Date; ","")&IF(INDEX('Game Records'!$C:$C,$H23)="","End Date; ","")&IF(AND(INDEX('Game Records'!$U:$U,$H23)<>"Subscription",INDEX('Game Records'!$U:$U,$H23)<>"Free Game",INDEX('Game Records'!$U:$U,$H23)<>"Disqualified — Free Game",OR(INDEX('Game Records'!$D:$D,$H23)="",LOWER(INDEX('Game Records'!$D:$D,$H23)&"")="n/a")),"Entry Mode; ","")&IF(AND(INDEX('Game Records'!$U:$U,$H23)<>"Subscription",INDEX('Game Records'!$U:$U,$H23)<>"Free Game",INDEX('Game Records'!$U:$U,$H23)<>"Disqualified — Free Game",OR(INDEX('Game Records'!$E:$E,$H23)="",LOWER(INDEX('Game Records'!$E:$E,$H23)&"")="n/a")),"Game Type; ","")&IF(INDEX('Game Records'!$F:$F,$H23)="","Payment Type; ","")&IF(AND(INDEX('Game Records'!$U:$U,$H23)<>"Subscription",INDEX('Game Records'!$U:$U,$H23)<>"Free Game",INDEX('Game Records'!$U:$U,$H23)<>"Disqualified — Free Game",INDEX('Game Records'!$G:$G,$H23)=""),"Gross Pot; ","")&IF(AND(INDEX('Game Records'!$U:$U,$H23)<>"Free Game",INDEX('Game Records'!$U:$U,$H23)<>"Disqualified — Free Game",INDEX('Game Records'!$H:$H,$H23)=""),"Entry Fee; ","")&IF(AND(INDEX('Game Records'!$U:$U,$H23)<>"Subscription",INDEX('Game Records'!$U:$U,$H23)<>"Free Game",INDEX('Game Records'!$U:$U,$H23)<>"Disqualified — Free Game",INDEX('Game Records'!$I:$I,$H23)=""),"Eligible Players; ","")&IF(AND(INDEX('Game Records'!$U:$U,$H23)<>"Subscription",INDEX('Game Records'!$U:$U,$H23)<>"Free Game",INDEX('Game Records'!$U:$U,$H23)<>"Disqualified — Free Game",INDEX('Game Records'!$J:$J,$H23)=""),"Total Players; ","")&IF(AND(LOWER(INDEX('Game Records'!$D:$D,$H23)&"")="finalized",LOWER(INDEX('Game Records'!$L:$L,$H23)&"")<>"yes",INDEX('Game Records'!$U:$U,$H23)<>"Subscription",INDEX('Game Records'!$U:$U,$H23)<>"Free Game",INDEX('Game Records'!$U:$U,$H23)<>"Disqualified — Free Game",INDEX('Game Records'!$K:$K,$H23)=""),"Final Earned; ","")&IF(AND(LOWER(INDEX('Game Records'!$D:$D,$H23)&"")="finalized",INDEX('Game Records'!$U:$U,$H23)<>"Subscription",INDEX('Game Records'!$U:$U,$H23)<>"Free Game",INDEX('Game Records'!$U:$U,$H23)<>"Disqualified — Free Game",OR(INDEX('Game Records'!$L:$L,$H23)="",LOWER(INDEX('Game Records'!$L:$L,$H23)&"")="n/a")),"Disqualified Status; ","")&IF(AND(OR(LOWER(TRIM(INDEX('Game Records'!$F:$F,$H23)&""))="free game",INDEX('Game Records'!$U:$U,$H23)="Free Game",INDEX('Game Records'!$U:$U,$H23)="Disqualified — Free Game"),N(INDEX('Game Records'!$H:$H,$H23))<>0),"Free Game has a non-zero Entry Fee. Free Game records require a $0 Entry Fee; ","")) | G23: =IF($H23="","",IFERROR(INDEX('Game Records'!$M:$M,$H23),"")) | H23: =IF($H22="","",IFERROR(MATCH(1,INDEX((ROW('Game Records'!$U$5:$U$504)>$H22)*(('Game Records'!$A$5:$A$504<>"")+('Game Records'!$B$5:$B$504<>"")+('Game Records'!$C$5:$C$504<>"")+('Game Records'!$D$5:$D$504<>"")+('Game Records'!$E$5:$E$504<>"")+('Game Records'!$F$5:$F$504<>"")+('Game Records'!$G$5:$G$504<>"")+('Game Records'!$H$5:$H$504<>"")+('Game Records'!$I$5:$I$504<>"")+('Game Records'!$J$5:$J$504<>"")+('Game Records'!$K$5:$K$504<>"")+('Game Records'!$L$5:$L$504<>"")+('Game Records'!$M$5:$M$504<>"")>0)*('Game Records'!$U$5:$U$504<>"Subscription"),0),0)+4,""))
A24: =IF($H24="","",ROWS($A$5:A24)) | B24: =IF($H24="","","G-"&TEXT($A24,"0000")) | C24: =IF($H24="","",IFERROR(INDEX('Game Records'!$A:$A,$H24),"")) | D24: =IF($H24="","",IFERROR(INDEX('Game Records'!$U:$U,$H24),"")) | E24: =IF($H24="","",IF($F24="","No Highlighted Fields","Highlighted Fields Present")) | F24: =IF($H24="","",IF(OR(NOT(ISFORMULA(INDEX('Game Records'!$N:$N,$H24))),NOT(ISFORMULA(INDEX('Game Records'!$O:$O,$H24))),NOT(ISFORMULA(INDEX('Game Records'!$P:$P,$H24))),NOT(ISFORMULA(INDEX('Game Records'!$Q:$Q,$H24))),NOT(ISFORMULA(INDEX('Game Records'!$R:$R,$H24))),NOT(ISFORMULA(INDEX('Game Records'!$S:$S,$H24))),NOT(ISFORMULA(INDEX('Game Records'!$T:$T,$H24))),NOT(ISFORMULA(INDEX('Game Records'!$U:$U,$H24))),NOT(ISFORMULA(INDEX('Game Records'!$V:$V,$H24))),NOT(ISFORMULA(INDEX('Game Records'!$W:$W,$H24))),NOT(ISFORMULA(INDEX('Game Records'!$X:$X,$H24))),NOT(ISFORMULA(INDEX('Game Records'!$Y:$Y,$H24))),NOT(ISFORMULA(INDEX('Game Records'!$Z:$Z,$H24)))),"Formula columns missing; ","")&IF(INDEX('Game Records'!$B:$B,$H24)="","Start Date; ","")&IF(INDEX('Game Records'!$C:$C,$H24)="","End Date; ","")&IF(AND(INDEX('Game Records'!$U:$U,$H24)<>"Subscription",INDEX('Game Records'!$U:$U,$H24)<>"Free Game",INDEX('Game Records'!$U:$U,$H24)<>"Disqualified — Free Game",OR(INDEX('Game Records'!$D:$D,$H24)="",LOWER(INDEX('Game Records'!$D:$D,$H24)&"")="n/a")),"Entry Mode; ","")&IF(AND(INDEX('Game Records'!$U:$U,$H24)<>"Subscription",INDEX('Game Records'!$U:$U,$H24)<>"Free Game",INDEX('Game Records'!$U:$U,$H24)<>"Disqualified — Free Game",OR(INDEX('Game Records'!$E:$E,$H24)="",LOWER(INDEX('Game Records'!$E:$E,$H24)&"")="n/a")),"Game Type; ","")&IF(INDEX('Game Records'!$F:$F,$H24)="","Payment Type; ","")&IF(AND(INDEX('Game Records'!$U:$U,$H24)<>"Subscription",INDEX('Game Records'!$U:$U,$H24)<>"Free Game",INDEX('Game Records'!$U:$U,$H24)<>"Disqualified — Free Game",INDEX('Game Records'!$G:$G,$H24)=""),"Gross Pot; ","")&IF(AND(INDEX('Game Records'!$U:$U,$H24)<>"Free Game",INDEX('Game Records'!$U:$U,$H24)<>"Disqualified — Free Game",INDEX('Game Records'!$H:$H,$H24)=""),"Entry Fee; ","")&IF(AND(INDEX('Game Records'!$U:$U,$H24)<>"Subscription",INDEX('Game Records'!$U:$U,$H24)<>"Free Game",INDEX('Game Records'!$U:$U,$H24)<>"Disqualified — Free Game",INDEX('Game Records'!$I:$I,$H24)=""),"Eligible Players; ","")&IF(AND(INDEX('Game Records'!$U:$U,$H24)<>"Subscription",INDEX('Game Records'!$U:$U,$H24)<>"Free Game",INDEX('Game Records'!$U:$U,$H24)<>"Disqualified — Free Game",INDEX('Game Records'!$J:$J,$H24)=""),"Total Players; ","")&IF(AND(LOWER(INDEX('Game Records'!$D:$D,$H24)&"")="finalized",LOWER(INDEX('Game Records'!$L:$L,$H24)&"")<>"yes",INDEX('Game Records'!$U:$U,$H24)<>"Subscription",INDEX('Game Records'!$U:$U,$H24)<>"Free Game",INDEX('Game Records'!$U:$U,$H24)<>"Disqualified — Free Game",INDEX('Game Records'!$K:$K,$H24)=""),"Final Earned; ","")&IF(AND(LOWER(INDEX('Game Records'!$D:$D,$H24)&"")="finalized",INDEX('Game Records'!$U:$U,$H24)<>"Subscription",INDEX('Game Records'!$U:$U,$H24)<>"Free Game",INDEX('Game Records'!$U:$U,$H24)<>"Disqualified — Free Game",OR(INDEX('Game Records'!$L:$L,$H24)="",LOWER(INDEX('Game Records'!$L:$L,$H24)&"")="n/a")),"Disqualified Status; ","")&IF(AND(OR(LOWER(TRIM(INDEX('Game Records'!$F:$F,$H24)&""))="free game",INDEX('Game Records'!$U:$U,$H24)="Free Game",INDEX('Game Records'!$U:$U,$H24)="Disqualified — Free Game"),N(INDEX('Game Records'!$H:$H,$H24))<>0),"Free Game has a non-zero Entry Fee. Free Game records require a $0 Entry Fee; ","")) | G24: =IF($H24="","",IFERROR(INDEX('Game Records'!$M:$M,$H24),"")) | H24: =IF($H23="","",IFERROR(MATCH(1,INDEX((ROW('Game Records'!$U$5:$U$504)>$H23)*(('Game Records'!$A$5:$A$504<>"")+('Game Records'!$B$5:$B$504<>"")+('Game Records'!$C$5:$C$504<>"")+('Game Records'!$D$5:$D$504<>"")+('Game Records'!$E$5:$E$504<>"")+('Game Records'!$F$5:$F$504<>"")+('Game Records'!$G$5:$G$504<>"")+('Game Records'!$H$5:$H$504<>"")+('Game Records'!$I$5:$I$504<>"")+('Game Records'!$J$5:$J$504<>"")+('Game Records'!$K$5:$K$504<>"")+('Game Records'!$L$5:$L$504<>"")+('Game Records'!$M$5:$M$504<>"")>0)*('Game Records'!$U$5:$U$504<>"Subscription"),0),0)+4,""))
... A504: =IF($H504="","",ROWS($A$5:A504)) | B504: =IF($H504="","","G-"&TEXT($A504,"0000")) | C504: =IF($H504="","",IFERROR(INDEX('Game Records'!$A:$A,$H504),"")) | D504: =IF($H504="","",IFERROR(INDEX('Game Records'!$U:$U,$H504),"")) | E504: =IF($H504="","",IF($F504="","No Highlighted Fields","Highlighted Fields Present")) | F504: =IF($H504="","",IF(OR(NOT(ISFORMULA(INDEX('Game Records'!$N:$N,$H504))),NOT(ISFORMULA(INDEX('Game Records'!$O:$O,$H504))),NOT(ISFORMULA(INDEX('Game Records'!$P:$P,$H504))),NOT(ISFORMULA(INDEX('Game Records'!$Q:$Q,$H504))),NOT(ISFORMULA(INDEX('Game Records'!$R:$R,$H504))),NOT(ISFORMULA(INDEX('Game Records'!$S:$S,$H504))),NOT(ISFORMULA(INDEX('Game Records'!$T:$T,$H504))),NOT(ISFORMULA(INDEX('Game Records'!$U:$U,$H504))),NOT(ISFORMULA(INDEX('Game Records'!$V:$V,$H504))),NOT(ISFORMULA(INDEX('Game Records'!$W:$W,$H504))),NOT(ISFORMULA(INDEX('Game Records'!$X:$X,$H504))),NOT(ISFORMULA(INDEX('Game Records'!$Y:$Y,$H504))),NOT(ISFORMULA(INDEX('Game Records'!$Z:$Z,$H504)))),"Formula columns missing; ","")&IF(INDEX('Game Records'!$B:$B,$H504)="","Start Date; ","")&IF(INDEX('Game Records'!$C:$C,$H504)="","End Date; ","")&IF(AND(INDEX('Game Records'!$U:$U,$H504)<>"Subscription",INDEX('Game Records'!$U:$U,$H504)<>"Free Game",INDEX('Game Records'!$U:$U,$H504)<>"Disqualified — Free Game",OR(INDEX('Game Records'!$D:$D,$H504)="",LOWER(INDEX('Game Records'!$D:$D,$H504)&"")="n/a")),"Entry Mode; ","")&IF(AND(INDEX('Game Records'!$U:$U,$H504)<>"Subscription",INDEX('Game Records'!$U:$U,$H504)<>"Free Game",INDEX('Game Records'!$U:$U,$H504)<>"Disqualified — Free Game",OR(INDEX('Game Records'!$E:$E,$H504)="",LOWER(INDEX('Game Records'!$E:$E,$H504)&"")="n/a")),"Game Type; ","")&IF(INDEX('Game Records'!$F:$F,$H504)="","Payment Type; ","")&IF(AND(INDEX('Game Records'!$U:$U,$H504)<>"Subscription",INDEX('Game Records'!$U:$U,$H504)<>"Free Game",INDEX('Game Records'!$U:$U,$H504)<>"Disqualified — Free Game",INDEX('Game Records'!$G:$G,$H504)=""),"Gross Pot; ","")&IF(AND(INDEX('Game Records'!$U:$U,$H504)<>"Free Game",INDEX('Game Records'!$U:$U,$H504)<>"Disqualified — Free Game",INDEX('Game Records'!$H:$H,$H504)=""),"Entry Fee; ","")&IF(AND(INDEX('Game Records'!$U:$U,$H504)<>"Subscription",INDEX('Game Records'!$U:$U,$H504)<>"Free Game",INDEX('Game Records'!$U:$U,$H504)<>"Disqualified — Free Game",INDEX('Game Records'!$I:$I,$H504)=""),"Eligible Players; ","")&IF(AND(INDEX('Game Records'!$U:$U,$H504)<>"Subscription",INDEX('Game Records'!$U:$U,$H504)<>"Free Game",INDEX('Game Records'!$U:$U,$H504)<>"Disqualified — Free Game",INDEX('Game Records'!$J:$J,$H504)=""),"Total Players; ","")&IF(AND(LOWER(INDEX('Game Records'!$D:$D,$H504)&"")="finalized",LOWER(INDEX('Game Records'!$L:$L,$H504)&"")<>"yes",INDEX('Game Records'!$U:$U,$H504)<>"Subscription",INDEX('Game Records'!$U:$U,$H504)<>"Free Game",INDEX('Game Records'!$U:$U,$H504)<>"Disqualified — Free Game",INDEX('Game Records'!$K:$K,$H504)=""),"Final Earned; ","")&IF(AND(LOWER(INDEX('Game Records'!$D:$D,$H504)&"")="finalized",INDEX('Game Records'!$U:$U,$H504)<>"Subscription",INDEX('Game Records'!$U:$U,$H504)<>"Free Game",INDEX('Game Records'!$U:$U,$H504)<>"Disqualified — Free Game",OR(INDEX('Game Records'!$L:$L,$H504)="",LOWER(INDEX('Game Records'!$L:$L,$H504)&"")="n/a")),"Disqualified Status; ","")&IF(AND(OR(LOWER(TRIM(INDEX('Game Records'!$F:$F,$H504)&""))="free game",INDEX('Game Records'!$U:$U,$H504)="Free Game",INDEX('Game Records'!$U:$U,$H504)="Disqualified — Free Game"),N(INDEX('Game Records'!$H:$H,$H504))<>0),"Free Game has a non-zero Entry Fee. Free Game records require a $0 Entry Fee; ","")) | G504: =IF($H504="","",IFERROR(INDEX('Game Records'!$M:$M,$H504),"")) | H504: =IF($H503="","",IFERROR(MATCH(1,INDEX((ROW('Game Records'!$U$5:$U$504)>$H503)*(('Game Records'!$A$5:$A$504<>"")+('Game Records'!$B$5:$B$504<>"")+('Game Records'!$C$5:$C$504<>"")+('Game Records'!$D$5:$D$504<>"")+('Game Records'!$E$5:$E$504<>"")+('Game Records'!$F$5:$F$504<>"")+('Game Records'!$G$5:$G$504<>"")+('Game Records'!$H$5:$H$504<>"")+('Game Records'!$I$5:$I$504<>"")+('Game Records'!$J$5:$J$504<>"")+('Game Records'!$K$5:$K$504<>"")+('Game Records'!$L$5:$L$504<>"")+('Game Records'!$M$5:$M$504<>"")>0)*('Game Records'!$U$5:$U$504<>"Subscription"),0),0)+4,""))

Sheet Summary
A1: StepCat Live Summary Dashboard — v252
A3: Game Result | B3: Game Count | C3: Share of Paid Games | D3: Cash / Credit Total | E3: Amount | F3: What It Represents
A4: Profit Games | B4: =COUNTIF('Game Records'!$U$5:$U$504,"Profit") -> 0 | C4: =IF($B$7=0,0,B4/$B$7) -> 0 | D4: Running Net Game Profit | E4: =Instructions!$B$29+SUM('Game Records'!$W$5:$W$504) -> 0 | F4: Gross profit minus lost entry fees
A5: Draw Games | B5: =COUNTIF('Game Records'!$U$5:$U$504,"Draw") -> 0 | C5: =IF($B$7=0,0,B5/$B$7) -> 0 | D5: Gross Profit Earned | E5: =SUM('Game Records'!$Q$5:$Q$504) -> 0 | F5: Positive paid-game cash profit only, before lost fees or membership costs
A6: Disqualified Games | B6: =COUNTIF('Game Records'!$U$5:$U$504,"Disqualified") -> 0 | C6: =IF($B$7=0,0,B6/$B$7) -> 0 | D6: Total Lost Entry Fees | E6: =SUM('Game Records'!$S$5:$S$504) -> 0 | F6: Full entry fees lost from disqualification
A7: Current Workbook Paid Games | B7: =SUM(B4:B6) -> 0 | C7: =IF(B7=0,0,1) -> 0 | D7: Membership Fees | E7: =Instructions!$B$30+SUMIFS('Game Records'!$H$5:$H$504,'Game Records'!$U$5:$U$504,"Subscription") -> 0 | F7: Annual membership cost, tracked as a separate non-game expense
A8: Prior Completed Games (reference) | B8: =Instructions!$B$31 -> 0 | D8: Actual Running Net Profit | E8: =E4-E7 -> 0 | F8: Running cash net game profit minus current and carried-over membership costs
A9: Completed Free Games (separate credit) | B9: =COUNTIFS('Game Records'!$D$5:$D$504,"Finalized",'Game Records'!$U$5:$U$504,"Free Game")+COUNTIFS('Game Records'!$D$5:$D$504,"Finalized",'Game Records'!$U$5:$U$504,"Disqualified — Free Game") -> 0 | C9: Separate | D9: Free Game Chips Earned | E9: =SUMIFS('Game Records'!$K$5:$K$504,'Game Records'!$D$5:$D$504,"Finalized",'Game Records'!$U$5:$U$504,"Free Game",'Game Records'!$K$5:$K$504,"<>",'Game Records'!$K$5:$K$504,">=0") -> 0 | F9: Non-cash chips/game credit earned from Free Games; excluded from every cash profit total
A31: Running Tally | B31: Exact Count | C31: Share
A32: Profit | B32: =B4 -> 0 | C32: =C4 -> 0
A33: Draw | B33: =B5 -> 0 | C33: =C5 -> 0
A34: Disqualified / Lost Entry Fee | B34: =B6 -> 0 | C34: =C6 -> 0
A35: Free Game (separate credit) | B35: =B9 -> 0 | C35: Separate
A36: Total Paid Games | B36: =B7 -> 0 | C36: =C7 -> 0

Sheet Game Comparisons
A1: Paid Game Performance — v252
A2: Compares finalized paid Member, Non-Member, and Unclassified games. Estimate rows, subscriptions, and Free Games are excluded; Free Games appear in the separate section below.
A3: Metric | B3: Member | C3: Non-Member | D3: Unclassified | E3: All Paid Games
A4: Completed Games | B4: =COUNTIFS('Game Records'!$E$5:$E$504,"Member",'Game Records'!$U$5:$U$504,"<>Estimate",'Game Records'!$U$5:$U$504,"<>Subscription",'Game Records'!$U$5:$U$504,"<>Free Game",'Game Records'!$U$5:$U$504,"<>Disqualified — Free Game",'Game Records'!$U$5:$U$504,"<>") | C4: =COUNTIFS('Game Records'!$E$5:$E$504,"Non-Member",'Game Records'!$U$5:$U$504,"<>Estimate",'Game Records'!$U$5:$U$504,"<>Subscription",'Game Records'!$U$5:$U$504,"<>Free Game",'Game Records'!$U$5:$U$504,"<>Disqualified — Free Game",'Game Records'!$U$5:$U$504,"<>") | D4: =SUMPRODUCT(('Game Records'!$U$5:$U$504<>"")*('Game Records'!$U$5:$U$504<>"Estimate")*('Game Records'!$U$5:$U$504<>"Subscription")*('Game Records'!$U$5:$U$504<>"Free Game")*('Game Records'!$U$5:$U$504<>"Disqualified — Free Game")*('Game Records'!$E$5:$E$504<>"Member")*('Game Records'!$E$5:$E$504<>"Non-Member")) | E4: =SUM(B4:D4) -> 0
A5: Profit Games | B5: =COUNTIFS('Game Records'!$E$5:$E$504,"Member",'Game Records'!$U$5:$U$504,"Profit") -> 0 | C5: =COUNTIFS('Game Records'!$E$5:$E$504,"Non-Member",'Game Records'!$U$5:$U$504,"Profit") -> 0 | D5: =SUMPRODUCT(('Game Records'!$U$5:$U$504="Profit")*('Game Records'!$E$5:$E$504<>"Member")*('Game Records'!$E$5:$E$504<>"Non-Member")) -> 0 | E5: =SUM(B5:D5) -> 0
A6: Profit Rate | B6: =IF(B4=0,0,B5/B4) -> 0 | C6: =IF(C4=0,0,C5/C4) -> 0 | D6: =IF(D4=0,0,D5/D4) -> 0 | E6: =IF(E4=0,0,E5/E4) -> 0
A7: Draw Rate | B7: =IF(B4=0,0,COUNTIFS('Game Records'!$E$5:$E$504,"Member",'Game Records'!$U$5:$U$504,"Draw")/B4) -> 0 | C7: =IF(C4=0,0,COUNTIFS('Game Records'!$E$5:$E$504,"Non-Member",'Game Records'!$U$5:$U$504,"Draw")/C4) -> 0 | D7: =IF(D4=0,0,SUMPRODUCT(('Game Records'!$U$5:$U$504="Draw")*('Game Records'!$E$5:$E$504<>"Member")*('Game Records'!$E$5:$E$504<>"Non-Member"))/D4) -> 0 | E7: =IF(E4=0,0,COUNTIF('Game Records'!$U$5:$U$504,"Draw")/E4) -> 0
A8: Disqualification Rate | B8: =IF(B4=0,0,COUNTIFS('Game Records'!$E$5:$E$504,"Member",'Game Records'!$U$5:$U$504,"Disqualified")/B4) -> 0 | C8: =IF(C4=0,0,COUNTIFS('Game Records'!$E$5:$E$504,"Non-Member",'Game Records'!$U$5:$U$504,"Disqualified")/C4) -> 0 | D8: =IF(D4=0,0,SUMPRODUCT(('Game Records'!$U$5:$U$504="Disqualified")*('Game Records'!$E$5:$E$504<>"Member")*('Game Records'!$E$5:$E$504<>"Non-Member"))/D4) -> 0 | E8: =IF(E4=0,0,COUNTIF('Game Records'!$U$5:$U$504,"Disqualified")/E4) -> 0
A9: Average Net Profit | B9: =IF(B4=0,0,B11/B4) -> 0 | C9: =IF(C4=0,0,C11/C4) -> 0 | D9: =IF(D4=0,0,D11/D4) -> 0 | E9: =IF(E4=0,0,E11/E4) -> 0
A10: Average ROI | B10: =IF(B4=0,0,SUMIFS('Game Records'!$T$5:$T$504,'Game Records'!$E$5:$E$504,"Member",'Game Records'!$U$5:$U$504,"<>Estimate",'Game Records'!$U$5:$U$504,"<>Subscription",'Game Records'!$U$5:$U$504,"<>Free Game",'Game Records'!$U$5:$U$504,"<>Disqualified — Free Game")/B4) | C10: =IF(C4=0,0,SUMIFS('Game Records'!$T$5:$T$504,'Game Records'!$E$5:$E$504,"Non-Member",'Game Records'!$U$5:$U$504,"<>Estimate",'Game Records'!$U$5:$U$504,"<>Subscription",'Game Records'!$U$5:$U$504,"<>Free Game",'Game Records'!$U$5:$U$504,"<>Disqualified — Free Game")/C4) | D10: =IF(D4=0,0,SUMIFS('Game Records'!$T$5:$T$504,'Game Records'!$U$5:$U$504,"<>Estimate",'Game Records'!$U$5:$U$504,"<>Subscription",'Game Records'!$U$5:$U$504,"<>Free Game",'Game Records'!$U$5:$U$504,"<>Disqualified — Free Game",'Game Records'!$E$5:$E$504,"<>Member",'Game Records'!$E$5:$E$504,"<>Non-Member")/D4) | E10: =IF(E4=0,0,SUMIFS('Game Records'!$T$5:$T$504,'Game Records'!$U$5:$U$504,"<>Estimate",'Game Records'!$U$5:$U$504,"<>Subscription",'Game Records'!$U$5:$U$504,"<>Free Game",'Game Records'!$U$5:$U$504,"<>Disqualified — Free Game")/E4)
A11: Total Net Profit | B11: =SUMIFS('Game Records'!$W$5:$W$504,'Game Records'!$E$5:$E$504,"Member",'Game Records'!$U$5:$U$504,"<>Estimate",'Game Records'!$U$5:$U$504,"<>Subscription",'Game Records'!$U$5:$U$504,"<>Free Game",'Game Records'!$U$5:$U$504,"<>Disqualified — Free Game") | C11: =SUMIFS('Game Records'!$W$5:$W$504,'Game Records'!$E$5:$E$504,"Non-Member",'Game Records'!$U$5:$U$504,"<>Estimate",'Game Records'!$U$5:$U$504,"<>Subscription",'Game Records'!$U$5:$U$504,"<>Free Game",'Game Records'!$U$5:$U$504,"<>Disqualified — Free Game") | D11: =SUMIFS('Game Records'!$W$5:$W$504,'Game Records'!$U$5:$U$504,"<>Estimate",'Game Records'!$U$5:$U$504,"<>Subscription",'Game Records'!$U$5:$U$504,"<>Free Game",'Game Records'!$U$5:$U$504,"<>Disqualified — Free Game",'Game Records'!$E$5:$E$504,"<>Member",'Game Records'!$E$5:$E$504,"<>Non-Member") | E11: =SUMIFS('Game Records'!$W$5:$W$504,'Game Records'!$U$5:$U$504,"<>Estimate",'Game Records'!$U$5:$U$504,"<>Subscription",'Game Records'!$U$5:$U$504,"<>Free Game",'Game Records'!$U$5:$U$504,"<>Disqualified — Free Game")
A12: Unclassified Games | B12: 0 | C12: 0 | D12: =D4 -> 0 | E12: =D4 -> 0
A15: Free Game Chip Performance
A16: Free Games are completed step challenges that award non-cash chips/game credit. They remain separate from paid-game ROI, paid-result averages, and all cash profit totals.
A17: Metric | B17: Free Game Chips | C17: What It Represents
A18: Completed Free Games | B18: =COUNTIFS('Game Records'!$D$5:$D$504,"Finalized",'Game Records'!$U$5:$U$504,"Free Game")+COUNTIFS('Game Records'!$D$5:$D$504,"Finalized",'Game Records'!$U$5:$U$504,"Disqualified — Free Game") -> 0 | C18: All finalized Free Game and Disqualified — Free Game records.
A19: Non-disqualified Free Games | B19: =COUNTIFS('Game Records'!$D$5:$D$504,"Finalized",'Game Records'!$U$5:$U$504,"Free Game") -> 0 | C19: Free Games completed without disqualification.
A20: Disqualified Free Games | B20: =COUNTIFS('Game Records'!$D$5:$D$504,"Finalized",'Game Records'!$U$5:$U$504,"Disqualified — Free Game") -> 0 | C20: Free Games whose disqualification status was recorded.
A21: Disqualification Rate | B21: =IF(B18=0,0,B20/B18) -> 0 | C21: Disqualified Free Games divided by all completed Free Games.
A22: Average Chips Earned | B22: =IF((COUNTIFS('Game Records'!$D$5:$D$504,"Finalized",'Game Records'!$U$5:$U$504,"Free Game",'Game Records'!$K$5:$K$504,"<>",'Game Records'!$K$5:$K$504,">=0")+COUNTIFS('Game Records'!$D$5:$D$504,"Finalized",'Game Records'!$U$5:$U$504,"Disqualified — Free Game"))=0,0,(SUMIFS('Game Records'!$K$5:$K$504,'Game Records'!$D$5:$D$504,"Finalized",'Game Records'!$U$5:$U$504,"Free Game",'Game Records'!$K$5:$K$504,"<>",'Game Records'!$K$5:$K$504,">=0"))/(COUNTIFS('Game Records'!$D$5:$D$504,"Finalized",'Game Records'!$U$5:$U$504,"Free Game",'Game Records'!$K$5:$K$504,"<>",'Game Records'!$K$5:$K$504,">=0")+COUNTIFS('Game Records'!$D$5:$D$504,"Finalized",'Game Records'!$U$5:$U$504,"Disqualified — Free Game"))) -> 0 | C22: Average of recorded chip amounts only; unknown blanks are excluded, while recorded 0.00-chip results remain included.
A23: Total Chips Earned | B23: =SUMIFS('Game Records'!$K$5:$K$504,'Game Records'!$D$5:$D$504,"Finalized",'Game Records'!$U$5:$U$504,"Free Game",'Game Records'!$K$5:$K$504,"<>",'Game Records'!$K$5:$K$504,">=0") -> 0 | C23: Combined non-cash chips/game credit; excluded from overall cash running net profit.
A24: Average Eliminated Players | B24: =IF((COUNTIFS('Game Records'!$D$5:$D$504,"Finalized",'Game Records'!$U$5:$U$504,"Free Game",'Game Records'!$I$5:$I$504,"<>",'Game Records'!$I$5:$I$504,">=0",'Game Records'!$J$5:$J$504,"<>",'Game Records'!$J$5:$J$504,">=0")+COUNTIFS('Game Records'!$D$5:$D$504,"Finalized",'Game Records'!$U$5:$U$504,"Disqualified — Free Game",'Game Records'!$I$5:$I$504,"<>",'Game Records'!$I$5:$I$504,">=0",'Game Records'!$J$5:$J$504,"<>",'Game Records'!$J$5:$J$504,">=0"))=0,0,(SUMIFS('Game Records'!$X$5:$X$504,'Game Records'!$D$5:$D$504,"Finalized",'Game Records'!$U$5:$U$504,"Free Game")+SUMIFS('Game Records'!$X$5:$X$504,'Game Records'!$D$5:$D$504,"Finalized",'Game Records'!$U$5:$U$504,"Disqualified — Free Game"))/(COUNTIFS('Game Records'!$D$5:$D$504,"Finalized",'Game Records'!$U$5:$U$504,"Free Game",'Game Records'!$I$5:$I$504,"<>",'Game Records'!$I$5:$I$504,">=0",'Game Records'!$J$5:$J$504,"<>",'Game Records'!$J$5:$J$504,">=0")+COUNTIFS('Game Records'!$D$5:$D$504,"Finalized",'Game Records'!$U$5:$U$504,"Disqualified — Free Game",'Game Records'!$I$5:$I$504,"<>",'Game Records'!$I$5:$I$504,">=0",'Game Records'!$J$5:$J$504,"<>",'Game Records'!$J$5:$J$504,">=0"))) -> 0 | C24: Average eliminated-player count when player totals are available.
A25: Average Elimination Rate | B25: =IF((COUNTIFS('Game Records'!$D$5:$D$504,"Finalized",'Game Records'!$U$5:$U$504,"Free Game",'Game Records'!$I$5:$I$504,"<>",'Game Records'!$I$5:$I$504,">=0",'Game Records'!$J$5:$J$504,"<>",'Game Records'!$J$5:$J$504,">=0")+COUNTIFS('Game Records'!$D$5:$D$504,"Finalized",'Game Records'!$U$5:$U$504,"Disqualified — Free Game",'Game Records'!$I$5:$I$504,"<>",'Game Records'!$I$5:$I$504,">=0",'Game Records'!$J$5:$J$504,"<>",'Game Records'!$J$5:$J$504,">=0"))=0,0,(SUMIFS('Game Records'!$Y$5:$Y$504,'Game Records'!$D$5:$D$504,"Finalized",'Game Records'!$U$5:$U$504,"Free Game")+SUMIFS('Game Records'!$Y$5:$Y$504,'Game Records'!$D$5:$D$504,"Finalized",'Game Records'!$U$5:$U$504,"Disqualified — Free Game"))/(COUNTIFS('Game Records'!$D$5:$D$504,"Finalized",'Game Records'!$U$5:$U$504,"Free Game",'Game Records'!$I$5:$I$504,"<>",'Game Records'!$I$5:$I$504,">=0",'Game Records'!$J$5:$J$504,"<>",'Game Records'!$J$5:$J$504,">=0")+COUNTIFS('Game Records'!$D$5:$D$504,"Finalized",'Game Records'!$U$5:$U$504,"Disqualified — Free Game",'Game Records'!$I$5:$I$504,"<>",'Game Records'!$I$5:$I$504,">=0",'Game Records'!$J$5:$J$504,"<>",'Game Records'!$J$5:$J$504,">=0"))) -> 0 | C25: Average elimination rate when player totals are available.
A26: Average ROI | B26: N/A | C26: N/A because Free Games have a $0.00 Entry Fee.
A27: All Completed Games | B27: =E4+B18 -> 0 | C27: All Paid Games plus completed Free Games; Subscription rows are excluded.

Sheet Best Results
A1: Best Results — Live Reference Table — v252
A2: Finalized game results only. Clear no-data messages appear until qualifying records exist.
A3: Metric | B3: Game | C3: Value | D3: Meaning
A4: Highest Net Profit | B4: =IF(COUNTIF('Game Records'!$U$5:$U$504,"Profit")=0,"No finalized paid games yet",IFERROR(INDEX('Game Records'!$A$5:$A$504,MATCH(MAX('Game Records'!$W$5:$W$504),'Game Records'!$W$5:$W$504,0)),"No finalized paid games yet")) | C4: =IF(COUNTIF('Game Records'!$U$5:$U$504,"Profit")=0,"N/A",MAX('Game Records'!$W$5:$W$504)) | D4: Largest positive game result
A5: Highest ROI | B5: =IF(COUNTIF('Game Records'!$U$5:$U$504,"Profit")=0,"No finalized paid games yet",IFERROR(INDEX('Game Records'!$A$5:$A$504,MATCH(MAX('Game Records'!$T$5:$T$504),'Game Records'!$T$5:$T$504,0)),"No finalized paid games yet")) | C5: =IF(COUNTIF('Game Records'!$U$5:$U$504,"Profit")=0,"N/A",MAX('Game Records'!$T$5:$T$504)) | D5: Best return on Entry Fee
A6: Largest Lost Entry Fee | B6: =IF(COUNTIF('Game Records'!$U$5:$U$504,"Disqualified")=0,"No paid disqualifications yet",IFERROR(INDEX('Game Records'!$A$5:$A$504,MATCH(MAX('Game Records'!$S$5:$S$504),'Game Records'!$S$5:$S$504,0)),"No paid disqualifications yet")) | C6: =IF(COUNTIF('Game Records'!$U$5:$U$504,"Disqualified")=0,"N/A",MAX('Game Records'!$S$5:$S$504)) | D6: Largest full-entry loss
A7: Lowest Elimination Rate | B7: =IF(COUNT('Game Records'!$Y$5:$Y$504)=0,"No elimination data yet",IFERROR(INDEX('Game Records'!$A$5:$A$504,MATCH(MINIFS('Game Records'!$Y$5:$Y$504,'Game Records'!$Y$5:$Y$504,">0"),'Game Records'!$Y$5:$Y$504,0)),"No elimination data yet")) | C7: =IF(COUNT('Game Records'!$Y$5:$Y$504)=0,"N/A",MINIFS('Game Records'!$Y$5:$Y$504,'Game Records'!$Y$5:$Y$504,">0")) | D7: Best recorded elimination rate
A8: Longest Challenge | B8: =IF(COUNT('Game Records'!$V$5:$V$504)=0,"No dated games yet",IFERROR(INDEX('Game Records'!$A$5:$A$504,MATCH(MAX('Game Records'!$V$5:$V$504),'Game Records'!$V$5:$V$504,0)),"No dated games yet")) | C8: =IF(COUNT('Game Records'!$V$5:$V$504)=0,"N/A",MAX('Game Records'!$V$5:$V$504)) | D8: Most weeks completed
